Workbook

Sheet Summary
A1: TEST PLAN SUMMARY
A2: partner-platform-prd-v1.8 | Generated: 2026-05-20
A3: No. | B3: BLOCK | C3: TOTAL | D3: COMPLETED | E3: PASSED | G3: FAILED | I3: NOT STARTED | K3: IN PROGRESS | M3: BLOCKED
E4: Number | F4: Percent | G4: Number | H4: Percent | I4: Number | J4: Percent | K4: Number | L4: Percent | M4: Number | N4: Percent | O4: COMMENT | P4: OWNER
A5: 1 | B5: Partner Platform | C5: =COUNTA('Partner Platform'!I14:I1070) -> 305 | D5: =(E5+G5)/C5 -> 0.53442623 | E5: =COUNTIF('Partner Platform'!I14:I1070,"PASSED") -> 151 | F5: =E5/C5 -> 0.49508197 | G5: =COUNTIF('Partner Platform'!I14:I1070,"FAILED") -> 12 | H5: =G5/C5 -> 0.039344262 | I5: =COUNTIF('Partner Platform'!I14:I1070,"NOT_STARTED") -> 2 | J5: =I5/C5 -> 0.006557377 | K5: =COUNTIF('Partner Platform'!I14:I1070,"IN_PROGRESS") -> 0 | L5: =K5/C5 -> 0 | M5: =COUNTIF('Partner Platform'!I14:I1070,"BLOCKED") -> 140 | N5: =M5/C5 -> 0.45901639 | P5: Trang Le
B6: TOTAL | C6: =SUM(C5) -> 305 | D6: =(E6+G6)/C6 -> 0.53442623 | E6: =SUM(E5) -> 151 | F6: =E6/C6 -> 0.49508197 | G6: =SUM(G5) -> 12 | H6: =G6/C6 -> 0.039344262 | I6: =SUM(H5) -> 0.039344262 | J6: =I6/C6 -> 0.00012899758 | K6: =SUM(K5) -> 0 | L6: =K6/C6 -> 0 | M6: =SUM(M5) -> 140 | N6: =M6/C6 -> 0.45901639
A22: Status | B22: Count
A23: Pass | B23: =COUNTIF('Partner Platform'!H:H,"Pass") -> 0
A24: Fail | B24: =COUNTIF('Partner Platform'!H:H,"Fail") -> 0
A25: Not Started | B25: =COUNTIF('Partner Platform'!H:H,"Not Started") -> 0
A26: In Progress | B26: =COUNTIF('Partner Platform'!H:H,"In Progress") -> 0
A27: Type | B27: Count
A28: Type | B28: Count
A29: UI | B29: =COUNTA('Partner Platform'!B87:B106) -> 8
A30: API | B30: =COUNTA('Partner Platform'!A287:A368) -> 2
A31: Coverage | B31: Count
A32: Automation | B32: Count
A33: Automated | B33: 138
A34: Manual Only | B34: 6
A36: Priority | B36: Count
A37: P1 | B37: =COUNTIF('Partner Platform'!F:F,"P1") -> 0
A38: P2 | B38: =COUNTIF('Partner Platform'!F:F,"P2") -> 0
A39: P3 | B39: =COUNTIF('Partner Platform'!F:F,"P3") -> 0
A40: P4 | B40: =COUNTIF('Partner Platform'!F:F,"P4") -> 0

Sheet Partner Platform
A1: PARTNER PLATFORM — MODULE STATUS SUMMARY
A2: Item | B2: Description | C2: Summary | D2: Manual | E2: Automation
A3: TOTAL | B3: Total number of tests | C3: =SUM(C4:C8) -> 305 | D3: =SUM(D4:D8) -> 305 | E3: =SUM(E4:E8) -> 163
A4: PASSED | B4: Number of tests PASSED | C4: =COUNTIF('Partner Platform'!I14:I1070,"PASSED") -> 151 | D4: =COUNTIF('Partner Platform'!J14:J1070,"PASSED") -> 0 | E4: =COUNTIFS('Partner Platform'!L14:L1070,"PASSED",'Partner Platform'!K14:K1070,"YES") -> 151
A5: FAILED | B5: Number of tests FAILED | C5: =COUNTIF('Partner Platform'!I14:I1070,"FAILED") -> 12 | D5: =COUNTIF('Partner Platform'!J14:J1070,"FAILED") -> 0 | E5: =COUNTIFS('Partner Platform'!L14:L1070,"FAILED",'Partner Platform'!K14:K1070,"YES") -> 12
A6: NOT_STARTED | B6: Number of tests that have not been started | C6: =COUNTIF('Partner Platform'!I14:I1070,"NOT_STARTED") -> 2 | D6: =COUNTIF('Partner Platform'!J14:J1070,"NOT_STARTED") -> 165 | E6: =COUNTIFS('Partner Platform'!L14:L1070,"NOT_STARTED",'Partner Platform'!K14:K1070,"YES") -> 0
A7: IN_PROGRESS | B7: Number of tests currently being tested | C7: =COUNTIF('Partner Platform'!I14:I1070,"IN_PROGRESS") -> 0 | D7: =COUNTIF('Partner Platform'!J14:J1070,"IN_PROGRESS") -> 0 | E7: =COUNTIFS('Partner Platform'!L14:L1070,"IN_PROGRESS",'Partner Platform'!K14:K1070,"YES") -> 0
A8: BLOCKED | B8: Tests that could not be executed | C8: =COUNTIF('Partner Platform'!I14:I1070,"BLOCKED") -> 140 | D8: =COUNTIF('Partner Platform'!J14:J1070,"BLOCKED") -> 140 | E8: =COUNTIFS('Partner Platform'!L14:L1070,"BLOCKED",'Partner Platform'!K14:K1070,"YES") -> 0
A12: Main Section | B12: Main Feature/Function | C12: Test Case Name | D12: Test Case ID | E12: Action | F12: Test Type | G12: Priority | H12: Severity | I12: Status | J12: Manual Status | K12: Auto | L12: Automation Status | M12: Requirement Ref | N12: Docs Refer | O12: Bug ID | P12: Owner | Q12: Note | R12: Test Description | S12: Test Step | T12: Primary Ref
A13: UI
A14: Commissions | B14: Commissions & Payouts | C14: PARTNER_UI_COMMISSIONS_001 | D14: 12060301 | E14: Calculate - Type estimated annual value - Commission projection updates live | F14: Functional | G14: P1 | H14: Critical | I14: =IF(K14="No",J14,IF(OR(J14="FAILED",L14="FAILED"),"FAILED",IF(OR(J14="PASSED",L14="PASSED"),"PASSED",IF(OR(J14="IN_PROGRESS",L14="IN_PROGRESS"),"IN_PROGRESS",IF(OR(J14="BLOCKED",L14="BLOCKED"),"BLOCKED","NOT_STARTED"))))) -> BLOCKED | J14: BLOCKED | K14: NO | L14: NOT_STARTED | M14: §4.4, Risk R2 | N14: partner-platform-prd-v1.8.md | P14: Trang Le | Q14: Type estimated annual value → commission projection updates live (in the deal-register wizard, step 2). Blocked on test data (verified live 2026-07-27): the test partner has no commission rate configured — /resources shows "Commission Rates: No rates configured yet. Contact your programme manager." The projection is Total rate × Estimated ACV, so with an empty rate it computes no value (probed: changing inputs shows no $ projection). Also the ACV isn't a direct input — "Estimated ACV / Rate / Projected commission" are collapsible display sections in the wizard (ACV appears derived from plan × seats), so there's nothing to "type" for a live rate×ACV calc. Unblock when a commission rate is configured for the test partner (via SA rate-table) so the projection produces a verifiable value. | T14: 4.4
C15: PARTNER_UI_COMMISSIONS_002 | D15: 12060302 | E15: View - Commissions page - Earned pending and paid totals are visible | F15: Functional | G15: P1 | H15: Major | I15: =IF(K15="No",J15,IF(OR(J15="FAILED",L15="FAILED"),"FAILED",IF(OR(J15="PASSED",L15="PASSED"),"PASSED",IF(OR(J15="IN_PROGRESS",L15="IN_PROGRESS"),"IN_PROGRESS",IF(OR(J15="BLOCKED",L15="BLOCKED"),"BLOCKED","NOT_STARTED"))))) -> PASSED | J15: NOT_STARTED | K15: YES | L15: PASSED | M15: §4.7 | N15: partner-platform-prd-v1.8.md | P15: Trang Le | Q15: PASSED (TC 12060402), verified 2026-07-28. Dashboard renders 3 KPI cards (Total pipeline ACV / Commission YTD / Active Tenants, each with a value) + 4 sections (Tier & Performance, Territory Assignments, Action Required, Pipeline Snapshot). Read-only; empty data shows "No Data Found". First DASHBOARD content test (establishes DashboardPage). Negative N/A, Idempotency N/A. | R15: Open the Commissions page and confirm the earned/pending/paid summary totals + ledger status tabs render. Read-only: works with an empty ledger (amounts may be $0) — verifies the page structure, not specific data. | S15: **Setup (precondition):** Log in as the channel-partner user; open `/commissions` via the shell and wait for the "Commissions" READY_MARKER; let the data settle. **Test Steps:** 1. The 4 summary totals render, each with a $ amount. → Expected: **Pending Payout**, **Paid YTD**, **Total Earned**, **Clawback Risk** cards each show a $ value (e.g. $0 on an empty ledger). 2. All ledger status tabs are visible. → Expected: **All / Earned / Pending / Approved / Paid / Disputed / Clawback** tabs render. **Expected (overall):** The Commissions page renders its summary totals + all ledger tabs (independent of how many commissions exist). | T15: 4.7
C16: PARTNER_UI_COMMISSIONS_003 | D16: 12060303 | E16: Trace - Commission row detail - Deal close to payment details are visible | F16: Functional | G16: P1 | H16: Major | I16: =IF(K16="No",J16,IF(OR(J16="FAILED",L16="FAILED"),"FAILED",IF(OR(J16="PASSED",L16="PASSED"),"PASSED",IF(OR(J16="IN_PROGRESS",L16="IN_PROGRESS"),"IN_PROGRESS",IF(OR(J16="BLOCKED",L16="BLOCKED"),"BLOCKED","NOT_STARTED"))))) -> BLOCKED | J16: BLOCKED | K16: NO | L16: NOT_STARTED | M16: §4.7, §5.6 | N16: partner-platform-prd-v1.8.md | P16: Trang Le | Q16: The commission ledger is **empty** — the test partner has no **Won** deals, so no commission rows exist ("No commissions yet"). Nothing to open / verify. Data-dependency chain: rate configured (SA_PARTNER_MODULE_009, not deployed) → deal approved (SA deal queue blocked by BUG-025) → deal Won → commission row. Unblock once at least one commission exists in the ledger. | T16: 4.7
C17: PARTNER_UI_COMMISSIONS_004 | D17: 12060304 | E17: Submit - Commission dispute - Dispute is created from one text field | F17: Functional | G17: P1 | H17: Major | I17: =IF(K17="No",J17,IF(OR(J17="FAILED",L17="FAILED"),"FAILED",IF(OR(J17="PASSED",L17="PASSED"),"PASSED",IF(OR(J17="IN_PROGRESS",L17="IN_PROGRESS"),"IN_PROGRESS",IF(OR(J17="BLOCKED",L17="BLOCKED"),"BLOCKED","NOT_STARTED"))))) -> BLOCKED | J17: BLOCKED | K17: NO | L17: NOT_STARTED | M17: §4.7 | N17: partner-platform-prd-v1.8.md | P17: Trang Le | Q17: Same as _003 — no commission rows in the ledger to dispute (partner has no Won deals → empty ledger). Needs a real commission entry first (rate → approved deal → Won). | T17: 4.7
C18: PARTNER_UI_COMMISSIONS_005 | D18: 12060305 | E18: Submit - Product failure waiver - Evidence can be linked and request submitted | F18: Functional | G18: P1 | H18: Critical | I18: =IF(K18="No",J18,IF(OR(J18="FAILED",L18="FAILED"),"FAILED",IF(OR(J18="PASSED",L18="PASSED"),"PASSED",IF(OR(J18="IN_PROGRESS",L18="IN_PROGRESS"),"IN_PROGRESS",IF(OR(J18="BLOCKED",L18="BLOCKED"),"BLOCKED","NOT_STARTED"))))) -> BLOCKED | J18: BLOCKED | K18: NO | L18: NOT_STARTED | M18: §4.7, §5.3 | N18: partner-platform-prd-v1.8.md | P18: Trang Le | Q18: Same as _003/_004 — no clawback-eligible commission row exists (empty ledger). Needs a commission in a clawback-eligible state first. | T18: 4.7
C19: PARTNER_UI_COMMISSIONS_006 | D19: 12060306 | E19: Approve - Commission payout over $10K - Two-eye approval is enforced | F19: Security | G19: P1 | H19: Critical | I19: =IF(K19="No",J19,IF(OR(J19="FAILED",L19="FAILED"),"FAILED",IF(OR(J19="PASSED",L19="PASSED"),"PASSED",IF(OR(J19="IN_PROGRESS",L19="IN_PROGRESS"),"IN_PROGRESS",IF(OR(J19="BLOCKED",L19="BLOCKED"),"BLOCKED","NOT_STARTED"))))) -> BLOCKED | J19: BLOCKED | K19: NO | L19: NOT_STARTED | M19: §5.6, §7.5 | N19: partner-platform-prd-v1.8.md | P19: Trang Le | Q19: Needs (a) a payout > $10K pending approval — which requires a Won deal → commission → payout (empty ledger, blocked as _003), and (b) the two-eye approval UI (SA-side, design PN012) which is **not deployed** on staging. Unblock when both the payout data + the two-eye approval UI exist. | T19: 5.6
C20: PARTNER_UI_COMMISSIONS_007 | D20: 12060307 | E20: Display - Clawback notification - Policy terms and product-failure waiver path are visible | F20: Functional | G20: P1 | H20: Major | I20: =IF(K20="No",J20,IF(OR(J20="FAILED",L20="FAILED"),"FAILED",IF(OR(J20="PASSED",L20="PASSED"),"PASSED",IF(OR(J20="IN_PROGRESS",L20="IN_PROGRESS"),"IN_PROGRESS",IF(OR(J20="BLOCKED",L20="BLOCKED"),"BLOCKED","NOT_STARTED"))))) -> BLOCKED | J20: BLOCKED | K20: NO | L20: NOT_STARTED | M20: §4.7, §5.3 | N20: partner-platform-prd-v1.8.md | P20: Trang Le | Q20: The SA Commission **configuration** view (which holds Clawback settings + the Waiver Review Queue) is **not deployed on staging** (re-verified 2026-07-30, same finding as _009/_010: no "View configuration" entry on `/partners/commissions`, config routes 404). An earlier note here checked the partner-portal `/commissions` (its "Clawback" tab only filters the empty ledger) — the actual clawback-policy/waiver experience is SA-side per PN021. Unblock when FE deploys the Commission configuration view. | T20: 4.7
C21: PARTNER_UI_COMMISSIONS_008 | D21: 12060308 | E21: Ask - Blazey commission question - Contextual answer is returned | F21: Functional | G21: P2 | H21: Major | I21: =IF(K21="No",J21,IF(OR(J21="FAILED",L21="FAILED"),"FAILED",IF(OR(J21="PASSED",L21="PASSED"),"PASSED",IF(OR(J21="IN_PROGRESS",L21="IN_PROGRESS"),"IN_PROGRESS",IF(OR(J21="BLOCKED",L21="BLOCKED"),"BLOCKED","NOT_STARTED"))))) -> BLOCKED | J21: BLOCKED | K21: NO | L21: NOT_STARTED | M21: §4.3, §10 | N21: partner-platform-prd-v1.8.md | P21: Trang Le | Q21: Depends on the **Blazey AI assistant** (deferred AI feature) + real commission context data. The assistant is not available/testable on the current build, and the ledger is empty (no commission context). Unblock when Blazey ships + commission data exists. | T21: 46305
C22: PARTNER_UI_COMMISSIONS_009 | D22: 12060309 | E22: Edit - Payout details by region - Correct payment methods are available | F22: Security | G22: P2 | H22: Major | I22: =IF(K22="No",J22,IF(OR(J22="FAILED",L22="FAILED"),"FAILED",IF(OR(J22="PASSED",L22="PASSED"),"PASSED",IF(OR(J22="IN_PROGRESS",L22="IN_PROGRESS"),"IN_PROGRESS",IF(OR(J22="BLOCKED",L22="BLOCKED"),"BLOCKED","NOT_STARTED"))))) -> BLOCKED | J22: BLOCKED | K22: NO | L22: NOT_STARTED | M22: §4.7 | N22: partner-platform-prd-v1.8.md | P22: Trang Le | Q22: No payout/banking-details edit UI found on the partner build — `/commissions` is a read-only ledger; a payout-details/settings screen (per region) was not located. Needs the payout-details UI + region fixtures. Unblock when the payout-details screen is available. | T22: 4.7
C23: PARTNER_UI_COMMISSIONS_010 | E23: Process - Commission clawback on early churn - Clawback is applied | F23: Functional | G23: P1 | H23: Major | I23: =IF(K23="No",J23,IF(OR(J23="FAILED",L23="FAILED"),"FAILED",IF(OR(J23="PASSED",L23="PASSED"),"PASSED",IF(OR(J23="IN_PROGRESS",L23="IN_PROGRESS"),"IN_PROGRESS",IF(OR(J23="BLOCKED",L23="BLOCKED"),"BLOCKED","NOT_STARTED"))))) -> BLOCKED | J23: BLOCKED | K23: NO | L23: NOT_STARTED | M23: §5.6 | N23: partner-platform-prd-v1.8.md | P23: Trang Le | Q23: Figma design: [PN013] Process commission clawback on early churn. Candidate TC — not yet in the plan. Verified live 2026-07-31 on the SA commission ledger (stgsa `/partners/commissions`): the ledger is **empty** ("No Data Found", 0 commissions) so there is no commission to clawback, and there is **no process-clawback action** in the UI (only a "Clawback Exposure" summary card + a Clawback status filter tab — no per-row "process clawback" control; design PN013 not deployed). Needs the full chain — rate configured → deal approved (blocked by BUG-025) → deal Won → commission — plus the process-clawback UI. Unblock when a churned-client commission exists + the process-clawback UI ships. | T23: 46178
B24: Commission Display | C24: PARTNER_UI_COMMISSIONS_011 | E24: Display - Reseller deal commission - Reseller rate shown, not referral rate | F24: Functional | G24: P1 | H24: Major | I24: =IF(K24="No",J24,IF(OR(J24="FAILED",L24="FAILED"),"FAILED",IF(OR(J24="PASSED",L24="PASSED"),"PASSED",IF(OR(J24="IN_PROGRESS",L24="IN_PROGRESS"),"IN_PROGRESS",IF(OR(J24="BLOCKED",L24="BLOCKED"),"BLOCKED","NOT_STARTED"))))) -> BLOCKED | J24: BLOCKED | K24: NO | L24: NOT_STARTED | M24: §3 Scenario B, §4.7, §5.3 | N24: partner-platform-prd-v1.8.md | P24: Trang Le | Q24: Needs a **Reseller-type partner** with a **Won reseller deal** and a reseller rate configured. The test partner is type Channel, the register wizard fixes deal type to Referral, and there is no configured rate / Won deal — so no reseller commission entry exists to verify. Unblock with a reseller partner + Won reseller deal + rate. | T24: 46207
B25: Invoice & Billing | C25: PARTNER_UI_COMMISSIONS_012 | E25: Invoice - Reseller deal close - Invoice generated for partner not end-client | F25: Functional | G25: P1 | H25: Critical | I25: =IF(K25="No",J25,IF(OR(J25="FAILED",L25="FAILED"),"FAILED",IF(OR(J25="PASSED",L25="PASSED"),"PASSED",IF(OR(J25="IN_PROGRESS",L25="IN_PROGRESS"),"IN_PROGRESS",IF(OR(J25="BLOCKED",L25="BLOCKED"),"BLOCKED","NOT_STARTED"))))) -> BLOCKED | J25: BLOCKED | K25: NO | L25: NOT_STARTED | M25: §3 Scenario B, §5.3 | N25: partner-platform-prd-v1.8.md | P25: Trang Le | Q25: Same dependency as _011 — needs a reseller partner + Won reseller deal that has passed commission processing, plus the invoice/billing UI (not seen on the partner build). Unblock with the reseller data + invoice UI. | T25: 3-B
A26: Dashboard | B26: Home KPIs & Actions | C26: PARTNER_UI_DASHBOARD_001 | D26: 12060401 | E26: View - Partner shell loads for channel partner - Dashboard is displayed | F26: Functional | G26: P1 | H26: Critical | I26: =IF(K26="No",J26,IF(OR(J26="FAILED",L26="FAILED"),"FAILED",IF(OR(J26="PASSED",L26="PASSED"),"PASSED",IF(OR(J26="IN_PROGRESS",L26="IN_PROGRESS"),"IN_PROGRESS",IF(OR(J26="BLOCKED",L26="BLOCKED"),"BLOCKED","NOT_STARTED"))))) -> PASSED | J26: NOT_STARTED | K26: YES | L26: PASSED | M26: §4.1, §4.2 | N26: partner-platform-prd-v1.8.md | P26: Trang Le | Q26: PASSED — verified 2026-07-28 (TC 12060401). Access-control style shell test: proves the partner portal exposes only partner routes and the Dashboard is the default landing page. Negative counterpart: N/A — access-control assertion is embedded (asserts SA-only routes are absent). Idempotency: N/A — read-only view. | R26: The partner shell loads for a channel-partner user and lands on the Dashboard. Confirms the shell chrome (brand + nav + profile), partner-only navigation (no SA/tenant-only routes leaked), and Dashboard content loading with no error/authorization banner. | S26: **Setup (precondition):** Log in as the channel-partner user; navigate to the portal root `/` (Dashboard is the default page) and wait for the "Tier & Performance" READY_MARKER. **Test Steps:** 1. Partner shell chrome renders. → Expected: the "PARTNER PORTAL" brand, ≥5 sidebar nav links, and the "Open profile menu" control are visible. 2. Only partner navigation is exposed. → Expected: partner routes `/dashboard`, `/deals`, `/commissions` present; NO SA/tenant-only routes (`/tenants`, `/billing`, `/plans`, `/partners`, `/connectors`, `/auditLog`). 3. Dashboard content loads with no error/authorization banner. → Expected: no "Something went wrong" / "not authorized" / "Unauthorized" / "403" / "Access denied"; the "Tier & Performance" panel is visible in `<main>`. **Expected (overall):** The partner shell loads for the channel partner with the Dashboard active, partner-scoped nav only, and no error/auth banner. | T26: 46057
C27: PARTNER_UI_DASHBOARD_002 | D27: 12060402 | E27: Render - Dashboard KPI cards available - Actionable metrics are visible | F27: Functional | G27: P1 | H27: Major | I27: =IF(K27="No",J27,IF(OR(J27="FAILED",L27="FAILED"),"FAILED",IF(OR(J27="PASSED",L27="PASSED"),"PASSED",IF(OR(J27="IN_PROGRESS",L27="IN_PROGRESS"),"IN_PROGRESS",IF(OR(J27="BLOCKED",L27="BLOCKED"),"BLOCKED","NOT_STARTED"))))) -> PASSED | J27: NOT_STARTED | K27: YES | L27: PASSED | M27: §4.3 | N27: partner-platform-prd-v1.8.md | P27: Trang Le | Q27: PASSED — verified 2026-07-28 (TC 12060402). First DASHBOARD content test — establishes the `DashboardPage` page-object (KPI cards, sections). Empty partner data shows "No Data Found" in Action Required / Pipeline Snapshot. Negative counterpart: N/A — read-only view. Idempotency: N/A. | R27: Open the partner Dashboard and confirm the KPI metric cards + main section panels render. Read-only: works with empty data (values may be 0 / USD 0) — verifies the cards render, not specific figures. | S27: **Setup (precondition):** Log in as the channel-partner user; open `/dashboard` via the shell and wait for the "Tier & Performance" READY_MARKER. **Test Steps:** 1. KPI cards render, each with a metric value. → Expected: **Total pipeline ACV**, **Commission YTD**, **Active Tenants** each show a value (e.g. "USD 0" / 0). 2. The main dashboard sections render. → Expected: **Tier & Performance**, **Territory Assignments**, **Action Required**, **Pipeline Snapshot** panels are visible. **Expected (overall):** The dashboard renders its KPI metric cards + all main sections (independent of the data). | T27: 4.3
C28: PARTNER_UI_DASHBOARD_003 | D28: 12060403 | E28: Render - Tier progress exists on dashboard - Progress to next tier is visible | F28: Functional | G28: P1 | H28: Major | I28: =IF(K28="No",J28,IF(OR(J28="FAILED",L28="FAILED"),"FAILED",IF(OR(J28="PASSED",L28="PASSED"),"PASSED",IF(OR(J28="IN_PROGRESS",L28="IN_PROGRESS"),"IN_PROGRESS",IF(OR(J28="BLOCKED",L28="BLOCKED"),"BLOCKED","NOT_STARTED"))))) -> FAILED | J28: NOT_STARTED | K28: YES | L28: FAILED | M28: §2.1, §4.3 | N28: partner-platform-prd-v1.8.md | O28: BUG-UI-014 | P28: Trang Le | Q28: PASSED — verified 2026-07-28 (TC 12060403; current=SELECT, working towards ADVANCED, ARR USD 0). **Plan-vs-live:** the plan also lists a **threshold target**, a **progress bar**, and a **remaining delta** — this build does NOT render those (no `role=progressbar` element, no threshold/remaining text); it shows current tier + next-tier copy + ARR + deals/win-rate. The test asserts what the UI actually renders. Negative counterpart: N/A — read-only view. Idempotency: N/A. | R28: The dashboard Tier Progress component shows progress to the next tier. Read-only. | S28: **Setup (precondition):** Log in as the channel-partner user; open `/dashboard` and wait for the "Tier & Performance" READY_MARKER. **Test Steps:** 1. Tier Progress shows the current tier + "working towards" the next tier + current ARR. → Expected: "Tier Progress" present; the **current tier** (SELECT/ADVANCED/PREMIER), the **"Working towards \<next tier\>"** copy, and **T12M ARR** are shown. 2. Progress metrics are shown. → Expected: the **deal count** and **Win rate** are shown in the tier progress panel. **Expected (overall):** Progress toward the next tier is visible (current tier + next-tier copy + ARR + metrics). | T28: 4.3
C29: PARTNER_UI_DASHBOARD_004 | D29: 12060404 | E29: Render - Action Required list has pending tasks - Partner sees next actions | F29: Functional | G29: P1 | H29: Major | I29: =IF(K29="No",J29,IF(OR(J29="FAILED",L29="FAILED"),"FAILED",IF(OR(J29="PASSED",L29="PASSED"),"PASSED",IF(OR(J29="IN_PROGRESS",L29="IN_PROGRESS"),"IN_PROGRESS",IF(OR(J29="BLOCKED",L29="BLOCKED"),"BLOCKED","NOT_STARTED"))))) -> BLOCKED | J29: BLOCKED | K29: NO | L29: NOT_STARTED | M29: §4.3 | N29: partner-platform-prd-v1.8.md | P29: Trang Le | Q29: No fixture / seeding path to make the Action Required list non-empty. The test partner (channel-partner) has empty data — the section renders its graceful empty state ("Action Required · No Data Found · Looks like there's nothing here yet"). Action-Required items are DERIVED (renewals due, deals needing partner action); there is no partner-side API to seed them, and the existing QA-AUTO deals (pending SA approval) do not surface here. The "has pending tasks" positive path cannot be verified until a partner account with real action items (or a seed hook) is available. Revisit with a data-seeded partner. | T29: 4.3
C30: PARTNER_UI_DASHBOARD_005 | D30: 12060405 | E30: Calculate - Tier qualification dashboard - T12M ARR threshold and next-tier delta are visible | F30: Functional | G30: P1 | H30: Major | I30: =IF(K30="No",J30,IF(OR(J30="FAILED",L30="FAILED"),"FAILED",IF(OR(J30="PASSED",L30="PASSED"),"PASSED",IF(OR(J30="IN_PROGRESS",L30="IN_PROGRESS"),"IN_PROGRESS",IF(OR(J30="BLOCKED",L30="BLOCKED"),"BLOCKED","NOT_STARTED"))))) -> FAILED | J30: NOT_STARTED | K30: YES | L30: FAILED | M30: §2.1, §4.3 | N30: partner-platform-prd-v1.8.md | O30: BUG-UI-007,BUG-UI-014 | P30: Trang Le | Q30: FAILED by design (be_gap) 2026-07-28 (TC 12060405). Build renders only current tier + "Working towards <next>" + current ARR + deal/win-rate ("0/0 deals"); NO ARR threshold, NO remaining delta, NO progress bar (no role=progressbar). Assertion fails with "confirm with BE". Complements DASHBOARD_003 (asserts only what UI renders); this TC pins the missing tier-qualification math. Excluded from merge gate. Negative/Idempotency: N/A (read-only calc). | R30: PARTNER_UI_DASHBOARD_001 | S30: **Setup (precondition):** Log in as the channel-partner user; open `/dashboard` and wait for the "Tier & Performance" READY_MARKER; locate the Tier Progress component. **Test Steps:** 1. Current tier + current T12M ARR are shown (baseline). → Expected: current tier (SELECT/ADVANCED/PREMIER) + "T12M ARR" are shown. **(PASSES — build renders these.)** 2. Next-tier T12M ARR threshold target + remaining delta are shown. → Expected: a threshold/target/remaining figure toward the next tier is shown. **(FAILS — not rendered.)** 3. A progress bar toward the next-tier threshold is shown. → Expected: a `role=progressbar` / `<progress>` element is present. **(Would FAIL — none rendered.)** **Expected (overall):** The tier-qualification threshold + remaining delta + progress bar are visible. | T30: 4.3
B31: Tier Progress | C31: PARTNER_UI_DASHBOARD_006 | D31: 12060406 | E31: Warn - Tier downgrade pending - 30-day notice and grace quarter are displayed | F31: Functional | G31: P1 | H31: Major | I31: =IF(K31="No",J31,IF(OR(J31="FAILED",L31="FAILED"),"FAILED",IF(OR(J31="PASSED",L31="PASSED"),"PASSED",IF(OR(J31="IN_PROGRESS",L31="IN_PROGRESS"),"IN_PROGRESS",IF(OR(J31="BLOCKED",L31="BLOCKED"),"BLOCKED","NOT_STARTED"))))) -> BLOCKED | J31: BLOCKED | K31: NO | L31: NOT_STARTED | M31: §2.1, §5.5 | N31: partner-platform-prd-v1.8.md | P31: Trang Le | Q31: The test partner is not in a **tier-downgrade-pending** state, and there is no way to seed one (tier downgrade is derived from T12M ARR falling below the current tier's threshold over a grace quarter). With no partner in that state, the 30-day-notice / grace-quarter warning cannot be triggered or verified. Also depends on the tier-qualification math that _005 showed is not fully rendered. Unblock with a partner fixture in the downgrade-pending state (+ the warning UI). | T31: 5.5
B32: Home KPIs & Actions | C32: PARTNER_UI_DASHBOARD_007 | D32: 12060407 | E32: Validate - Dashboard hides vanity metrics - Only actionable/clickable values are shown | F32: Negative | G32: P3 | H32: Minor | I32: =IF(K32="No",J32,IF(OR(J32="FAILED",L32="FAILED"),"FAILED",IF(OR(J32="PASSED",L32="PASSED"),"PASSED",IF(OR(J32="IN_PROGRESS",L32="IN_PROGRESS"),"IN_PROGRESS",IF(OR(J32="BLOCKED",L32="BLOCKED"),"BLOCKED","NOT_STARTED"))))) -> PASSED | J32: NOT_STARTED | K32: YES | L32: PASSED | M32: §4.3 | N32: partner-platform-prd-v1.8.md | P32: Trang Le | Q32: CODE COMPLETE, run PENDING VERIFY (TC 12060407) 2026-07-28. No green run yet: staging partner dashboard MFE degraded ~15:35 (<main>/"Tier & Performance" not rendering within 90s; earlier probes rendered in ~8s — staging outage, not a test defect). Re-run when staging recovers. Negative TC by design. Idempotency N/A (read-only). | R32: (Negative guard) Dashboard hides vanity metrics — per PRD §4.3 the first dashboard view shows ONLY actionable/decision-supporting values (pipeline ACV, commission, active tenants, tier progress, action items, pipeline snapshot) and must NOT surface non-actionable vanity metrics (page/profile views, impressions, followers, bounce rate, login counts). | S32: 1. Log in as channel-partner; open /dashboard, wait for "Tier & Performance" → Expected: dashboard ready. 2. Only actionable KPI metrics shown → Expected: Total pipeline ACV, Commission YTD, Active Tenants visible. 3. No vanity metrics present → Expected: none of {page views, profile views, impressions, followers, bounce rate, time on page, click-through, logins, vanity} in <main>. 4. Page hierarchy still highlights actionable sections → Expected: Action Required, Tier Progress, Pipeline Snapshot visible. | T32: 4.3
B33: Blazey AI Assistant | C33: PARTNER_UI_DASHBOARD_008 | D33: 12060408 | E33: Ask - Blazey deal status question on dashboard - Current deal stage and assigned rep contact are returned | F33: Functional | G33: P2 | H33: Major | I33: =IF(K33="No",J33,IF(OR(J33="FAILED",L33="FAILED"),"FAILED",IF(OR(J33="PASSED",L33="PASSED"),"PASSED",IF(OR(J33="IN_PROGRESS",L33="IN_PROGRESS"),"IN_PROGRESS",IF(OR(J33="BLOCKED",L33="BLOCKED"),"BLOCKED","NOT_STARTED"))))) -> BLOCKED | J33: BLOCKED | K33: NO | L33: NOT_STARTED | M33: §4.3, §10.10 | N33: partner-platform-prd-v1.8.md | P33: Trang Le | Q33: Depends on the **Blazey AI assistant** (deferred AI feature) — the widget is not available/testable on the current build — plus real deal data for the partner. Unblock when Blazey ships + the partner has deals. | T33: 4.3
C34: PARTNER_UI_DASHBOARD_009 | D34: 12060409 | E34: Ask - Blazey tier projection question on dashboard - ARR needed and timeline to next tier are displayed | F34: Functional | G34: P2 | H34: Major | I34: =IF(K34="No",J34,IF(OR(J34="FAILED",L34="FAILED"),"FAILED",IF(OR(J34="PASSED",L34="PASSED"),"PASSED",IF(OR(J34="IN_PROGRESS",L34="IN_PROGRESS"),"IN_PROGRESS",IF(OR(J34="BLOCKED",L34="BLOCKED"),"BLOCKED","NOT_STARTED"))))) -> BLOCKED | J34: BLOCKED | K34: NO | L34: NOT_STARTED | M34: §4.3, §10.10 | N34: partner-platform-prd-v1.8.md | P34: Trang Le | Q34: Same as _008 — depends on the Blazey AI assistant (deferred) + tier data. Note the tier-qualification figures it would quote (threshold/gap) are also the ones _005 showed the UI doesn't fully render yet. Unblock when Blazey ships. | T34: 4.3
A35: My Clients | B35: Client Health & MSP | C35: PARTNER_UI_MY_CLIENTS_001 | E35: Click - Action Required renewal CTA - Renewal registration flow opens | F35: Functional | G35: P1 | H35: Major | I35: =IF(K35="No",J35,IF(OR(J35="FAILED",L35="FAILED"),"FAILED",IF(OR(J35="PASSED",L35="PASSED"),"PASSED",IF(OR(J35="IN_PROGRESS",L35="IN_PROGRESS"),"IN_PROGRESS",IF(OR(J35="BLOCKED",L35="BLOCKED"),"BLOCKED","NOT_STARTED"))))) -> BLOCKED | J35: BLOCKED | K35: NO | L35: NOT_STARTED | M35: §4.3, §4.6 | N35: partner-platform-prd-v1.8.md | P35: Trang Le | Q35: module not deployed | T35: 4.6
C36: PARTNER_UI_MY_CLIENTS_002 | E36: List - Open My Clients - Post-close clients are displayed | F36: Functional | G36: P1 | H36: Major | I36: =IF(K36="No",J36,IF(OR(J36="FAILED",L36="FAILED"),"FAILED",IF(OR(J36="PASSED",L36="PASSED"),"PASSED",IF(OR(J36="IN_PROGRESS",L36="IN_PROGRESS"),"IN_PROGRESS",IF(OR(J36="BLOCKED",L36="BLOCKED"),"BLOCKED","NOT_STARTED"))))) -> BLOCKED | J36: BLOCKED | K36: NO | L36: NOT_STARTED | M36: §4.6 | N36: partner-platform-prd-v1.8.md | P36: Trang Le | Q36: module not deployed | T36: 4.6
C37: PARTNER_UI_MY_CLIENTS_003 | E37: Open - Client health detail - ARR, renewal, usage, tickets, and CSM are visible | F37: Functional | G37: P1 | H37: Critical | I37: =IF(K37="No",J37,IF(OR(J37="FAILED",L37="FAILED"),"FAILED",IF(OR(J37="PASSED",L37="PASSED"),"PASSED",IF(OR(J37="IN_PROGRESS",L37="IN_PROGRESS"),"IN_PROGRESS",IF(OR(J37="BLOCKED",L37="BLOCKED"),"BLOCKED","NOT_STARTED"))))) -> BLOCKED | J37: BLOCKED | K37: NO | L37: NOT_STARTED | M37: §1.3, §4.6 | N37: partner-platform-prd-v1.8.md | P37: Trang Le | Q37: module not deployed | T37: 4.6
C38: PARTNER_UI_MY_CLIENTS_004 | E38: Register - Renewal deal from client detail - Renewal context is prefilled | F38: Functional | G38: P1 | H38: Major | I38: =IF(K38="No",J38,IF(OR(J38="FAILED",L38="FAILED"),"FAILED",IF(OR(J38="PASSED",L38="PASSED"),"PASSED",IF(OR(J38="IN_PROGRESS",L38="IN_PROGRESS"),"IN_PROGRESS",IF(OR(J38="BLOCKED",L38="BLOCKED"),"BLOCKED","NOT_STARTED"))))) -> BLOCKED | J38: BLOCKED | K38: NO | L38: NOT_STARTED | M38: §3 Scenario F, §4.6 | N38: partner-platform-prd-v1.8.md | P38: Trang Le | Q38: module not deployed | T38: 4.6
C39: PARTNER_UI_MY_CLIENTS_005 | E39: Add - MSP managed client - Provisioning form is shown | F39: Functional | G39: P1 | H39: Critical | I39: =IF(K39="No",J39,IF(OR(J39="FAILED",L39="FAILED"),"FAILED",IF(OR(J39="PASSED",L39="PASSED"),"PASSED",IF(OR(J39="IN_PROGRESS",L39="IN_PROGRESS"),"IN_PROGRESS",IF(OR(J39="BLOCKED",L39="BLOCKED"),"BLOCKED","NOT_STARTED"))))) -> BLOCKED | J39: BLOCKED | K39: NO | L39: NOT_STARTED | M39: §3 Scenario G, §7.3 | N39: partner-platform-prd-v1.8.md | P39: Trang Le | Q39: module not deployed | T39: 3-G
C40: PARTNER_UI_MY_CLIENTS_006 | E40: Toggle - MSP ticket consent default - Consent is off by default | F40: Security | G40: P1 | H40: Major | I40: =IF(K40="No",J40,IF(OR(J40="FAILED",L40="FAILED"),"FAILED",IF(OR(J40="PASSED",L40="PASSED"),"PASSED",IF(OR(J40="IN_PROGRESS",L40="IN_PROGRESS"),"IN_PROGRESS",IF(OR(J40="BLOCKED",L40="BLOCKED"),"BLOCKED","NOT_STARTED"))))) -> BLOCKED | J40: BLOCKED | K40: NO | L40: NOT_STARTED | M40: §3 Scenario G, §7.3, §9.2 | N40: partner-platform-prd-v1.8.md | P40: Trang Le | Q40: module not deployed | T40: 3-G
C41: PARTNER_UI_MY_CLIENTS_007 | E41: Filter - Renewal This Quarter - Only qualifying clients are shown | F41: Functional | G41: P2 | H41: Major | I41: =IF(K41="No",J41,IF(OR(J41="FAILED",L41="FAILED"),"FAILED",IF(OR(J41="PASSED",L41="PASSED"),"PASSED",IF(OR(J41="IN_PROGRESS",L41="IN_PROGRESS"),"IN_PROGRESS",IF(OR(J41="BLOCKED",L41="BLOCKED"),"BLOCKED","NOT_STARTED"))))) -> BLOCKED | J41: BLOCKED | K41: NO | L41: NOT_STARTED | M41: §4.6 | N41: partner-platform-prd-v1.8.md | P41: Trang Le | Q41: module not deployed | T41: 4.6
C42: PARTNER_UI_MY_CLIENTS_008 | E42: Filter - Health At Risk - At-risk clients are shown | F42: Functional | G42: P2 | H42: Major | I42: =IF(K42="No",J42,IF(OR(J42="FAILED",L42="FAILED"),"FAILED",IF(OR(J42="PASSED",L42="PASSED"),"PASSED",IF(OR(J42="IN_PROGRESS",L42="IN_PROGRESS"),"IN_PROGRESS",IF(OR(J42="BLOCKED",L42="BLOCKED"),"BLOCKED","NOT_STARTED"))))) -> BLOCKED | J42: BLOCKED | K42: NO | L42: NOT_STARTED | M42: §1.3, §4.6 | N42: partner-platform-prd-v1.8.md | P42: Trang Le | Q42: module not deployed | T42: 4.6
C43: PARTNER_UI_MY_CLIENTS_009 | E43: Search - Find client by name - Matching clients are displayed | F43: Functional | G43: P2 | H43: Major | I43: =IF(K43="No",J43,IF(OR(J43="FAILED",L43="FAILED"),"FAILED",IF(OR(J43="PASSED",L43="PASSED"),"PASSED",IF(OR(J43="IN_PROGRESS",L43="IN_PROGRESS"),"IN_PROGRESS",IF(OR(J43="BLOCKED",L43="BLOCKED"),"BLOCKED","NOT_STARTED"))))) -> BLOCKED | J43: BLOCKED | K43: NO | L43: NOT_STARTED | M43: §4.6 | N43: partner-platform-prd-v1.8.md | P43: Trang Le | Q43: module not deployed | T43: 4.6
C44: PARTNER_UI_MY_CLIENTS_010 | E44: Display - Blazey client insight - Adoption recommendation appears | F44: Functional | G44: P2 | H44: Major | I44: =IF(K44="No",J44,IF(OR(J44="FAILED",L44="FAILED"),"FAILED",IF(OR(J44="PASSED",L44="PASSED"),"PASSED",IF(OR(J44="IN_PROGRESS",L44="IN_PROGRESS"),"IN_PROGRESS",IF(OR(J44="BLOCKED",L44="BLOCKED"),"BLOCKED","NOT_STARTED"))))) -> BLOCKED | J44: BLOCKED | K44: NO | L44: NOT_STARTED | M44: §1.3, §4.6 | N44: partner-platform-prd-v1.8.md | P44: Trang Le | Q44: module not deployed | T44: 4.6
B45: Expansion Deal | C45: PARTNER_UI_MY_CLIENTS_011 | E45: Register - Expansion deal from My Clients - Existing client pre-filled in wizard | F45: Functional | G45: P1 | H45: Critical | I45: =IF(K45="No",J45,IF(OR(J45="FAILED",L45="FAILED"),"FAILED",IF(OR(J45="PASSED",L45="PASSED"),"PASSED",IF(OR(J45="IN_PROGRESS",L45="IN_PROGRESS"),"IN_PROGRESS",IF(OR(J45="BLOCKED",L45="BLOCKED"),"BLOCKED","NOT_STARTED"))))) -> BLOCKED | J45: BLOCKED | K45: NO | L45: NOT_STARTED | M45: §3 Scenario F, §4.6, §4.4 | N45: partner-platform-prd-v1.8.md | P45: Trang Le | Q45: Expansion starts from My Clients — existing client context must pre-fill wizard, not blank form | R45: Validate the UI flow for expansion deal registration from My Clients so that existing client details are pre-filled in the deal wizard. Scope covers the My Clients list, client detail page, expansion deal CTA, deal registration wizard pre-fill behavior, and PRD coverage §3 Scenario F, §4.6, §4.4. Out of scope: commission calculation and tenant provisioning. | S45: 1. Log in as an active partner with at least one existing closed client in My Clients. 2. Navigate to My Clients and open the client detail page. 3. Locate and click the "Register Expansion Deal" CTA. 4. Verify the deal registration wizard opens with company name, domain, and tenant reference pre-filled from the existing client record. 5. Confirm the wizard does not require re-entering client details already on file. 6. Submit the expansion deal and verify it appears in My Pipeline. | T45: 3-F
C46: PARTNER_UI_MY_CLIENTS_012 | E46: Display - Blazey client insight - Adoption recommendation appears | F46: Functional | G46: P1 | H46: Critical | I46: =IF(K46="No",J46,IF(OR(J46="FAILED",L46="FAILED"),"FAILED",IF(OR(J46="PASSED",L46="PASSED"),"PASSED",IF(OR(J46="IN_PROGRESS",L46="IN_PROGRESS"),"IN_PROGRESS",IF(OR(J46="BLOCKED",L46="BLOCKED"),"BLOCKED","NOT_STARTED"))))) -> BLOCKED | J46: BLOCKED | K46: NO | L46: NOT_STARTED | M46: §3 Scenario F, §7.4 | N46: partner-platform-prd-v1.8.md | P46: Trang Le | Q46: Key invariant: expansion must reuse existing tenant_id — new tenant must NOT be provisioned | R46: Validate the UI flow for expansion deal submission so that existing tenant_id is reused and no new tenant is created. Scope covers the deal registration wizard review step, submission confirmation, deal detail page tenant reference, and PRD coverage §3 Scenario F, §7.4. Out of scope: commission calculation and billing. | S46: 1. Submit an expansion deal for an existing client via the registration wizard (from TC_011 or equivalent fixture). 2. Open the submitted deal in My Pipeline and navigate to deal detail. 3. Verify the deal detail shows the existing client's tenant_id (not a new one). 4. Confirm no new tenant provisioning task or pending-tenant state is shown. 5. Verify the expansion deal is linked to the same client record in My Clients. | T46: 3-F
C47: PARTNER_UI_MY_CLIENTS_013 | E47: Display - Blazey client insight - Adoption recommendation appears | F47: Functional | G47: P1 | H47: Major | I47: =IF(K47="No",J47,IF(OR(J47="FAILED",L47="FAILED"),"FAILED",IF(OR(J47="PASSED",L47="PASSED"),"PASSED",IF(OR(J47="IN_PROGRESS",L47="IN_PROGRESS"),"IN_PROGRESS",IF(OR(J47="BLOCKED",L47="BLOCKED"),"BLOCKED","NOT_STARTED"))))) -> BLOCKED | J47: BLOCKED | K47: NO | L47: NOT_STARTED | M47: §3 Scenario F, §4.6, §7.4 | N47: partner-platform-prd-v1.8.md | P47: Trang Le | Q47: After expansion close, ARR on client card must reflect the expanded value | R47: Validate the UI flow for post-close expansion deal so that ARR is updated in the My Clients client detail card. Scope covers the My Clients list, client detail page, ARR metric display, and PRD coverage §3 Scenario F, §4.6, §7.4. Out of scope: commission payout and new tenant provisioning. | S47: 1. Log in as a partner with a Won expansion deal fixture for an existing client. 2. Navigate to My Clients and open the client detail page for that client. 3. Verify the ARR displayed on the client detail card reflects the updated value after the expansion close. 4. Confirm the ARR increase matches the expansion deal value. 5. Verify no duplicate client record was created — the same client entry shows the expanded ARR. | T47: 3-F
A48: My Pipeline | B48: Deal Registration | C48: PARTNER_UI_MY_PIPELINE_001 | D48: 12060201 | E48: Register - Enter valid company details - Wizard advances to contact step | F48: Functional | G48: P1 | H48: Critical | I48: =IF(K48="No",J48,IF(OR(J48="FAILED",L48="FAILED"),"FAILED",IF(OR(J48="PASSED",L48="PASSED"),"PASSED",IF(OR(J48="IN_PROGRESS",L48="IN_PROGRESS"),"IN_PROGRESS",IF(OR(J48="BLOCKED",L48="BLOCKED"),"BLOCKED","NOT_STARTED"))))) -> PASSED | J48: NOT_STARTED | K48: YES | L48: PASSED | M48: §4.4 | N48: partner-platform-prd-v1.8.md | P48: Trang Le | Q48: PASSED (TC 12060201), verified 2026-07-24. Register-a-Deal wizard step 1: valid company details enable Next -> advance to Step 2 (Deal info) -> Back preserves company name. Plan-vs-live: plan says "advances to contact step" but contact is IN step 1; validation is via DISABLING Next (no inline error). Modal-only (no submit) — unaffected by the deals-list defect. Negative = _002. Idempotency N/A. | R48: Register-a-Deal wizard step 1: entering valid company details (name, domain, country) + primary contact enables Next, advances to Step 2 (Deal info), and preserves the company data when going Back. Modal-only; does not submit. | S48: **Setup (precondition):** Log in as the channel-partner user; open `/deals`; click "Register a deal" to open the wizard (opens on "Step 1 of 3 — Register company"). **Test Steps:** 1. Enter company details (name, domain, country) + primary contact (name, email), then verify each field holds the entered value. → Expected: every field **echoes** the entered value (company name, domain, contact name, email — no silent mutation/clear), a country is selected, and — with all required fields filled — "Next" becomes **enabled**. ("Valid" here = required-complete + values echoed; this build does not format-check the fields — that gap is _003.) 2. Click Next. → Expected: wizard advances to **Step 2 of 3 (Deal info)** and the Deal-info content renders (a step-2-only field, e.g. "Expected close date", is visible — proving it landed on Deal info, not just a counter change). Deep Deal-info field testing is _008–_012. 3. Go Back to step 1. → Expected: returns to Step 1 of 3 and the **company name is preserved**. | T48: 4.4
C49: PARTNER_UI_MY_PIPELINE_002 | D49: 12060202 | E49: Validate - Leave company name blank - Required field error is shown | F49: Negative | G49: P1 | H49: Major | I49: =IF(K49="No",J49,IF(OR(J49="FAILED",L49="FAILED"),"FAILED",IF(OR(J49="PASSED",L49="PASSED"),"PASSED",IF(OR(J49="IN_PROGRESS",L49="IN_PROGRESS"),"IN_PROGRESS",IF(OR(J49="BLOCKED",L49="BLOCKED"),"BLOCKED","NOT_STARTED"))))) -> PASSED | J49: NOT_STARTED | K49: YES | L49: PASSED | M49: §4.4 | N49: partner-platform-prd-v1.8.md | P49: Trang Le | Q49: PASSED (TC 12060202), verified 2026-07-24. Negative of _001: with company name blank, Next stays disabled and the wizard cannot advance; filling company name enables Next -> proves it is required. Plan-vs-live: plan says "required error shown" but this build has NO inline error text — required fields are enforced by disabling Next. Idempotency N/A (no submit). | R49: Negative counterpart of _001: leaving the required company name blank blocks the wizard from advancing (Next stays disabled); providing it unblocks — proving company name is required. | S49: **Setup (precondition):** Open `/deals`; launch the Register-a-Deal wizard (Step 1 of 3). **Test Steps:** 1. Fill everything EXCEPT company name (domain, country, contact name, email). → Expected: "Next" stays **disabled** and the wizard stays on Step 1 of 3 (cannot advance with a blank required field). 2. Fill the company name. → Expected: "Next" becomes **enabled** (company name was the blocking required field). | T49: 4.4
C50: PARTNER_UI_MY_PIPELINE_003 | D50: 12060203 | E50: Validate - Enter invalid domain - Domain format error is shown | F50: Negative | G50: P1 | H50: Major | I50: =IF(K50="No",J50,IF(OR(J50="FAILED",L50="FAILED"),"FAILED",IF(OR(J50="PASSED",L50="PASSED"),"PASSED",IF(OR(J50="IN_PROGRESS",L50="IN_PROGRESS"),"IN_PROGRESS",IF(OR(J50="BLOCKED",L50="BLOCKED"),"BLOCKED","NOT_STARTED"))))) -> PASSED | J50: NOT_STARTED | K50: YES | L50: PASSED | M50: §4.4 | N50: partner-platform-prd-v1.8.md | P50: Trang Le | R50: Negative (fail-by-design): an invalid/malformed domain in the register wizard must be rejected with a domain-format error (block advancing or flag the field). All cases run (collected). | S50: **Setup (precondition):** Open the Register-a-Deal wizard (step 1) with valid company name, country, and primary contact; vary only the Domain field. **Test Steps:** (each = enter a malformed domain, blur, check it is rejected) 1. `@@@` → Expected: rejected (Next disabled or field flagged). **Currently FAILS** — accepted (Next stays enabled, field not flagged). 2. `ab cd` (space) → Expected: rejected. **Currently FAILS** — accepted. 3. `notadomain` (no TLD) → Expected: rejected. **Currently FAILS** — accepted. 4. `http://x.com` (scheme, not a bare domain) → Expected: rejected. **Currently FAILS** — accepted. **Expected (overall):** A malformed domain is rejected with a clear format error; no deal is created. | T50: 4.4
C51: PARTNER_UI_MY_PIPELINE_004 | D51: 12060204 | E51: Warn - Domain already exists - Inline active-account warning is shown | F51: Functional | G51: P1 | H51: Critical | I51: =IF(K51="No",J51,IF(OR(J51="FAILED",L51="FAILED"),"FAILED",IF(OR(J51="PASSED",L51="PASSED"),"PASSED",IF(OR(J51="IN_PROGRESS",L51="IN_PROGRESS"),"IN_PROGRESS",IF(OR(J51="BLOCKED",L51="BLOCKED"),"BLOCKED","NOT_STARTED"))))) -> PASSED | J51: NOT_STARTED | K51: YES | L51: PASSED | M51: §3 Scenario D, §4.4 | N51: partner-platform-prd-v1.8.md | P51: Trang Le | Q51: PASSED — verified 2026-07-27 (TC 12060204). On blur the field calls `GET /v1/partner/portal/ | R51: In the register wizard, entering a domain (subdomain label) already reserved by another active deal shows an inline active-account/conflict warning; a free domain shows none. UI-only (no submit). | S51: **Setup (precondition):** Prove via the partner `check-domain` API which candidate label is reserved (`available=false`) vs free (`available=true`) — so the UI assertion is not circular. Open the wizard with valid company/country/contact. NOTE: the "Domain" field is a **subdomain label** (lowercase/numbers/hyphens, no dots) — placeholder "acme.com" is misleading; a value with dots returns 400 from check-domain. **Test Steps:** 1. Enter the RESERVED domain (proven `available=false`, e.g. "test"). → Expected: inline warning shows, e.g. **"This domain is reserved by another active deal. Register will get a conflict queue."** (Next stays enabled — the deal would enter the conflict queue on submit, not blocked.) 2. Enter an AVAILABLE domain (proven `available=true`) — control. → Expected: no reserved/active-deal warning. **Expected (overall):** A reserved domain surfaces the inline active-account/conflict warning; a free domain does not. | T51: 4.4
C52: PARTNER_UI_MY_PIPELINE_005 | D52: 12060205 | E52: Submit - Existing domain with warning - Deal enters conflict queue | F52: Functional | G52: P1 | H52: Critical | I52: =IF(K52="No",J52,IF(OR(J52="FAILED",L52="FAILED"),"FAILED",IF(OR(J52="PASSED",L52="PASSED"),"PASSED",IF(OR(J52="IN_PROGRESS",L52="IN_PROGRESS"),"IN_PROGRESS",IF(OR(J52="BLOCKED",L52="BLOCKED"),"BLOCKED","NOT_STARTED"))))) -> PASSED | J52: NOT_STARTED | K52: YES | L52: PASSED | M52: §3 Scenario D, §5.2 | N52: partner-platform-prd-v1.8.md | P52: Trang Le | Q52: PASSED — verified 2026-07-27 (TC 12060205). Full e2e submit works: reserved-domain warning → Deal info → **submit → 201** (deal id logged in the run for manual lookup). **PENDING (verify step — intentionally not asserted yet):** confirming the deal actually LANDS in the conflict queue is deferred — the partner deals-list endpoint is 400 (`_024`) so the deal isn't listable, and there is no delete API to clean up the created deal. **To improve once BE provides a way to fetch/remove the created deal** (user following up with BE). Side-effect: each run creates one non-deletable deal. Negative/conflict-detection is covered by _004 (UI warning) + API `2060204`. Idempotency: N/A here (duplicate-register is _022). | R52: Submit the full register wizard on an already-reserved domain (the conflict path). Fills every step (company + contact + reserved domain; deal info: plan / seats / region / expected close date) and submits; a deal is created (would enter the conflict queue). | S52: **Setup (precondition):** Prove via `check-domain` API a reserved label (available=false). Open the wizard. **Test Steps:** 1. Step 1 with the RESERVED domain → the inline conflict warning shows ("reserved by another active deal … conflict queue"); advance. → Expected: warning shown; wizard advances to Deal info. 2. Fill Deal info — plan (billing cycle auto-sets), granted seats, region, expected close date (next month) → advance to Summary. → Expected: with Deal info complete, "Next" is enabled; wizard reaches Step 3 of 3 (Summary). 3. Submit. → Expected: submission succeeds — `POST /v1/partner/portal/deals` returns **201** and a deal id. **Expected (overall):** The wizard submits end-to-end on a reserved domain and the deal is created. | T52: 3-D
C53: PARTNER_UI_MY_PIPELINE_006 | D53: 12060206 | E53: Validate - Enter contact without email - Required field error is shown | F53: Negative | G53: P1 | H53: Major | I53: =IF(K53="No",J53,IF(OR(J53="FAILED",L53="FAILED"),"FAILED",IF(OR(J53="PASSED",L53="PASSED"),"PASSED",IF(OR(J53="IN_PROGRESS",L53="IN_PROGRESS"),"IN_PROGRESS",IF(OR(J53="BLOCKED",L53="BLOCKED"),"BLOCKED","NOT_STARTED"))))) -> PASSED | J53: NOT_STARTED | K53: YES | L53: PASSED | M53: §4.4 | N53: partner-platform-prd-v1.8.md | P53: Trang Le | Q53: PASSED — verified 2026-07-27 (TC 12060206). Same mechanism as _002: required fields enforced by disabling "Next" (no inline error text). Idempotency: N/A (validation, no submit). | R53: Negative (required): leaving the primary-contact **email** blank blocks the wizard from advancing; providing a valid email unblocks — proving the email is required. | S53: **Setup (precondition):** Open the wizard (Step 1); fill every other required field (company name, domain, country, contact name). **Test Steps:** 1. Leave contact email blank (others filled). → Expected: email field confirmed blank while others hold values; "Next" stays **disabled** — block attributable only to the missing email. 2. Fill a valid email. → Expected: "Next" becomes **enabled**. **Expected (overall):** A blank required email prevents advancing; a valid email allows it. | T53: 4.4
C54: PARTNER_UI_MY_PIPELINE_007 | D54: 12060207 | E54: Validate - Enter malformed email - Email error is shown | F54: Negative | G54: P1 | H54: Major | I54: =IF(K54="No",J54,IF(OR(J54="FAILED",L54="FAILED"),"FAILED",IF(OR(J54="PASSED",L54="PASSED"),"PASSED",IF(OR(J54="IN_PROGRESS",L54="IN_PROGRESS"),"IN_PROGRESS",IF(OR(J54="BLOCKED",L54="BLOCKED"),"BLOCKED","NOT_STARTED"))))) -> PASSED | J54: NOT_STARTED | K54: YES | L54: PASSED | M54: §4.4 | N54: partner-platform-prd-v1.8.md | P54: Trang Le | R54: Negative (fail-by-design): a malformed contact **email** must be rejected with a format error (block advancing or flag the field). All cases run (collected). | S54: **Setup (precondition):** Open the wizard (Step 1) with valid company/domain/country/contact-name; vary only the email. **Test Steps:** (each = enter a malformed email, blur, check it is rejected) 1. `notanemail` (no @) → Expected: rejected. **Currently FAILS** — accepted (field keeps value, Next enabled, not flagged). 2. `abc@` (no domain) → Expected: rejected. **Currently FAILS** — accepted. 3. `abc@x` (no TLD) → Expected: rejected. **Currently FAILS** — accepted. 4. `a b@x.com` (space) → Expected: rejected. **Currently FAILS** — accepted. **Expected (overall):** A malformed email is rejected with a clear format error; no deal is created. | T54: 4.4
C55: PARTNER_UI_MY_PIPELINE_008 | D55: 12060208 | E55: Select - Choose referral deal type - Direct billing model is implied | F55: Functional | G55: P1 | H55: Major | I55: =IF(K55="No",J55,IF(OR(J55="FAILED",L55="FAILED"),"FAILED",IF(OR(J55="PASSED",L55="PASSED"),"PASSED",IF(OR(J55="IN_PROGRESS",L55="IN_PROGRESS"),"IN_PROGRESS",IF(OR(J55="BLOCKED",L55="BLOCKED"),"BLOCKED","NOT_STARTED"))))) -> PASSED | J55: NOT_STARTED | K55: YES | L55: PASSED | M55: §2.2, §2.3, §4.4 | N55: partner-platform-prd-v1.8.md | P55: Trang Le | Q55: PASSED — verified 2026-07-27 (TC 12060208). On this build the deal type is a **fixed read-only "Referral" badge** (reseller/co-sell are NOT selectable — clicking it opens nothing, there's no deal-type dropdown, and no "Reseller"/"Co-sell" text). Referral implies the direct billing model (business rule); the UI shows only the type label "Referral" (no explicit "direct billing" text). No submit → no side-effect. Idempotency: N/A. | R55: Choosing the referral deal type: on this wizard the deal type is Referral (default), and it persists to the Summary. UI-only (no submit). | S55: **Setup (precondition):** Open the wizard; complete step 1 (company/domain/country/contact). **Test Steps:** 1. On Deal info, the deal type shows **Referral** (Reseller/Co-sell are not offered — see _009/_010). → Expected: "Referral" visible; no "Reseller" option present. 2. Complete Deal info (plan/seats/region/date) → continue to Summary. → Expected: reaches Step 3 of 3 (Summary). 3. Summary persists the deal type. → Expected: Summary shows **Deal type = Referral**. **Expected (overall):** Referral deal type is captured and persists across navigation to the Summary. | T55: 4.4
C56: PARTNER_UI_MY_PIPELINE_009 | D56: 12060209 | E56: Select - Choose reseller deal type - Reseller billing path is available | F56: Functional | G56: P1 | H56: Major | I56: =IF(K56="No",J56,IF(OR(J56="FAILED",L56="FAILED"),"FAILED",IF(OR(J56="PASSED",L56="PASSED"),"PASSED",IF(OR(J56="IN_PROGRESS",L56="IN_PROGRESS"),"IN_PROGRESS",IF(OR(J56="BLOCKED",L56="BLOCKED"),"BLOCKED","NOT_STARTED"))))) -> BLOCKED | J56: BLOCKED | K56: NO | L56: NOT_STARTED | M56: §2.2, §3 Scenario B, §4.4 | N56: partner-platform-prd-v1.8.md | P56: Trang Le | Q56: Choose reseller deal type → reseller billing path. Blocked (verified live 2026-07-27): the register wizard does **not offer a reseller deal type** — the deal type is a fixed read-only "Referral" badge (no deal-type dropdown; clicking it opens nothing; "Reseller" text is absent). There is no UI control to select reseller, so the reseller billing path cannot be exercised from the wizard. (The API supports dealType `reseller` — see `make_deal` / API deal TCs — so this is a UI gap.) Unblock when the wizard exposes a deal-type selector with reseller. | T56: 4.4
C57: PARTNER_UI_MY_PIPELINE_010 | D57: 12060210 | E57: Select - Choose co-sell deal type - Co-sell option is captured | F57: Functional | G57: P1 | H57: Major | I57: =IF(K57="No",J57,IF(OR(J57="FAILED",L57="FAILED"),"FAILED",IF(OR(J57="PASSED",L57="PASSED"),"PASSED",IF(OR(J57="IN_PROGRESS",L57="IN_PROGRESS"),"IN_PROGRESS",IF(OR(J57="BLOCKED",L57="BLOCKED"),"BLOCKED","NOT_STARTED"))))) -> BLOCKED | J57: BLOCKED | K57: NO | L57: NOT_STARTED | M57: §2.3, §3 Scenario C, §4.4 | N57: partner-platform-prd-v1.8.md | P57: Trang Le | Q57: Choose co-sell deal type → co-sell option captured. Blocked (verified live 2026-07-27): same as _009 — the wizard's deal type is a fixed read-only "Referral" badge with no selector; "Co-sell" is not offered in the UI. No control to choose co-sell. (API supports `co_sell`.) Unblock when the wizard exposes a deal-type selector with co-sell. #### PARTNER_UI_MY_PIPELINE_011 | T57: 4.4
C58: PARTNER_UI_MY_PIPELINE_011 | D58: 12060211 | E58: Confirm - Review registration summary - All entered data is displayed | F58: Functional | G58: P1 | H58: Major | I58: =IF(K58="No",J58,IF(OR(J58="FAILED",L58="FAILED"),"FAILED",IF(OR(J58="PASSED",L58="PASSED"),"PASSED",IF(OR(J58="IN_PROGRESS",L58="IN_PROGRESS"),"IN_PROGRESS",IF(OR(J58="BLOCKED",L58="BLOCKED"),"BLOCKED","NOT_STARTED"))))) -> PASSED | J58: NOT_STARTED | K58: YES | L58: PASSED | M58: §4.4 | N58: partner-platform-prd-v1.8.md | P58: Trang Le | Q58: PASSED — verified 2026-07-27 (TC 12060211). Uses 4 unique text inputs (company/domain/contact/email) asserted verbatim on the Summary → strong proof the entered data is displayed. Verified pre-submit (no submit → no side-effect). Idempotency: N/A. | R58: The review Summary (step 3) displays all entered data. Fills the wizard with known unique values (company / domain / contact name / email) + deal info, reaches the Summary, and confirms every entered value is shown for review. Verified at the Summary (pre-submit); no submit → no deal created. | S58: **Setup (precondition):** Open the wizard; fill step 1 (company/domain/country/contact) + Deal info (plan/seats/region/expected close date) with known data. **Test Steps:** 1. Summary shows the entered COMPANY + CONTACT values. → Expected: the unique company name, domain, contact name, and email are all visible on the Summary. 2. Summary shows the DEAL section fields. → Expected: Deal type = **Referral**, plus Expected close date, Plan source, and Country rows are shown. **Expected (overall):** The Summary reflects every entered value for review before submission. | T58: 4.4
C59: PARTNER_UI_MY_PIPELINE_012 | D59: 12060212 | E59: Submit - Valid deal registration - Success response appears within 2 seconds | F59: Performance | G59: P1 | H59: Critical | I59: =IF(K59="No",J59,IF(OR(J59="FAILED",L59="FAILED"),"FAILED",IF(OR(J59="PASSED",L59="PASSED"),"PASSED",IF(OR(J59="IN_PROGRESS",L59="IN_PROGRESS"),"IN_PROGRESS",IF(OR(J59="BLOCKED",L59="BLOCKED"),"BLOCKED","NOT_STARTED"))))) -> PASSED | J59: NOT_STARTED | K59: YES | L59: PASSED | M59: §4.4 | N59: partner-platform-prd-v1.8.md | P59: Trang Le | Q59: PASSED — verified 2026-07-27 (TC 12060212; observed ~642 ms). Measures the register API round-trip (server + network), not full UI render. Side-effect: submitting creates a real deal (no delete API — see _005; deal id logged in the run). A staging blip can push it over 2s → re-run before filing a perf bug. Idempotency: N/A here (duplicate-register is _022). | R59: Performance — a valid deal registration returns a success response within 2 seconds. Submits the full wizard with a valid (available) domain and measures the register API's own network round-trip. | S59: **Setup (precondition):** Open the wizard; fill step 1 (company/domain/country/contact) + Deal info (plan/seats/region/expected close date) with a unique available domain. **Test Steps:** 1. Submit the deal. → Expected: `POST /v1/partner/portal/deals` returns **2xx** (201) with a deal id. 2. Measure the response time. → Expected: the request→response round-trip is **< 2000 ms** (measured from the request's network timing: responseEnd − requestStart; excludes UI render). **Expected (overall):** A valid registration succeeds and the API responds within the 2s budget. | T59: 4.4
C60: PARTNER_UI_MY_PIPELINE_013 | D60: 12060213 | E60: Complete - Registration on mobile viewport - Flow can finish under 90 seconds | F60: Performance | G60: P1 | H60: Critical | I60: =IF(K60="No",J60,IF(OR(J60="FAILED",L60="FAILED"),"FAILED",IF(OR(J60="PASSED",L60="PASSED"),"PASSED",IF(OR(J60="IN_PROGRESS",L60="IN_PROGRESS"),"IN_PROGRESS",IF(OR(J60="BLOCKED",L60="BLOCKED"),"BLOCKED","NOT_STARTED"))))) -> PASSED | J60: NOT_STARTED | K60: YES | L60: PASSED | M60: §4.4 | N60: partner-platform-prd-v1.8.md | P60: Trang Le | Q60: PASSED — verified 2026-07-27 (TC 12060213; observed ~6 s, well under 90 s). All wizard controls (dropdowns, date picker, submit) work at 375×812. Side-effect: submitting creates a real deal (no delete API — see _005; deal id logged). Partner UI login can flake (login page slow to render) → the run may BLOCK on a login timeout; re-run. Idempotency: N/A. | R60: Performance/mobile — the deal registration flow finishes under 90 seconds on a mobile viewport (375×812). Completes the full wizard and submits at mobile width, timing the whole flow (open wizard → submitted). | S60: **Setup (precondition):** Resize the page to 375×812; open the wizard. **Test Steps:** 1. At mobile width, fill step 1 (company/domain/country/contact) and advance. 2. Fill Deal info (plan/seats/region/expected close date) and advance to Summary. 3. Submit → the register succeeds and the whole flow completes within budget. → Expected: `POST /v1/partner/portal/deals` 2xx (201); elapsed from opening the wizard to the success response is **< 90 s**. **Expected (overall):** The registration is completable on mobile within 90 seconds. | T60: 4.4
B61: Pipeline Management | C61: PARTNER_UI_MY_PIPELINE_014 | D61: 12060214 | E61: List - Open My Pipeline - All deal stages and counts are visible | F61: Functional | G61: P1 | H61: Major | I61: =IF(K61="No",J61,IF(OR(J61="FAILED",L61="FAILED"),"FAILED",IF(OR(J61="PASSED",L61="PASSED"),"PASSED",IF(OR(J61="IN_PROGRESS",L61="IN_PROGRESS"),"IN_PROGRESS",IF(OR(J61="BLOCKED",L61="BLOCKED"),"BLOCKED","NOT_STARTED"))))) -> PASSED | J61: NOT_STARTED | K61: YES | L61: PASSED | M61: §4.5 | N61: partner-platform-prd-v1.8.md | P61: Trang Le | Q61: PASSED — verified 2026-07-24 (TC 12060214). All 6 stages render with counts (0 on the empty test pipeline); summary + Register CTA visible. First MY_PIPELINE content test — establishes the `DealsPage` page-object (stage tabs, counts, controls) reused by the filter/card TCs (_024/_025/_026/_027/_033). Negative counterpart: N/A — a read-only view has no invalid-input surface. Idempotency: N/A — read-only (creates nothing). | R61: Open My Pipeline (the Deals page) and confirm all deal stages and their counts are visible — the pipeline shows the 6 stage tabs (All / Pending / Approved / Won / Lost / Expired), each with a numeric deal count, plus the pipeline summary and the Register CTA. Read-only: works with an empty pipeline (counts may be 0) — it verifies the stages RENDER, not any specific data. | S61: **Setup (precondition):** Log in once as the configured channel-partner user; open `/deals` via the shell and wait for the "Deal Pipeline" READY_MARKER. **Test Steps:** 1. All 6 pipeline stage tabs are visible. → Expected: All, Pending, Approved, Won, Lost, Expired tabs all render (role=tab). 2. Every stage tab shows a numeric deal count. → Expected: each tab shows an integer count ≥ 0 (e.g. "All 0"). 3. Pipeline summary + Register CTA are visible. → Expected: "… deals in your pipeline" summary and the "Register a deal" button are visible. **Expected (overall):** The pipeline renders all 6 stages with counts + summary + Register CTA (independent of how many deals exist). | T61: 4.5
C62: PARTNER_UI_MY_PIPELINE_015 | E62: Open - Deal detail timeline - Registration and approval history is shown | F62: Functional | G62: P1 | H62: Major | I62: =IF(K62="No",J62,IF(OR(J62="FAILED",L62="FAILED"),"FAILED",IF(OR(J62="PASSED",L62="PASSED"),"PASSED",IF(OR(J62="IN_PROGRESS",L62="IN_PROGRESS"),"IN_PROGRESS",IF(OR(J62="BLOCKED",L62="BLOCKED"),"BLOCKED","NOT_STARTED"))))) -> BLOCKED | J62: BLOCKED | K62: NO | L62: NOT_STARTED | M62: §4.5, §9.4 | N62: partner-platform-prd-v1.8.md | P62: Trang Le | Q62: deal detail timeline / approval history: deals-list 400 "Invalid id: 'pro-v1'" → pipeline empty, no deal to open; same BE defect as _024 | T62: 4.5
C63: PARTNER_UI_MY_PIPELINE_016 | E63: Accept - Co-sell override proposal - Partner acceptance is recorded | F63: Functional | G63: P1 | H63: Critical | I63: =IF(K63="No",J63,IF(OR(J63="FAILED",L63="FAILED"),"FAILED",IF(OR(J63="PASSED",L63="PASSED"),"PASSED",IF(OR(J63="IN_PROGRESS",L63="IN_PROGRESS"),"IN_PROGRESS",IF(OR(J63="BLOCKED",L63="BLOCKED"),"BLOCKED","NOT_STARTED"))))) -> BLOCKED | J63: BLOCKED | K63: NO | L63: NOT_STARTED | M63: §3 Scenario C, §5.2, §8.5 | N63: partner-platform-prd-v1.8.md | P63: Trang Le | Q63: accept co-sell override proposal: co-sell deal type not offered in the wizard + needs a proposal; feature absent | T63: 3-C
C64: PARTNER_UI_MY_PIPELINE_017 | E64: Block - Co-sell override under or equal $100K ACV - Override option is unavailable | F64: Negative | G64: P1 | H64: Major | I64: =IF(K64="No",J64,IF(OR(J64="FAILED",L64="FAILED"),"FAILED",IF(OR(J64="PASSED",L64="PASSED"),"PASSED",IF(OR(J64="IN_PROGRESS",L64="IN_PROGRESS"),"IN_PROGRESS",IF(OR(J64="BLOCKED",L64="BLOCKED"),"BLOCKED","NOT_STARTED"))))) -> BLOCKED | J64: BLOCKED | K64: NO | L64: NOT_STARTED | M64: §3 Scenario C, §5.2 | N64: partner-platform-prd-v1.8.md | P64: Trang Le | Q64: Negative: co-sell override ≤ $100K unavailable: co-sell not offered in the UI | T64: 3-C
C65: PARTNER_UI_MY_PIPELINE_018 | E65: Require - Co-sell override above $100K ACV - Partner written agreement is required | F65: Functional | G65: P1 | H65: Critical | I65: =IF(K65="No",J65,IF(OR(J65="FAILED",L65="FAILED"),"FAILED",IF(OR(J65="PASSED",L65="PASSED"),"PASSED",IF(OR(J65="IN_PROGRESS",L65="IN_PROGRESS"),"IN_PROGRESS",IF(OR(J65="BLOCKED",L65="BLOCKED"),"BLOCKED","NOT_STARTED"))))) -> BLOCKED | J65: BLOCKED | K65: NO | L65: NOT_STARTED | M65: §3 Scenario C, §5.2 | N65: partner-platform-prd-v1.8.md | P65: Trang Le | Q65: co-sell override > $100K requires written agreement: co-sell not offered in the UI | T65: 3-C
B66: Deal Registration | C66: PARTNER_UI_MY_PIPELINE_019 | E66: Enrich - Blur valid domain - Company enrichment data is populated | F66: Functional | G66: P2 | H66: Major | I66: =IF(K66="No",J66,IF(OR(J66="FAILED",L66="FAILED"),"FAILED",IF(OR(J66="PASSED",L66="PASSED"),"PASSED",IF(OR(J66="IN_PROGRESS",L66="IN_PROGRESS"),"IN_PROGRESS",IF(OR(J66="BLOCKED",L66="BLOCKED"),"BLOCKED","NOT_STARTED"))))) -> BLOCKED | J66: BLOCKED | K66: NO | L66: NOT_STARTED | M66: §4.4, §8.5 | N66: partner-platform-prd-v1.8.md | P66: Trang Le | Q66: enrich on blur valid domain: no enrichment feature — verified live 2026-07-30, Headcount is a manual "Select range" dropdown + Logo is a manual URL field; blur only derives the tenant subdomain | T66: 4.4
C67: PARTNER_UI_MY_PIPELINE_020 | E67: Select - Choose modules of interest - Selected modules persist to confirmation | F67: Functional | G67: P2 | H67: Major | I67: =IF(K67="No",J67,IF(OR(J67="FAILED",L67="FAILED"),"FAILED",IF(OR(J67="PASSED",L67="PASSED"),"PASSED",IF(OR(J67="IN_PROGRESS",L67="IN_PROGRESS"),"IN_PROGRESS",IF(OR(J67="BLOCKED",L67="BLOCKED"),"BLOCKED","NOT_STARTED"))))) -> BLOCKED | J67: BLOCKED | K67: NO | L67: NOT_STARTED | M67: §4.4 | N67: partner-platform-prd-v1.8.md | P67: Trang Le | Q67: choose modules of interest: no modules-of-interest selection in the wizard — verified live 2026-07-30, step 2 has deal type/plan/seats/region/close date only | T67: 4.4
C68: PARTNER_UI_MY_PIPELINE_021 | E68: Register - Conflict-lost prospect after 90 days - New registration path is available | F68: Functional | G68: P2 | H68: Major | I68: =IF(K68="No",J68,IF(OR(J68="FAILED",L68="FAILED"),"FAILED",IF(OR(J68="PASSED",L68="PASSED"),"PASSED",IF(OR(J68="IN_PROGRESS",L68="IN_PROGRESS"),"IN_PROGRESS",IF(OR(J68="BLOCKED",L68="BLOCKED"),"BLOCKED","NOT_STARTED"))))) -> BLOCKED | J68: BLOCKED | K68: NO | L68: NOT_STARTED | M68: §3 Scenario D, §4.4 | N68: partner-platform-prd-v1.8.md | P68: Trang Le | Q68: register conflict-lost prospect after 90 days: needs a conflict-lost deal aged 90 days — time-based data not available | T68: 4.4
C69: PARTNER_UI_MY_PIPELINE_022 | E69: Block - No deal registration by either partner - Commission is not awarded to any party | F69: Negative | G69: P2 | H69: Major | I69: =IF(K69="No",J69,IF(OR(J69="FAILED",L69="FAILED"),"FAILED",IF(OR(J69="PASSED",L69="PASSED"),"PASSED",IF(OR(J69="IN_PROGRESS",L69="IN_PROGRESS"),"IN_PROGRESS",IF(OR(J69="BLOCKED",L69="BLOCKED"),"BLOCKED","NOT_STARTED"))))) -> BLOCKED | J69: BLOCKED | K69: NO | L69: NOT_STARTED | M69: §3 Scenario I | N69: partner-platform-prd-v1.8.md | P69: Trang Le | Q69: Negative: no registration by either partner → commission not awarded: behavioural/backend outcome, no partner-UI action to exercise | T69: 3-I
C70: PARTNER_UI_MY_PIPELINE_023 | E70: Register - Reseller deal type - End-client price field is absent | F70: Functional | G70: P1 | H70: Critical | I70: =IF(K70="No",J70,IF(OR(J70="FAILED",L70="FAILED"),"FAILED",IF(OR(J70="PASSED",L70="PASSED"),"PASSED",IF(OR(J70="IN_PROGRESS",L70="IN_PROGRESS"),"IN_PROGRESS",IF(OR(J70="BLOCKED",L70="BLOCKED"),"BLOCKED","NOT_STARTED"))))) -> BLOCKED | J70: BLOCKED | K70: NO | L70: NOT_STARTED | M70: §1.2, §3 Scenario B, §4.4 | N70: partner-platform-prd-v1.8.md | P70: Trang Le | Q70: reseller deal → end-client price field absent: reseller deal type not offered in the wizard; feature absent | T70: 3-B
B71: Pipeline Management | C71: PARTNER_UI_MY_PIPELINE_024 | D71: 12060224 | E71: Click - Pipeline deal row - Deal Detail drawer opens | F71: Functional | G71: P2 | H71: Major | I71: =IF(K71="No",J71,IF(OR(J71="FAILED",L71="FAILED"),"FAILED",IF(OR(J71="PASSED",L71="PASSED"),"PASSED",IF(OR(J71="IN_PROGRESS",L71="IN_PROGRESS"),"IN_PROGRESS",IF(OR(J71="BLOCKED",L71="BLOCKED"),"BLOCKED","NOT_STARTED"))))) -> PASSED | J71: NOT_STARTED | K71: YES | L71: PASSED | M71: §4.3, §4.5 | N71: partner-platform-prd-v1.8.md | P71: Trang Le | Q71: PASSED — verified 2026-10-14 (TC 12060224). Unblocked after the BE fixed `GET /v1/partner/portal/deals` (was 400 "Invalid id: 'pro-v1'" on legacy-slug plan refs) — re-probed live 2026-10-02: 200, 20 rows/page, total 102. Negative/Idempotency: N/A — read-only view. | R71: Click a deal row in My Pipeline and confirm the Deal Detail drawer opens in place (no route change). | S71: **Setup (precondition):** Log in once as the shared channel-partner user (a partner WITH deals — 102 live on 2026-10-02); open `/deals` via the shell, wait for the "Deal Pipeline" READY_MARKER and for the deals list to settle. **Test Steps:** 1. Click the first deal row → the Deal Detail drawer opens. → Expected: a dialog with the heading "Deal Detail" becomes visible. 2. The drawer opens in place (URL stays on /deals). → Expected: the page URL is unchanged — detail is a drawer, not a new route. **Teardown:** none — read-only. **Expected (overall):** a deal row opens its detail drawer on the pipeline page. | T71: 46085
C72: PARTNER_UI_MY_PIPELINE_025 | D72: 12060225 | E72: Click - Filter button - Filter builder popover opens | F72: Functional | G72: P2 | H72: Major | I72: =IF(K72="No",J72,IF(OR(J72="FAILED",L72="FAILED"),"FAILED",IF(OR(J72="PASSED",L72="PASSED"),"PASSED",IF(OR(J72="IN_PROGRESS",L72="IN_PROGRESS"),"IN_PROGRESS",IF(OR(J72="BLOCKED",L72="BLOCKED"),"BLOCKED","NOT_STARTED"))))) -> PASSED | J72: NOT_STARTED | K72: YES | L72: PASSED | M72: §4.5 | N72: partner-platform-prd-v1.8.md | P72: Trang Le | Q72: PASSED — verified 2026-10-14 (TC 12060225). Unblocked after the BE fixed `GET /v1/partner/portal/deals` (was 400 "Invalid id: 'pro-v1'" on legacy-slug plan refs) — re-probed live 2026-10-02: 200, 20 rows/page, total 102. **Re-scoped:** the original intent was "filter by company text", but the portal has **no free-text search box** — filtering is a radix "builder" (field combobox, default Deal Type, + Add Filter). This TC covers the entry point; applying a filter and asserting narrowed results needs a dedicated builder-interaction spec (follow-up). Real list narrowing is covered by _035 (stage control). Negative/Idempotency: N/A — read-only. | R72: Open the Filter control on My Pipeline and confirm the filter builder popover opens. | S72: **Setup (precondition):** Log in once as the shared channel-partner user (a partner WITH deals — 102 live on 2026-10-02); open `/deals` via the shell, wait for the "Deal Pipeline" READY_MARKER and for the deals list to settle. **Test Steps:** 1. Click Filter → the filter popover opens. → Expected: the radix filter popover is visible. 2. The popover exposes the filter builder ('Add Filter' control). → Expected: an "Add Filter" control is present inside the popover. **Teardown:** none — read-only. **Expected (overall):** the advanced-filter entry point opens and is interactive. | T72: 46146
C73: PARTNER_UI_MY_PIPELINE_026 | D73: 12060226 | E73: Filter - Select deal type - Pipeline list is filtered | F73: Functional | G73: P2 | H73: Major | I73: =IF(K73="No",J73,IF(OR(J73="FAILED",L73="FAILED"),"FAILED",IF(OR(J73="PASSED",L73="PASSED"),"PASSED",IF(OR(J73="IN_PROGRESS",L73="IN_PROGRESS"),"IN_PROGRESS",IF(OR(J73="BLOCKED",L73="BLOCKED"),"BLOCKED","NOT_STARTED"))))) -> BLOCKED | J73: BLOCKED | K73: NO | L73: NOT_STARTED | M73: §4.5 | N73: partner-platform-prd-v1.8.md | P73: Trang Le | Q73: filter by deal type: deals-list 400 → pipeline empty; a Filter button exists but filtering can't be verified with 0 deals; same BE defect as _024/_025 | T73: 4.5
C74: PARTNER_UI_MY_PIPELINE_027 | D74: 12060227 | E74: Filter - Select module - Pipeline list is filtered | F74: Functional | G74: P2 | H74: Major | I74: =IF(K74="No",J74,IF(OR(J74="FAILED",L74="FAILED"),"FAILED",IF(OR(J74="PASSED",L74="PASSED"),"PASSED",IF(OR(J74="IN_PROGRESS",L74="IN_PROGRESS"),"IN_PROGRESS",IF(OR(J74="BLOCKED",L74="BLOCKED"),"BLOCKED","NOT_STARTED"))))) -> BLOCKED | J74: BLOCKED | K74: NO | L74: NOT_STARTED | M74: §4.5 | N74: partner-platform-prd-v1.8.md | P74: Trang Le | Q74: filter by module: same deals-list 400 + no "module" concept in the deal model/wizard | T74: 4.5
C75: PARTNER_UI_MY_PIPELINE_028 | D75: 12060228 | E75: Add - Deal shared note - Note appears with author and timestamp | F75: Functional | G75: P2 | H75: Major | I75: =IF(K75="No",J75,IF(OR(J75="FAILED",L75="FAILED"),"FAILED",IF(OR(J75="PASSED",L75="PASSED"),"PASSED",IF(OR(J75="IN_PROGRESS",L75="IN_PROGRESS"),"IN_PROGRESS",IF(OR(J75="BLOCKED",L75="BLOCKED"),"BLOCKED","NOT_STARTED"))))) -> BLOCKED | J75: BLOCKED | K75: NO | L75: NOT_STARTED | M75: §3 Scenario C, §4.5 | N75: partner-platform-prd-v1.8.md | P75: Trang Le | Q75: add shared note to a deal: no deal detail — deals-list 400, pipeline empty, no deal to open | T75: 3-C
C76: PARTNER_UI_MY_PIPELINE_029 | D76: 12060229 | E76: Upload - Deal document - Document appears in deal detail | F76: Functional | G76: P2 | H76: Major | I76: =IF(K76="No",J76,IF(OR(J76="FAILED",L76="FAILED"),"FAILED",IF(OR(J76="PASSED",L76="PASSED"),"PASSED",IF(OR(J76="IN_PROGRESS",L76="IN_PROGRESS"),"IN_PROGRESS",IF(OR(J76="BLOCKED",L76="BLOCKED"),"BLOCKED","NOT_STARTED"))))) -> BLOCKED | J76: BLOCKED | K76: NO | L76: NOT_STARTED | M76: §4.5 | N76: partner-platform-prd-v1.8.md | P76: Trang Le | Q76: upload document to a deal: no deal detail — same as _028 | T76: 4.5
C77: PARTNER_UI_MY_PIPELINE_030 | D77: 12060230 | E77: View - Assigned BlazeUp rep - Name, photo, email, and scheduling CTA are visible | F77: Functional | G77: P2 | H77: Major | I77: =IF(K77="No",J77,IF(OR(J77="FAILED",L77="FAILED"),"FAILED",IF(OR(J77="PASSED",L77="PASSED"),"PASSED",IF(OR(J77="IN_PROGRESS",L77="IN_PROGRESS"),"IN_PROGRESS",IF(OR(J77="BLOCKED",L77="BLOCKED"),"BLOCKED","NOT_STARTED"))))) -> BLOCKED | J77: BLOCKED | K77: NO | L77: NOT_STARTED | M77: §3 Scenario A, §4.5 | N77: partner-platform-prd-v1.8.md | P77: Trang Le | Q77: view assigned BlazeUp rep: a rep is assigned on SA approval (blocked by BUG-025) + deals-list 400, no deal to open | T77: 3-A
C78: PARTNER_UI_MY_PIPELINE_031 | D78: 12060231 | E78: Request - Manual protection extension - Request is submitted with reason | F78: Functional | G78: P2 | H78: Major | I78: =IF(K78="No",J78,IF(OR(J78="FAILED",L78="FAILED"),"FAILED",IF(OR(J78="PASSED",L78="PASSED"),"PASSED",IF(OR(J78="IN_PROGRESS",L78="IN_PROGRESS"),"IN_PROGRESS",IF(OR(J78="BLOCKED",L78="BLOCKED"),"BLOCKED","NOT_STARTED"))))) -> BLOCKED | J78: BLOCKED | K78: NO | L78: NOT_STARTED | M78: §5.2, §8.5 | N78: partner-platform-prd-v1.8.md | P78: Trang Le | Q78: request manual protection extension: needs an approved deal with a running protection clock + deal detail — deals-list 400 / no SA approval | T78: 5.2
C79: PARTNER_UI_MY_PIPELINE_032 | D79: 12060232 | E79: List - My Pipeline deals table - Rows and expected columns render | F79: Functional | G79: P1 | H79: Major | I79: =IF(K79="No",J79,IF(OR(J79="FAILED",L79="FAILED"),"FAILED",IF(OR(J79="PASSED",L79="PASSED"),"PASSED",IF(OR(J79="IN_PROGRESS",L79="IN_PROGRESS"),"IN_PROGRESS",IF(OR(J79="BLOCKED",L79="BLOCKED"),"BLOCKED","NOT_STARTED"))))) -> PASSED | J79: NOT_STARTED | K79: YES | L79: PASSED | M79: §4.5 | N79: partner-platform-prd-v1.8.md | P79: Trang Le | Q79: PASSED — verified 2026-10-14 (TC 12060234). New TC (2026-10-14) — numbered _034 because _015-_033 are reserved for other scenarios. Negative/Idempotency: N/A — read-only. | R79: On a partner with deals, the My Pipeline deals table renders rows and the expected columns. | S79: **Setup (precondition):** Log in once as the shared channel-partner user (a partner WITH deals — 102 live on 2026-10-02); open `/deals` via the shell, wait for the "Deal Pipeline" READY_MARKER and for the deals list to settle. **Test Steps:** 1. The deals table shows the expected column headers. → Expected: headers include DEAL ID, DOMAIN, DEAL TYPE, ESTIMATED ACV, STATUS. 2. At least one deal row is rendered. → Expected: ≥ 1 data row (not the "No deals found" empty state). 3. The first row carries a Deal ID and a STATUS value. → Expected: both cells are non-empty. **Teardown:** none — read-only. **Expected (overall):** the deals list renders (the regression that blocked _024/_025). | T79: 46146
C80: PARTNER_UI_MY_PIPELINE_033 | D80: 12060233 | E80: Click - Pipeline stage control - List filters to that status | F80: Functional | G80: P2 | H80: Major | I80: =IF(K80="No",J80,IF(OR(J80="FAILED",L80="FAILED"),"FAILED",IF(OR(J80="PASSED",L80="PASSED"),"PASSED",IF(OR(J80="IN_PROGRESS",L80="IN_PROGRESS"),"IN_PROGRESS",IF(OR(J80="BLOCKED",L80="BLOCKED"),"BLOCKED","NOT_STARTED"))))) -> PASSED | J80: NOT_STARTED | K80: YES | L80: PASSED | M80: §4.5 | N80: partner-platform-prd-v1.8.md | P80: Trang Le | Q80: PASSED — verified 2026-10-14 (TC 12060235). Stage controls are BUTTONS "&lt;Stage&gt; &lt;count&gt;" (All/Pending/Approved/In Progress/Won/Lost/Expired). Negative/Idempotency: N/A — read-only. | R80: A pipeline stage control filters the list to that status. | S80: **Setup (precondition):** Log in once as the shared channel-partner user (a partner WITH deals — 102 live on 2026-10-02); open `/deals` via the shell, wait for the "Deal Pipeline" READY_MARKER and for the deals list to settle. **Test Steps:** 1. Pick a non-empty stage that fits on one page (1..20 deals). → Expected: a non-'All' stage button whose count is 1..20 exists. 2. Click the stage and the list shows exactly its deals. → Expected: rendered row count equals the stage's count (polled — the table re-renders client-side). 3. Every rendered row has that stage's STATUS. → Expected: each row's STATUS matches the stage. **Teardown:** none — read-only. **Expected (overall):** stage controls narrow the list correctly. | T80: 46146
C81: PARTNER_UI_MY_PIPELINE_034 | D81: 12060234 | E81: Click - Pipeline deal row - Detail drawer shows the clicked deal's info | F81: Functional | G81: P2 | H81: Major | I81: =IF(K81="No",J81,IF(OR(J81="FAILED",L81="FAILED"),"FAILED",IF(OR(J81="PASSED",L81="PASSED"),"PASSED",IF(OR(J81="IN_PROGRESS",L81="IN_PROGRESS"),"IN_PROGRESS",IF(OR(J81="BLOCKED",L81="BLOCKED"),"BLOCKED","NOT_STARTED"))))) -> PASSED | J81: NOT_STARTED | K81: YES | L81: PASSED | M81: §4.5 | N81: partner-platform-prd-v1.8.md | P81: Trang Le | Q81: PASSED — verified 2026-10-14 (TC 12060236). Negative/Idempotency: N/A — read-only. | R81: The Deal Detail drawer shows the clicked deal's info. | S81: **Setup (precondition):** Log in once as the shared channel-partner user (a partner WITH deals — 102 live on 2026-10-02); open `/deals` via the shell, wait for the "Deal Pipeline" READY_MARKER and for the deals list to settle. **Test Steps:** 1. The drawer shows the DEAL INFO and COMPANY INFO sections. → Expected: both section headings are visible in the drawer (opened from the first row in Setup). 2. The drawer reflects the clicked deal (its company/domain text appears). → Expected: a token from the row's DOMAIN cell appears inside the Deal Detail dialog. **Teardown:** none — read-only. **Expected (overall):** the drawer shows the deal that was clicked, not a blank shell. | T81: 46146
C82: PARTNER_UI_MY_PIPELINE_035 | D82: 12060235 | E82: Paginate - Go to page 2 - A different set of deals loads | F82: Functional | G82: P2 | H82: Major | I82: =IF(K82="No",J82,IF(OR(J82="FAILED",L82="FAILED"),"FAILED",IF(OR(J82="PASSED",L82="PASSED"),"PASSED",IF(OR(J82="IN_PROGRESS",L82="IN_PROGRESS"),"IN_PROGRESS",IF(OR(J82="BLOCKED",L82="BLOCKED"),"BLOCKED","NOT_STARTED"))))) -> PASSED | J82: NOT_STARTED | K82: YES | L82: PASSED | M82: §4.5 | N82: partner-platform-prd-v1.8.md | P82: Trang Le | Q82: PASSED — verified 2026-10-14 (TC 12060238). Footer: "Showing 1 - 20 of 102 | 20 / page | 1..6 | Go to page". Negative/Idempotency: N/A — read-only. | R82: Pagination — page 2 loads a different set of deals. | S82: **Setup (precondition):** Log in once as the shared channel-partner user (a partner WITH deals — 102 live on 2026-10-02); open `/deals` via the shell, wait for the "Deal Pipeline" READY_MARKER and for the deals list to settle. More than one page of deals (All &gt; 20); otherwise the TC reports BLOCKED. **Test Steps:** 1. Jump to page 2 → a new page of deals loads. → Expected: via the "Go to page" input, the first row changes and rows still render. 2. Page 2's first deal differs from page 1. → Expected: page-2 first Deal ID ≠ page-1 first Deal ID. **Teardown:** none — read-only. **Expected (overall):** paging through the pipeline loads new rows. | T82: 46146
C83: PARTNER_UI_MY_PIPELINE_036 | D83: 12060236 | E83: List - Deal rows - DEAL TYPE / ESTIMATED ACV / STATUS are well-formed | F83: Functional | G83: P2 | H83: Major | I83: =IF(K83="No",J83,IF(OR(J83="FAILED",L83="FAILED"),"FAILED",IF(OR(J83="PASSED",L83="PASSED"),"PASSED",IF(OR(J83="IN_PROGRESS",L83="IN_PROGRESS"),"IN_PROGRESS",IF(OR(J83="BLOCKED",L83="BLOCKED"),"BLOCKED","NOT_STARTED"))))) -> PASSED | J83: NOT_STARTED | K83: YES | L83: PASSED | M83: §4.5 | N83: partner-platform-prd-v1.8.md | P83: Trang Le | Q83: PASSED — verified 2026-10-14 (TC 12060239). Soft-collect (`soft=gaps`) so one bad row never hides others. Negative/Idempotency: N/A — read-only. | R83: Each deal row's DEAL TYPE / ESTIMATED ACV / STATUS are well-formed. | S83: **Setup (precondition):** Log in once as the shared channel-partner user (a partner WITH deals — 102 live on 2026-10-02); open `/deals` via the shell, wait for the "Deal Pipeline" READY_MARKER and for the deals list to settle. **Test Steps:** (one step per row, first ≤ 5 rows; failures collected) 1..N. Row i: DEAL TYPE / ESTIMATED ACV / STATUS are valid. → Expected: DEAL TYPE ∈ Referral/Reseller/Co-sell; ESTIMATED ACV contains an amount; STATUS ∈ Pending/Approved/Won/Lost/Expired/In Progress/Registered. **Teardown:** none — read-only. **Expected (overall):** the typed columns render valid values on every row. | T83: 46146
C84: PARTNER_UI_MY_PIPELINE_037 | D84: 12060237 | E84: Click - Zero-count stage - 'No deals found' empty state is shown | F84: Functional | G84: P2 | H84: Major | I84: =IF(K84="No",J84,IF(OR(J84="FAILED",L84="FAILED"),"FAILED",IF(OR(J84="PASSED",L84="PASSED"),"PASSED",IF(OR(J84="IN_PROGRESS",L84="IN_PROGRESS"),"IN_PROGRESS",IF(OR(J84="BLOCKED",L84="BLOCKED"),"BLOCKED","NOT_STARTED"))))) -> FAILED | J84: NOT_STARTED | K84: YES | L84: FAILED | M84: §4.5 | N84: partner-platform-prd-v1.8.md | O84: BUG-API-043 | P84: Trang Le | Q84: PASSED — verified 2026-10-14 (TC 12060240). Negative/Idempotency: N/A — read-only. Numbered _040: _037 is reserved in the Excel test plan (reseller billing tag). | R84: A zero-count stage shows the "No deals found" empty state. | S84: **Setup (precondition):** Log in once as the shared channel-partner user (a partner WITH deals — 102 live on 2026-10-02); open `/deals` via the shell, wait for the "Deal Pipeline" READY_MARKER and for the deals list to settle. **Test Steps:** 1. Find a stage with a zero deal count. → Expected: a stage button shows 0 (e.g. In Progress / Lost / Expired). 2. Switching to it shows the 'No deals found' empty state. → Expected: the empty-state message is visible. 3. No deal data rows are listed under the empty stage. → Expected: 0 rows carrying a "D#…" Deal ID (the single placeholder row is the empty-state message). **Teardown:** none — read-only. **Expected (overall):** an empty stage renders a clear empty state, no stale rows. | T84: 46146
B85: Deal Management | C85: PARTNER_UI_MY_PIPELINE_038 | E85: Won - Reseller marks deal Won - Partner self-confirms close without SA approval | F85: Functional | G85: P1 | H85: Critical | I85: =IF(K85="No",J85,IF(OR(J85="FAILED",L85="FAILED"),"FAILED",IF(OR(J85="PASSED",L85="PASSED"),"PASSED",IF(OR(J85="IN_PROGRESS",L85="IN_PROGRESS"),"IN_PROGRESS",IF(OR(J85="BLOCKED",L85="BLOCKED"),"BLOCKED","NOT_STARTED"))))) -> BLOCKED | J85: BLOCKED | K85: NO | L85: NOT_STARTED | M85: §3 Scenario B, §4.4, §5.2 | N85: partner-platform-prd-v1.8.md | P85: Trang Le | Q85: reseller marks deal Won / self-confirm: reseller deal type not offered in the UI | T85: 3-B
B86: Deal List View | C86: PARTNER_UI_MY_PIPELINE_039 | E86: Display - Pipeline deal card - Reseller billing model tag is visible | F86: Functional | G86: P1 | H86: Major | I86: =IF(K86="No",J86,IF(OR(J86="FAILED",L86="FAILED"),"FAILED",IF(OR(J86="PASSED",L86="PASSED"),"PASSED",IF(OR(J86="IN_PROGRESS",L86="IN_PROGRESS"),"IN_PROGRESS",IF(OR(J86="BLOCKED",L86="BLOCKED"),"BLOCKED","NOT_STARTED"))))) -> BLOCKED | J86: BLOCKED | K86: NO | L86: NOT_STARTED | M86: §3 Scenario B, §4.5 | N86: partner-platform-prd-v1.8.md | P86: Trang Le | Q86: pipeline card shows reseller billing tag: deals-list 400 → no card renders + reseller not offered | T86: 3-B
A87: Partner Portal Shell | B87: Navigation & Shell | C87: PARTNER_UI_PARTNER_PORTAL_SHELL_001 | D87: 12060101 | E87: Navigate - Open main menu routes - Correct page content is shown | F87: Functional | G87: P1 | H87: Major | I87: =IF(K87="No",J87,IF(OR(J87="FAILED",L87="FAILED"),"FAILED",IF(OR(J87="PASSED",L87="PASSED"),"PASSED",IF(OR(J87="IN_PROGRESS",L87="IN_PROGRESS"),"IN_PROGRESS",IF(OR(J87="BLOCKED",L87="BLOCKED"),"BLOCKED","NOT_STARTED"))))) -> PASSED | J87: NOT_STARTED | K87: YES | L87: PASSED | M87: §4.2 | N87: partner-platform-prd-v1.8.md | P87: Trang Le | R87: Open every primary nav route of the partner portal shell and confirm each page's content module renders (correct page content shown, no micro-frontend error). One looping test walks all pages via direct URL and soft-collects failures → a single verdict naming any bad page. | S87: **Setup (precondition):** Log in once as the configured channel-partner user (session-cached partner UI login). Warm up the SPA (open Dashboard once) so the first page in the loop isn't charged the one-off bootstrap. **Test Steps:** (each page = one `page.goto(route)` then wait for its READY_MARKER in `<main>`, fast-fail on the "Something went wrong" MFE panel) — primary nav verified live 2026-07-23: 1. Dashboard → `/dashboard` → Expected: page title **"Tier & Performance"** visible in `<main>`, no error panel. 2. Deals → `/deals` → Expected: **"Deal Pipeline"** visible. 3. Commissions → `/commissions` → Expected: **"Commissions"** visible. 4. Resources → `/resources` → Expected: **"Resources"** visible. 5. My Apps → `/apps` → Expected: **"My Apps"** visible. **Expected (overall):** All 5 primary pages render their content module (no MFE error panel); a broken page fast-fails naming which one. | T87: 4.2
B88: Responsive Layout | C88: PARTNER_UI_PARTNER_PORTAL_SHELL_002 | D88: 12060102 | E88: Responsive - Partner portal mobile layout - Controls remain usable | F88: Functional | G88: P2 | H88: Major | I88: =IF(K88="No",J88,IF(OR(J88="FAILED",L88="FAILED"),"FAILED",IF(OR(J88="PASSED",L88="PASSED"),"PASSED",IF(OR(J88="IN_PROGRESS",L88="IN_PROGRESS"),"IN_PROGRESS",IF(OR(J88="BLOCKED",L88="BLOCKED"),"BLOCKED","NOT_STARTED"))))) -> PASSED | J88: NOT_STARTED | K88: YES | L88: PASSED | M88: §4.1, §4.4 | N88: partner-platform-prd-v1.8.md | O88: BUG-UI-010 | P88: Trang Le | Q88: FAILED by design (TC 12060102), verified 2026-07-24. Mobile 375x812. 3/5 pages fit + mobile nav works (icon-bar sidebar, tap routes OK), but Deals (+162px) and My Apps (+263px) overflow horizontally at 375px = responsive-layout defects (content doesn't fit small screens -> sideways scroll). Confirm with FE. Negative N/A (responsive smoke). Idempotency N/A (read-only). | R88: Open the partner portal at a common mobile viewport (375x812) and confirm the shell stays usable on every primary nav page: section renders, sidebar nav reachable, and layout does not overflow horizontally. Then tap a sidebar link to prove mobile navigation works. One looping test reports a single verdict naming any bad page. | S88: **Setup (precondition):** Log in once as the configured channel-partner user; resize the page to 375×812; warm up the SPA (open Dashboard once). **Test Steps:** (per page at mobile width: shell READY_MARKER visible + ≥1 nav link visible + horizontal overflow ≤ 5px scrollbar allowance) — verified live 2026-07-24: 1. Dashboard `/dashboard` → Expected: renders, nav reachable, no h-overflow. → **PASS** (overflow 0px). 2. Deals `/deals` → Expected: no h-overflow. → **FAILS** — content overflows the 375px viewport by **+162px** (tabs/filter/view controls don't fit → sideways scroll). 3. Commissions `/commissions` → Expected: no h-overflow. → **PASS** (0px). 4. Resources `/resources` → Expected: no h-overflow. → **PASS** (0px). 5. My Apps `/apps` → Expected: no h-overflow. → **FAILS** — overflows by **+263px**. 6. Tap sidebar link at mobile → Commissions routes + renders. → **PASS** (mobile nav is usable). **Expected (overall):** Every primary page fits the mobile viewport (no horizontal overflow) with the nav reachable; tapping nav routes correctly. | T88: 4.1
B89: Dual Account Switcher | C89: PARTNER_UI_PARTNER_PORTAL_SHELL_003 | D89: 12060103 | E89: Switch - Dual account partner activates account switcher - Pack and Channel dashboards toggle correctly | F89: Functional | G89: P2 | H89: Major | I89: =IF(K89="No",J89,IF(OR(J89="FAILED",L89="FAILED"),"FAILED",IF(OR(J89="PASSED",L89="PASSED"),"PASSED",IF(OR(J89="IN_PROGRESS",L89="IN_PROGRESS"),"IN_PROGRESS",IF(OR(J89="BLOCKED",L89="BLOCKED"),"BLOCKED","NOT_STARTED"))))) -> BLOCKED | J89: BLOCKED | K89: NO | L89: NOT_STARTED | M89: §3-H | N89: partner-platform-prd-v1.8.md | P89: Trang Le | Q89: Dual-account partner switching between **Pack** and **Channel** dashboards. Cannot automate — the feature and the test data do not exist on staging (verified live 2026-07-24): (a) **no account-switcher control** in the portal shell — the header "Select" is the tier badge (tier=`select`), not an account switcher, and the profile menu only offers Profile/Logout; (b) the logged-in partner is a **single account** — `GET /v1/partner/auth/me` returns one `partnerId` with `type:"channel"`, `tier:"select"`, no accounts array; (c) **no "Pack" concept** — the partner `type` enum is channel/referral/msp/system_integrator (no "pack"), so a Pack↔Channel dual-account cannot even be represented. Unblock when BE ships multi-account membership (one user → a Pack + a Channel account) + a shell account switcher, AND a dual-account test partner is provisioned. | T89: 3-H
A90: Partner Team | B90: Team & Referral Links | C90: PARTNER_UI_PARTNER_TEAM_001 | D90: 12060601 | E90: Invite - Partner team member - Invitation is sent with role | F90: Functional | G90: P2 | H90: Major | I90: =IF(K90="No",J90,IF(OR(J90="FAILED",L90="FAILED"),"FAILED",IF(OR(J90="PASSED",L90="PASSED"),"PASSED",IF(OR(J90="IN_PROGRESS",L90="IN_PROGRESS"),"IN_PROGRESS",IF(OR(J90="BLOCKED",L90="BLOCKED"),"BLOCKED","NOT_STARTED"))))) -> PASSED | J90: NOT_STARTED | K90: YES | L90: PASSED | M90: §4.10 | N90: partner-platform-prd-v1.8.md | P90: Trang Le | Q90: PASSED — verified 2026-07-30 (TC 12060601). Partner-side team management on `/directory` (Invite User → email/name/role → Send → one-time credential → member Active). New config section `PARTNER.ui.PARTNER_TEAM = 6`. Side-effect: each run creates a real Active member (unique `qa.auto+…` email; no UI delete — members accumulate). Negative counterpart: N/A here (could add required-field validation later). Idempotency: N/A (unique email each run). | R90: Invite a partner team member. On the partner Directory (`/directory`), open "Invite User", fill the new member's email + name + role, send the invite, and confirm the invitation is created (one-time credential shown) and the member appears in the team table with its role. | S90: **Setup (precondition):** Log in as the channel-partner user (stgpartners, 2FA); open `/directory` and wait for the "Directory" READY_MARKER. **Test Steps:** 1. The member table + Invite User action render. → Expected: MEMBER / ROLE / STATUS / LAST LOGIN columns + "Invite User" button. 2. The Invite dialog exposes email + name + a role selector. → Expected: Email*, First name*, Last name*, Role (default "Viewer") fields + Send Invite. 3. Send the invite → "User invited" confirmation. → Expected: the credential dialog ("User invited" — one-time temporary password) appears; close via Done. 4. The invited member appears in the Directory with its role. → Expected: a row for the invited email shows role "Viewer" and status Active. **Expected (overall):** The invitation is created with the role and the new member is visible in the Directory. | T90: 4.10
C91: PARTNER_UI_PARTNER_TEAM_002 | E91: Create - Campaign referral link - Link and analytics row are created | F91: Functional | G91: P2 | H91: Major | I91: =IF(K91="No",J91,IF(OR(J91="FAILED",L91="FAILED"),"FAILED",IF(OR(J91="PASSED",L91="PASSED"),"PASSED",IF(OR(J91="IN_PROGRESS",L91="IN_PROGRESS"),"IN_PROGRESS",IF(OR(J91="BLOCKED",L91="BLOCKED"),"BLOCKED","NOT_STARTED"))))) -> BLOCKED | J91: BLOCKED | K91: NO | L91: NOT_STARTED | M91: §4.10, §8.4 | N91: partner-platform-prd-v1.8.md | P91: Trang Le | Q91: create campaign referral link: no referral-link UI found on `/directory`; feature not located on the partner portal — recheck if/when a referral-link area ships | T91: 4.10
C92: PARTNER_UI_PARTNER_TEAM_003 | E92: Copy - Referral link - Clipboard action succeeds | F92: Functional | G92: P3 | H92: Minor | I92: =IF(K92="No",J92,IF(OR(J92="FAILED",L92="FAILED"),"FAILED",IF(OR(J92="PASSED",L92="PASSED"),"PASSED",IF(OR(J92="IN_PROGRESS",L92="IN_PROGRESS"),"IN_PROGRESS",IF(OR(J92="BLOCKED",L92="BLOCKED"),"BLOCKED","NOT_STARTED"))))) -> BLOCKED | J92: BLOCKED | K92: NO | L92: NOT_STARTED | M92: §4.10 | N92: partner-platform-prd-v1.8.md | P92: Trang Le | Q92: copy referral link: same — no referral-link UI found | T92: 4.10
A93: Resources | B93: Resources & Sandbox | C93: PARTNER_UI_RESOURCES_001 | E93: Reset - Demo sandbox - Profile selection and reset confirmation are shown | F93: Functional | G93: P2 | H93: Major | I93: =IF(K93="No",J93,IF(OR(J93="FAILED",L93="FAILED"),"FAILED",IF(OR(J93="PASSED",L93="PASSED"),"PASSED",IF(OR(J93="IN_PROGRESS",L93="IN_PROGRESS"),"IN_PROGRESS",IF(OR(J93="BLOCKED",L93="BLOCKED"),"BLOCKED","NOT_STARTED"))))) -> BLOCKED | J93: BLOCKED | K93: NO | L93: NOT_STARTED | M93: §4.9, §8.3, §12.1 B5 | N93: partner-platform-prd-v1.8.md | P93: Trang Le | Q93: demo sandbox reset: no sandbox UI | T93: 4.9
C94: PARTNER_UI_RESOURCES_002 | E94: Configure - Demo sandbox weekly auto-reset - Toggle is default off with reset warning | F94: Functional | G94: P2 | H94: Major | I94: =IF(K94="No",J94,IF(OR(J94="FAILED",L94="FAILED"),"FAILED",IF(OR(J94="PASSED",L94="PASSED"),"PASSED",IF(OR(J94="IN_PROGRESS",L94="IN_PROGRESS"),"IN_PROGRESS",IF(OR(J94="BLOCKED",L94="BLOCKED"),"BLOCKED","NOT_STARTED"))))) -> BLOCKED | J94: BLOCKED | K94: NO | L94: NOT_STARTED | M94: §4.9, §8.3, §12.1 B5 | N94: partner-platform-prd-v1.8.md | P94: Trang Le | Q94: sandbox weekly auto-reset toggle: no sandbox UI | T94: 4.9
C95: PARTNER_UI_RESOURCES_003 | E95: Download - Marketing resource - Correct file is served | F95: Functional | G95: P3 | H95: Minor | I95: =IF(K95="No",J95,IF(OR(J95="FAILED",L95="FAILED"),"FAILED",IF(OR(J95="PASSED",L95="PASSED"),"PASSED",IF(OR(J95="IN_PROGRESS",L95="IN_PROGRESS"),"IN_PROGRESS",IF(OR(J95="BLOCKED",L95="BLOCKED"),"BLOCKED","NOT_STARTED"))))) -> BLOCKED | J95: BLOCKED | K95: NO | L95: NOT_STARTED | M95: §4.9 | N95: partner-platform-prd-v1.8.md | P95: Trang Le | Q95: download marketing resource: no marketing-assets UI | T95: 4.9
C96: PARTNER_UI_RESOURCES_004 | E96: Generate - Co-branded pitch deck - Partner logo is inserted | F96: Functional | G96: P3 | H96: Minor | I96: =IF(K96="No",J96,IF(OR(J96="FAILED",L96="FAILED"),"FAILED",IF(OR(J96="PASSED",L96="PASSED"),"PASSED",IF(OR(J96="IN_PROGRESS",L96="IN_PROGRESS"),"IN_PROGRESS",IF(OR(J96="BLOCKED",L96="BLOCKED"),"BLOCKED","NOT_STARTED"))))) -> BLOCKED | J96: BLOCKED | K96: NO | L96: NOT_STARTED | M96: §4.9 | N96: partner-platform-prd-v1.8.md | P96: Trang Le | Q96: generate co-branded pitch deck: no generator UI | T96: 4.9
C97: PARTNER_UI_RESOURCES_005 | E97: Open - ROI calculator - Prospect PDF can be generated | F97: Functional | G97: P3 | H97: Minor | I97: =IF(K97="No",J97,IF(OR(J97="FAILED",L97="FAILED"),"FAILED",IF(OR(J97="PASSED",L97="PASSED"),"PASSED",IF(OR(J97="IN_PROGRESS",L97="IN_PROGRESS"),"IN_PROGRESS",IF(OR(J97="BLOCKED",L97="BLOCKED"),"BLOCKED","NOT_STARTED"))))) -> BLOCKED | J97: BLOCKED | K97: NO | L97: NOT_STARTED | M97: §4.9 | N97: partner-platform-prd-v1.8.md | P97: Trang Le | Q97: ROI calculator → prospect PDF: no calculator UI | T97: 4.9
A98: SA Partner Module | B98: Deal Conflict Queue | C98: PARTNER_UI_SA_PARTNER_MODULE_001 | E98: Resolve - Conflict queue with reasoning - Decision is saved and parties notified | F98: Functional | G98: P1 | H98: Critical | I98: =IF(K98="No",J98,IF(OR(J98="FAILED",L98="FAILED"),"FAILED",IF(OR(J98="PASSED",L98="PASSED"),"PASSED",IF(OR(J98="IN_PROGRESS",L98="IN_PROGRESS"),"IN_PROGRESS",IF(OR(J98="BLOCKED",L98="BLOCKED"),"BLOCKED","NOT_STARTED"))))) -> BLOCKED | J98: BLOCKED | K98: NO | L98: NOT_STARTED | M98: §3 Scenario D, §5.2, §9.4 | N98: partner-platform-prd-v1.8.md | P98: Trang Le | Q98: Blocked by the SA Deal Approval Queue backend defect (see _007 / BUG-025). The Conflict Queue (`/partners/deals` → Conflicts tab) fails to load any deals — every tab shows "Server Error — Invalid id: 'pro-v1'" — so no conflicted deal can be opened to resolve. Revisit once BUG-025 is fixed and a two-parties-same-domain conflict fixture exists. | T98: 5.2
C99: PARTNER_UI_SA_PARTNER_MODULE_002 | E99: Resolve - Conflict queue decision - Prospect confirmation and written reasoning are visible | F99: Functional | G99: P1 | H99: Critical | I99: =IF(K99="No",J99,IF(OR(J99="FAILED",L99="FAILED"),"FAILED",IF(OR(J99="PASSED",L99="PASSED"),"PASSED",IF(OR(J99="IN_PROGRESS",L99="IN_PROGRESS"),"IN_PROGRESS",IF(OR(J99="BLOCKED",L99="BLOCKED"),"BLOCKED","NOT_STARTED"))))) -> BLOCKED | J99: BLOCKED | K99: NO | L99: NOT_STARTED | M99: §3 Scenario D, §5.2, §9.4 | N99: partner-platform-prd-v1.8.md | P99: Trang Le | Q99: Same as _001 — the Conflict Queue deal list fails to load (BUG-025), so the conflict-decision detail UI cannot be reached. Needs BUG-025 fixed + a conflict fixture with prospect-confirmation data. | T99: 5.2
B100: Partner Directory | C100: PARTNER_UI_SA_PARTNER_MODULE_003 | D100: 12060503 | E100: Admin - Partner directory loads - Filters and partner rows are visible | F100: Functional | G100: P1 | H100: Critical | I100: =IF(K100="No",J100,IF(OR(J100="FAILED",L100="FAILED"),"FAILED",IF(OR(J100="PASSED",L100="PASSED"),"PASSED",IF(OR(J100="IN_PROGRESS",L100="IN_PROGRESS"),"IN_PROGRESS",IF(OR(J100="BLOCKED",L100="BLOCKED"),"BLOCKED","NOT_STARTED"))))) -> PASSED | J100: NOT_STARTED | K100: YES | L100: PASSED | M100: §5.1 | N100: partner-platform-prd-v1.8.md | P100: Trang Le | Q100: PASSED 2026-07-29 (TC 12060503). First SA_PARTNER_MODULE test; establishes stgsa SA-side surface via ShellPage + new PartnerDirectoryPage (make_page/super-admin, not partner portal). Config PARTNER.ui.SA_PARTNER_MODULE=5. Empty-safe (verified 0 rows + 1 row). Negative/Idempotency: N/A (read-only load). stgsa flapped during verify; passed once stable. | T100: 5.1
C101: PARTNER_UI_SA_PARTNER_MODULE_013 | D101: 12060513 | E101: Open - Partner detail page - Overview, deals, commission, members are visible | F101: Functional | G101: P1 | H101: Major | I101: =IF(K101="No",J101,IF(OR(J101="FAILED",L101="FAILED"),"FAILED",IF(OR(J101="PASSED",L101="PASSED"),"PASSED",IF(OR(J101="IN_PROGRESS",L101="IN_PROGRESS"),"IN_PROGRESS",IF(OR(J101="BLOCKED",L101="BLOCKED"),"BLOCKED","NOT_STARTED"))))) -> PASSED | J101: NOT_STARTED | K101: YES | L101: PASSED | M101: §5.1 | N101: partner-platform-prd-v1.8.md | P101: Trang Le | Q101: Figma design: [PN002] View Partner Detail page. PASSED, verified 2026-07-31 (TC 12060513). Read-only load check (empty-safe). Negative counterpart: N/A — read-only load. Idempotency: N/A. | R101: The SA-side Partner Detail page (stgsa `/partners/<id>`) loads with its detail chrome — the Overview / Deals / Commission / Members tabs, the Tier & Performance + Territory Assignments sections, the partner info (id + type + tier), and the Partner-actions control. | S101: **Setup (precondition):** Log in as super-admin (stgsa); self-seed a throwaway partner via **Onboard Partner** (the Directory list is unreliable on staging), then open its detail. **Test Steps:** 1. The detail tabs render. → Expected: **Overview**, **Deals**, **Commission**, **Members** tabs are visible (Radix `role="tab"`). **(PASSES.)** 2. The Overview sections + partner info render. → Expected: **Tier & Performance** + **Territory Assignments** sections + partner company name + **Channel** type + **PAR-…** id are visible. **(PASSES.)** 3. The Partner-actions control renders. → Expected: the **Partner actions** kebab control is visible on the header. **(PASSES.)** **Expected (overall):** The SA Partner Detail loads with tabs, sections, partner info, and the actions control. | T101: 46027
C102: PARTNER_UI_SA_PARTNER_MODULE_014 | D102: 12060514 | E102: Manage - Partner team member - Deactivate and reactivate a member | F102: Functional | G102: P1 | H102: Major | I102: =IF(K102="No",J102,IF(OR(J102="FAILED",L102="FAILED"),"FAILED",IF(OR(J102="PASSED",L102="PASSED"),"PASSED",IF(OR(J102="IN_PROGRESS",L102="IN_PROGRESS"),"IN_PROGRESS",IF(OR(J102="BLOCKED",L102="BLOCKED"),"BLOCKED","NOT_STARTED"))))) -> PASSED | J102: NOT_STARTED | K102: YES | L102: PASSED | M102: §5.1 | N102: partner-platform-prd-v1.8.md | P102: Trang Le | Q102: Figma design: [PN014] View and manage partner team members. PASSED, verified 2026-08-03 (TC 12060514). Password for the throwaway staging user is generated and never logged. **Scope:** the Members tab exposes only **Add User** (create) + a per-row **Reset Password** action — there is **NO member deactivate / reactivate / suspend / remove** control on this build (verified live 2026-08-03: full row HTML + hover + keyword scan), so the deactivate/reactivate half of the original _014 intent is **not automatable** (UI not implemented). If/when that control ships, extend this TC. Negative counterpart: N/A — happy-path add (form-validation negatives are a separate TC). Idempotency: N/A — each add creates a distinct user (unique email).. | R102: From the SA Partner Detail → **Members** tab, an SA adds a portal user (member) to an active partner; the new user appears in the Portal Users list with **Active** status. | S102: **Setup (precondition):** Log in as super-admin (stgsa); self-seed a throwaway partner, **Approve** it (Pending → Active), open the Members tab. **Test Steps:** 1. The Members tab shows the Portal Users list (empty). → Expected: **Portal Users** heading + an **Add User** / **Add First User** control; empty-state "No portal users yet". **(PASSES.)** 2. Add a portal user (First / Last / Email / Password / Role via the Add-User form → **Create Portal User**). → Expected: **"Portal user created successfully"** confirmation. **(PASSES.)** 3. The new user appears as an Active row. → Expected: the new user's row shows the email + **Viewer** role + **Active** status; the header reads **Portal Users (1)**. **(PASSES.)** **Expected (overall):** An SA can add a portal user to a partner; it appears Active in the Portal Users list.
C103: PARTNER_UI_SA_PARTNER_MODULE_015 | D103: 12060515 | E103: Suspend - Active partner account - Partner is suspended with a reason | F103: Security | G103: P1 | H103: Major | I103: =IF(K103="No",J103,IF(OR(J103="FAILED",L103="FAILED"),"FAILED",IF(OR(J103="PASSED",L103="PASSED"),"PASSED",IF(OR(J103="IN_PROGRESS",L103="IN_PROGRESS"),"IN_PROGRESS",IF(OR(J103="BLOCKED",L103="BLOCKED"),"BLOCKED","NOT_STARTED"))))) -> PASSED | J103: NOT_STARTED | K103: YES | L103: PASSED | M103: §5.1 | N103: partner-platform-prd-v1.8.md | P103: Trang Le | Q103: Figma design: [PN015] Suspend active partner account. | R103: From the SA Partner Detail page, an Active partner is suspended via **Partner actions → Deactivate**. Expected: the partner transitions out of Active (Suspended/Inactive) and portal access is revoked. | S103: **Setup (precondition):** Log in as super-admin (stgsa); self-seed a throwaway partner, **Approve** it (Pending → Active). **Test Steps:** 1. Deactivate (suspend) the active partner — Partner actions → Deactivate → confirm the "Deactivate Partner" dialog. → Expected: the request succeeds. **(FAILS.)** 2. The partner is suspended and no error is shown. → Expected: no error banner; partner is no longer Active (Suspended/Inactive). **(FAILS.)** **Expected (overall):** An SA can suspend an Active partner from the UI; the partner loses portal access.
...

Sheet Regression Suite
A1: REGRESSION SUITE — MODULE STATUS SUMMARY
A2: Item | B2: Description | C2: Summary
A3: TOTAL | B3: Total number of tests | C3: =SUM(C4:C8) -> 119
A4: PASSED | B4: Number of tests PASSED | C4: =COUNTIF('Regression Suite'!G13:G999,"PASSED") -> 0
A5: FAILED | B5: Number of tests FAILED | C5: =COUNTIF('Regression Suite'!G13:G999,"FAILED") -> 0
A6: NOT_STARTED | B6: Number of tests not started | C6: =COUNTIF('Regression Suite'!G13:G999,"NOT_STARTED") -> 118
A7: IN_PROGRESS | B7: Number currently being tested | C7: =COUNTIF('Regression Suite'!G13:G999,"IN_PROGRESS") -> 0
A8: BLOCKED | B8: Tests that could not be executed | C8: =COUNTIF('Regression Suite'!G13:G999,"BLOCKED") -> 1
A11: REGRESSION SUITE — P1 Test Cases (All Modules)
A12: Auto-compiled from all P1 TCs across active modules | Run before every release
A13: TC ID | B13: Module | C13: Test Case Name | D13: Type (UI/API) | E13: Priority | F13: Owner | G13: Automation Status | H13: Automation TC Mapping
A14: Partner Platform
A15: PARTNER_UI_PARTNER_PORTAL_SHELL_001 | B15: Partner Platform | C15: Navigate - Open main menu routes - Correct page content is shown | D15: UI | E15: P1 | F15: Trang Le | G15: NOT_STARTED | H15: tests/ui/partner_002
A16: PARTNER_UI_DASHBOARD_001 | B16: Partner Platform | C16: View - Partner shell loads for channel partner - Dashboard is displayed | D16: UI | E16: P1 | F16: Trang Le | G16: NOT_STARTED | H16: tests/ui/partner_001
A17: PARTNER_UI_DASHBOARD_002 | B17: Partner Platform | C17: Render - Dashboard KPI cards available - Actionable metrics are visible | D17: UI | E17: P1 | F17: Trang Le | G17: NOT_STARTED | H17: tests/ui/partner_003
A18: PARTNER_UI_DASHBOARD_003 | B18: Partner Platform | C18: Render - Tier progress exists on dashboard - Progress to next tier is visible | D18: UI | E18: P1 | F18: Trang Le | G18: NOT_STARTED | H18: tests/ui/partner_004
A19: PARTNER_UI_DASHBOARD_004 | B19: Partner Platform | C19: Render - Action Required list has pending tasks - Partner sees next actions | D19: UI | E19: P1 | F19: Trang Le | G19: NOT_STARTED | H19: tests/ui/partner_005
A20: PARTNER_UI_DASHBOARD_005 | B20: Partner Platform | C20: Calculate - Tier qualification dashboard - T12M ARR threshold and next-tier delta are visible | D20: UI | E20: P1 | F20: Trang Le | G20: NOT_STARTED
A21: PARTNER_UI_DASHBOARD_006 | B21: Partner Platform | C21: Warn - Tier downgrade pending - 30-day notice and grace quarter are displayed | D21: UI | E21: P1 | F21: Trang Le | G21: NOT_STARTED
A22: PARTNER_UI_MY_PIPELINE_001 | B22: Partner Platform | C22: Register - Enter valid company details - Wizard advances to contact step | D22: UI | E22: P1 | F22: Trang Le | G22: NOT_STARTED | H22: tests/ui/partner_010
A23: PARTNER_UI_MY_PIPELINE_002 | B23: Partner Platform | C23: Validate - Leave company name blank - Required field error is shown | D23: UI | E23: P1 | F23: Trang Le | G23: NOT_STARTED | H23: tests/ui/partner_011
A24: PARTNER_UI_MY_PIPELINE_003 | B24: Partner Platform | C24: Validate - Enter invalid domain - Domain format error is shown | D24: UI | E24: P1 | F24: Trang Le | G24: NOT_STARTED | H24: tests/ui/partner_012
A25: PARTNER_UI_MY_PIPELINE_004 | B25: Partner Platform | C25: Warn - Domain already exists - Inline active-account warning is shown | D25: UI | E25: P1 | F25: Trang Le | G25: NOT_STARTED | H25: tests/ui/partner_014
A26: PARTNER_UI_MY_PIPELINE_005 | B26: Partner Platform | C26: Submit - Existing domain with warning - Deal enters conflict queue | D26: UI | E26: P1 | F26: Trang Le | G26: NOT_STARTED | H26: tests/ui/partner_015
A27: PARTNER_UI_MY_PIPELINE_006 | B27: Partner Platform | C27: Validate - Enter contact without email - Required field error is shown | D27: UI | E27: P1 | F27: Trang Le | G27: NOT_STARTED | H27: tests/ui/partner_016
A28: PARTNER_UI_MY_PIPELINE_007 | B28: Partner Platform | C28: Validate - Enter malformed email - Email error is shown | D28: UI | E28: P1 | F28: Trang Le | G28: NOT_STARTED | H28: tests/ui/partner_017
A29: PARTNER_UI_MY_PIPELINE_008 | B29: Partner Platform | C29: Select - Choose referral deal type - Direct billing model is implied | D29: UI | E29: P1 | F29: Trang Le | G29: NOT_STARTED | H29: tests/ui/partner_020
A30: PARTNER_UI_MY_PIPELINE_009 | B30: Partner Platform | C30: Select - Choose reseller deal type - Reseller billing path is available | D30: UI | E30: P1 | F30: Trang Le | G30: NOT_STARTED | H30: tests/ui/partner_021
A31: PARTNER_UI_MY_PIPELINE_010 | B31: Partner Platform | C31: Select - Choose co-sell deal type - Co-sell option is captured | D31: UI | E31: P1 | F31: Trang Le | G31: NOT_STARTED | H31: tests/ui/partner_022
A32: PARTNER_UI_MY_PIPELINE_011 | B32: Partner Platform | C32: Confirm - Review registration summary - All entered data is displayed | D32: UI | E32: P1 | F32: Trang Le | G32: NOT_STARTED | H32: tests/ui/partner_023
A33: PARTNER_UI_MY_PIPELINE_012 | B33: Partner Platform | C33: Submit - Valid deal registration - Success response appears within 2 seconds | D33: UI | E33: P1 | F33: Trang Le | G33: NOT_STARTED | H33: tests/ui/partner_024
... A37: PARTNER_UI_MY_PIPELINE_016 | B37: Partner Platform | C37: Accept - Co-sell override proposal - Partner acceptance is recorded | D37: UI | E37: P1 | F37: Trang Le | G37: NOT_STARTED | H37: tests/ui/partner_034
A38: PARTNER_UI_MY_PIPELINE_017 | B38: Partner Platform | C38: Block - Co-sell override under or equal $100K ACV - Override option is unavailable | D38: UI | E38: P1 | F38: Trang Le | G38: NOT_STARTED
A39: PARTNER_UI_MY_PIPELINE_018 | B39: Partner Platform | C39: Require - Co-sell override above $100K ACV - Partner written agreement is required | D39: UI | E39: P1 | F39: Trang Le | G39: NOT_STARTED
A40: PARTNER_UI_MY_CLIENTS_001 | B40: Partner Platform | C40: Click - Action Required renewal CTA - Renewal registration flow opens | D40: UI | E40: P1 | F40: Trang Le | G40: NOT_STARTED | H40: tests/ui/partner_006
A41: PARTNER_UI_MY_CLIENTS_002 | B41: Partner Platform | C41: List - Open My Clients - Post-close clients are displayed | D41: UI | E41: P1 | F41: Trang Le | G41: NOT_STARTED | H41: tests/ui/partner_036
A42: PARTNER_UI_MY_CLIENTS_003 | B42: Partner Platform | C42: Open - Client health detail - ARR, renewal, usage, tickets, and CSM are visible | D42: UI | E42: P1 | F42: Trang Le | G42: NOT_STARTED | H42: tests/ui/partner_040
A43: PARTNER_UI_MY_CLIENTS_004 | B43: Partner Platform | C43: Register - Renewal deal from client detail - Renewal context is prefilled | D43: UI | E43: P1 | F43: Trang Le | G43: NOT_STARTED | H43: tests/ui/partner_041
A44: PARTNER_UI_MY_CLIENTS_005 | B44: Partner Platform | C44: Add - MSP managed client - Provisioning form is shown | D44: UI | E44: P1 | F44: Trang Le | G44: NOT_STARTED | H44: tests/ui/partner_043
A45: PARTNER_UI_MY_CLIENTS_006 | B45: Partner Platform | C45: Toggle - MSP ticket consent default - Consent is off by default | D45: UI | E45: P1 | F45: Trang Le | G45: NOT_STARTED | H45: tests/ui/partner_044
A46: PARTNER_UI_COMMISSIONS_001 | B46: Partner Platform | C46: Calculate - Type estimated annual value - Commission projection updates live | D46: UI | E46: P1 | F46: Trang Le | G46: NOT_STARTED | H46: tests/ui/partner_018
A47: PARTNER_UI_COMMISSIONS_002 | B47: Partner Platform | C47: View - Commissions page - Earned pending and paid totals are visible | D47: UI | E47: P1 | F47: Trang Le | G47: NOT_STARTED | H47: tests/ui/partner_045
A48: PARTNER_UI_COMMISSIONS_003 | B48: Partner Platform | C48: Trace - Commission row detail - Deal close to payment details are visible | D48: UI | E48: P1 | F48: Trang Le | G48: NOT_STARTED | H48: tests/ui/partner_046
A49: PARTNER_UI_COMMISSIONS_004 | B49: Partner Platform | C49: Submit - Commission dispute - Dispute is created from one text field | D49: UI | E49: P1 | F49: Trang Le | G49: NOT_STARTED | H49: tests/ui/partner_047
A50: PARTNER_UI_COMMISSIONS_005 | B50: Partner Platform | C50: Submit - Product failure waiver - Evidence can be linked and request submitted | D50: UI | E50: P1 | F50: Trang Le | G50: NOT_STARTED | H50: tests/ui/partner_048
A51: PARTNER_UI_COMMISSIONS_006 | B51: Partner Platform | C51: Approve - Commission payout over $10K - Two-eye approval is enforced | D51: UI | E51: P1 | F51: Trang Le | G51: NOT_STARTED | H51: tests/ui/partner_069
A52: PARTNER_UI_COMMISSIONS_007 | B52: Partner Platform | C52: Display - Clawback notification - Policy terms and product-failure waiver path are visible | D52: UI | E52: P1 | F52: Trang Le | G52: NOT_STARTED
A53: PARTNER_UI_SA_PARTNER_MODULE_001 | B53: Partner Platform | C53: Resolve - Conflict queue with reasoning - Decision is saved and parties notified | D53: UI | E53: P1 | F53: Trang Le | G53: NOT_STARTED | H53: tests/ui/partner_066
A54: PARTNER_UI_SA_PARTNER_MODULE_002 | B54: Partner Platform | C54: Resolve - Conflict queue decision - Prospect confirmation and written reasoning are visible | D54: UI | E54: P1 | F54: Trang Le | G54: NOT_STARTED
A55: PARTNER_UI_SA_PARTNER_MODULE_003 | B55: Partner Platform | C55: Admin - Partner directory loads - Filters and partner rows are visible | D55: UI | E55: P1 | F55: Trang Le | G55: NOT_STARTED | H55: tests/ui/partner_060
A56: PARTNER_UI_SA_PARTNER_MODULE_004 | B56: Partner Platform | C56: Review - Partner application FSM - SA Review Legal Countersign and Final Approval stages are visible | D56: UI | E56: P1 | F56: Trang Le | G56: NOT_STARTED | H56: tests/ui/partner_061
A57: PARTNER_UI_SA_PARTNER_MODULE_005 | B57: Partner Platform | C57: Block - Missing signed agreement - SA cannot advance to legal countersign | D57: UI | E57: P1 | F57: Trang Le | G57: NOT_STARTED | H57: tests/ui/partner_062
A58: PARTNER_UI_SA_PARTNER_MODULE_006 | B58: Partner Platform | C58: Approve - Partner final approval - Portal account creation is triggered | D58: UI | E58: P1 | F58: Trang Le | G58: NOT_STARTED | H58: tests/ui/partner_063
A59: PARTNER_UI_SA_PARTNER_MODULE_007 | B59: Partner Platform | C59: Review - SA deal approval queue - Pending and conflict queues are visible | D59: UI | E59: P1 | F59: Trang Le | G59: NOT_STARTED | H59: tests/ui/partner_064
A60: PARTNER_UI_SA_PARTNER_MODULE_008 | B60: Partner Platform | C60: Approve - SA assigns rep to co-sell deal - Approval starts protection clock | D60: UI | E60: P1 | F60: Trang Le | G60: NOT_STARTED | H60: tests/ui/partner_065
A61: PARTNER_UI_SA_PARTNER_MODULE_009 | B61: Partner Platform | C61: Configure - Commission rate table - Versioned rates can be edited | D61: UI | E61: P1 | F61: Trang Le | G61: NOT_STARTED | H61: tests/ui/partner_067
A62: PARTNER_UI_SECURITY_COMPLIANCE_001 | B62: Partner Platform | C62: Deny - Cross-partner data access in UI - Other partner data is not visible | D62: UI | E62: P1 | F62: Trang Le | G62: NOT_STARTED | H62: tests/ui/partner_073
A63: PARTNER_UI_SECURITY_COMPLIANCE_002 | B63: Partner Platform | C63: Audit - SA action completed - Activity log entry is visible | D63: UI | E63: P1 | F63: Trang Le | G63: NOT_STARTED | H63: tests/ui/partner_074
A64: PARTNER_UI_SECURITY_COMPLIANCE_003 | B64: Partner Platform | C64: Validate - Deal registration prospect data minimization - Only allowed prospect fields are requested | D64: UI | E64: P1 | F64: Trang Le | G64: NOT_STARTED
A65: PARTNER_API_AUTH_ACCESS_CONTROL_001 | B65: Partner Platform | C65: Authenticate - Valid partner JWT - Partner-scoped request succeeds | D65: API | E65: P1 | F65: Trang Le | G65: NOT_STARTED | H65: tests/api/partner_001
A66: PARTNER_API_AUTH_ACCESS_CONTROL_002 | B66: Partner Platform | C66: Reject - Tenant JWT on partner API - Request is unauthorized | D66: API | E66: P1 | F66: Trang Le | G66: NOT_STARTED | H66: tests/api/partner_002
A67: PARTNER_API_AUTH_ACCESS_CONTROL_003 | B67: Partner Platform | C67: Reject - Partner JWT accessing another partner - Request is forbidden | D67: API | E67: P1 | F67: Trang Le | G67: NOT_STARTED | H67: tests/api/partner_003
A68: PARTNER_API_AUTH_ACCESS_CONTROL_004 | B68: Partner Platform | C68: Enforce - Admin MFA policy - Protected action requires MFA | D68: API | E68: P1 | F68: Trang Le | G68: NOT_STARTED | H68: tests/api/partner_004
A69: PARTNER_API_AUTH_ACCESS_CONTROL_005 | B69: Partner Platform | C69: Guard - MSP accesses payroll data - Request is forbidden | D69: API | E69: P1 | F69: Trang Le | G69: NOT_STARTED | H69: tests/api/partner_027
A70: PARTNER_API_AUTH_ACCESS_CONTROL_006 | B70: Partner Platform | C70: Guard - MSP exports employee records - Request is forbidden | D70: API | E70: P1 | F70: Trang Le | G70: NOT_STARTED | H70: tests/api/partner_028
A71: PARTNER_API_DASHBOARD_DATA_001 | B71: Partner Platform | C71: GET - Partner dashboard stats - KPI schema is returned | D71: API | E71: P1 | F71: Trang Le | G71: NOT_STARTED | H71: tests/api/partner_005
A72: PARTNER_API_DEAL_REGISTRATION_001 | B72: Partner Platform | C72: Validate - Missing required registration fields - 400 response includes field errors | D72: API | E72: P1 | F72: Trang Le | G72: NOT_STARTED | H72: tests/api/partner_010
A73: PARTNER_API_DEAL_REGISTRATION_PIPELINE_001 | B73: Partner Platform | C73: POST - Register referral deal - Deal is created pending approval | D73: API | E73: P1 | F73: Trang Le | G73: NOT_STARTED | H73: tests/api/partner_006
A74: PARTNER_API_DEAL_REGISTRATION_PIPELINE_002 | B74: Partner Platform | C74: POST - Register reseller deal - Billing model reseller is stored | D74: API | E74: P1 | F74: Trang Le | G74: NOT_STARTED | H74: tests/api/partner_007
A75: PARTNER_API_DEAL_REGISTRATION_PIPELINE_003 | B75: Partner Platform | C75: POST - Register co-sell deal - Co-sell metadata is stored | D75: API | E75: P1 | F75: Trang Le | G75: NOT_STARTED | H75: tests/api/partner_008
A76: PARTNER_API_DEAL_REGISTRATION_PIPELINE_004 | B76: Partner Platform | C76: POST - Register deal with existing domain - Conflict status is raised | D76: API | E76: P1 | F76: Trang Le | G76: NOT_STARTED | H76: tests/api/partner_009
... A82: PARTNER_API_DEAL_REGISTRATION_PIPELINE_010 | B82: Partner Platform | C82: Sync - Deal approved event - CRM owner and stage are updated | D82: API | E82: P1 | F82: Trang Le | G82: NOT_STARTED | H82: tests/api/partner_056
A83: PARTNER_API_DEAL_REGISTRATION_PIPELINE_011 | B83: Partner Platform | C83: Calculate - Co-sell split default - 70/30 split is stored for standard co-sell deal | D83: API | E83: P1 | F83: Trang Le | G83: NOT_STARTED
A84: PARTNER_API_DEAL_REGISTRATION_PIPELINE_012 | B84: Partner Platform | C84: Reject - Co-sell split override at or below $100K ACV - Override is not accepted | D84: API | E84: P1 | F84: Trang Le | G84: NOT_STARTED
A85: PARTNER_API_DEAL_REGISTRATION_PIPELINE_013 | B85: Partner Platform | C85: Resolve - Conflict with prospect confirmation - Confirmed partner wins conflict | D85: API | E85: P1 | F85: Trang Le | G85: NOT_STARTED
A86: PARTNER_API_DEAL_REGISTRATION_PIPELINE_014 | B86: Partner Platform | C86: Resolve - Conflict with unreachable prospect - First registered deal wins tiebreaker | D86: API | E86: P1 | F86: Trang Le | G86: NOT_STARTED
A87: PARTNER_API_DEAL_REGISTRATION_PIPELINE_015 | B87: Partner Platform | C87: Enforce - Multi-partner influenced deal with no registration - No attribution or commission is created on tenant provisioning | D87: API | E87: P1 | F87: Trang Le | G87: NOT_STARTED
A88: PARTNER_API_PIPELINE_MANAGEMENT_001 | B88: Partner Platform | C88: GET - Partner deals list - Only own deals are returned | D88: API | E88: P1 | F88: Trang Le | G88: NOT_STARTED | H88: tests/api/partner_012
A89: PARTNER_API_TENANT_PROVISIONING_ATTRIBUTION_001 | B89: Partner Platform | C89: POST - Accept co-sell override - Override is locked at approval | D89: API | E89: P1 | F89: Trang Le | G89: NOT_STARTED | H89: tests/api/partner_016
A90: PARTNER_API_TENANT_PROVISIONING_ATTRIBUTION_002 | B90: Partner Platform | C90: POST - Referral close - Tenant provision and commission events are emitted | D90: API | E90: P1 | F90: Trang Le | G90: NOT_STARTED | H90: tests/api/partner_029
A91: PARTNER_API_TENANT_PROVISIONING_ATTRIBUTION_003 | B91: Partner Platform | C91: POST - Reseller close - Invoice targets reseller partner | D91: API | E91: P1 | F91: Trang Le | G91: NOT_STARTED | H91: tests/api/partner_030
A92: PARTNER_API_TENANT_PROVISIONING_ATTRIBUTION_004 | B92: Partner Platform | C92: POST - Expansion close - Existing tenant line items are updated | D92: API | E92: P1 | F92: Trang Le | G92: NOT_STARTED | H92: tests/api/partner_031
A93: PARTNER_API_TENANT_PROVISIONING_ATTRIBUTION_005 | B93: Partner Platform | C93: Calculate - Expansion commission NN stage - Full configured rate applies | D93: API | E93: P1 | F93: Trang Le | G93: NOT_STARTED | H93: tests/api/partner_032
A94: PARTNER_API_TENANT_PROVISIONING_ATTRIBUTION_006 | B94: Partner Platform | C94: Calculate - Expansion commission EN stage - Lower configured rate applies | D94: API | E94: P1 | F94: Trang Le | G94: NOT_STARTED | H94: tests/api/partner_033
A95: PARTNER_API_TENANT_PROVISIONING_ATTRIBUTION_007 | B95: Partner Platform | C95: Sync - Deal won event - CRM opportunity closes won with tenant ID | D95: API | E95: P1 | F95: Trang Le | G95: NOT_STARTED | H95: tests/api/partner_057
A96: PARTNER_API_TENANT_PROVISIONING_ATTRIBUTION_008 | B96: Partner Platform | C96: Store - Tenant attribution block - Permanent partner fields are written | D96: API | E96: P1 | F96: Trang Le | G96: NOT_STARTED | H96: tests/api/partner_058
A97: PARTNER_API_TENANT_PROVISIONING_ATTRIBUTION_009 | B97: Partner Platform | C97: Override - Tenant attribution by SA - Two-eye approval and history are required | D97: API | E97: P1 | F97: Trang Le | G97: NOT_STARTED | H97: tests/api/partner_059
A98: PARTNER_API_TENANT_PROVISIONING_ATTRIBUTION_010 | B98: Partner Platform | C98: Lock - Co-sell override after partner acceptance - Approved split cannot be renegotiated | D98: API | E98: P1 | F98: Trang Le | G98: NOT_STARTED
A99: PARTNER_API_CLIENT_HEALTH_MSP_001 | B99: Partner Platform | C99: GET - Partner clients - Post-close tenants are returned | D99: API | E99: P1 | F99: Trang Le | G99: NOT_STARTED | H99: tests/api/partner_021
A100: PARTNER_API_CLIENT_HEALTH_MSP_002 | B100: Partner Platform | C100: GET - Client health metrics - Usage renewal and ticket metrics are returned | D100: API | E100: P1 | F100: Trang Le | G100: NOT_STARTED | H100: tests/api/partner_022
A101: PARTNER_API_CLIENT_HEALTH_MSP_003 | B101: Partner Platform | C101: GET - Client tickets without MSP consent - Only count and severity are returned | D101: API | E101: P1 | F101: Trang Le | G101: NOT_STARTED | H101: tests/api/partner_023
A102: PARTNER_API_CLIENT_HEALTH_MSP_004 | B102: Partner Platform | C102: GET - Client tickets with MSP consent - Ticket content is returned | D102: API | E102: P1 | F102: Trang Le | G102: NOT_STARTED | H102: tests/api/partner_024
A103: PARTNER_API_CLIENT_HEALTH_MSP_005 | B103: Partner Platform | C103: PATCH - Revoke MSP consent - Content access stops immediately | D103: API | E103: P1 | F103: Trang Le | G103: NOT_STARTED | H103: tests/api/partner_025
A104: PARTNER_API_CLIENT_HEALTH_MSP_006 | B104: Partner Platform | C104: POST - MSP tenant provision - partner_managed tenant is created | D104: API | E104: P1 | F104: Trang Le | G104: NOT_STARTED | H104: tests/api/partner_026
A105: PARTNER_API_CLIENT_HEALTH_MSP_007 | B105: Partner Platform | C105: Transfer - MSP handoff - Old history preserved and event emitted | D105: API | E105: P1 | F105: Trang Le | G105: NOT_STARTED | H105: tests/api/partner_060
A106: PARTNER_API_CLIENT_HEALTH_MSP_008 | B106: Partner Platform | C106: Calculate - MSP tier qualification - Total managed ARR is used | D106: API | E106: P1 | F106: Trang Le | G106: NOT_STARTED | H106: tests/api/partner_062
A107: PARTNER_API_CLIENT_HEALTH_MSP_009 | B107: Partner Platform | C107: Audit - MSP consent grant and revoke - Event includes actor timestamps and access changes immediately | D107: API | E107: P1 | F107: Trang Le | G107: NOT_STARTED
A108: PARTNER_API_COMMISSIONS_PAYOUTS_001 | B108: Partner Platform | C108: Calculate - Renewal EE stage - Lowest configured rate applies | D108: API | E108: P1 | F108: Trang Le | G108: NOT_STARTED | H108: tests/api/partner_034
A109: PARTNER_API_COMMISSIONS_PAYOUTS_002 | B109: Partner Platform | C109: GET - Commission history - Partner commission ledger is returned | D109: API | E109: P1 | F109: Trang Le | G109: NOT_STARTED | H109: tests/api/partner_035
A110: PARTNER_API_COMMISSIONS_PAYOUTS_003 | B110: Partner Platform | C110: POST - Commission dispute - Dispute log entry is created | D110: API | E110: P1 | F110: Trang Le | G110: NOT_STARTED | H110: tests/api/partner_036
...

Sheet Execution Log
A1: Execution Log
A2: Sprint / Release | B2: Date | C2: Build Version | D2: Module | E2: TC ID | F2: Executor | G2: Result | H2: Note
A3: Sprint 1 | B3: 2026-05-20 | C3: v0.1.0-alpha | D3: Partner Platform | E3: PARTNER_UI_001 | F3: Trang Le | G3: Not Started | H3: Initial smoke run — placeholder

Sheet Test Scope
A1: TEST SCOPE
A2: Document: partner-platform-prd-v1.8 | Last updated: 2026-05-20 | Status: Living Document
A3: ✅ IN SCOPE
A4: Category | B4: Module | C4: Description | D4: Owner | E4: Status
A5: Partner Platform
A6: In Scope | B6: Partner Platform | C6: Partner portal shell: navigation, dashboard, KPI cards, tier progress, action-required list. | D6: QA Team | E6: Active
A7: In Scope | B7: Partner Platform | C7: Deal registration wizard: referral, reseller, co-sell deal types; validation, conflict detection, commission projection. | D7: QA Team | E7: Active
A8: In Scope | B8: Partner Platform | C8: Pipeline management: deal list, filters, deal detail, timeline, notes, documents, BlazeUp rep view. | D8: QA Team | E8: Active
A9: In Scope | B9: Partner Platform | C9: Client health: client list, health detail (ARR, renewal, usage, tickets), MSP managed client provisioning, consent toggle. | D9: QA Team | E9: Active
A10: In Scope | B10: Partner Platform | C10: Commissions: earned/pending/paid totals, commission trace, dispute submission, product failure waiver, payout details. | D10: QA Team | E10: Active
A11: In Scope | B11: Partner Platform | C11: Training & Resources: certifications, learning paths, marketing assets, co-branded deck, ROI calculator, sandbox reset. | D11: QA Team | E11: Active
A12: In Scope | B12: Partner Platform | C12: Team & Referral: team member invite, campaign referral link creation and analytics. | D12: QA Team | E12: Active
A13: In Scope | B13: Partner Platform | C13: SA Partner Module: partner directory, application FSM (staged approval), deal approval/conflict queues, commission config, territory, analytics, ledger approval. | D13: QA Team | E13: Active
A14: In Scope | B14: Partner Platform | C14: Backend APIs: ms-sa-partners endpoints, Kafka events, MongoDB/Redis persistence, commission engine, tenant provisioning, MSP scope guard, audit trail. | D14: QA Team | E14: Active
A15: In Scope | B15: Partner Platform | C15: Security: partner JWT separation, cross-partner isolation, MFA gates, MSP consent enforcement, SA two-eye approvals, data residency. | D15: QA Team | E15: Active
A17: 🚫 OUT OF SCOPE
A18: Category | B18: Module | C18: Description | D18: Owner | E18: Status
A19: Pack Partner
A20: Out of Scope | B20: Pack Partner | C20: Pack Partner marketplace features — only separation from Channel Partner accounts is validated. | D20: N/A | E20: Excluded
A21: Partner Platform
A22: Out of Scope | B22: Partner Platform | C22: Final Legal/Compliance decisions pending sign-off — related test cases are placeholders only. | D22: N/A | E22: Excluded
A23: Out of Scope | B23: Partner Platform | C23: Exact commission rates/window durations for NN/EN/EE stages — SA will configure values before launch; exact figures not testable yet. | D23: N/A | E23: Pending
A24: Out of Scope | B24: Partner Platform | C24: Third-party training platform vendor behavior — deferred until build-vs-buy decision is finalized. | D24: N/A | E24: Pending
A25: Other Modules
A26: Out of Scope | B26: Other Modules | C26: 9 remaining modules (CRM, etc.) — not yet assigned; will be added as requirements are provided. | D26: N/A | E26: Pending
A28: 📌 ASSUMPTIONS
A29: Category | B29: Module | C29: Description | D29: Owner | E29: Status
A30: All Modules
A31: Assumption | B31: All Modules | C31: This is a living document. New modules will be added as requirements are provided by the team. | D31: QA Team | E31: Active
A32: In Scope | B32: Partner Platform | C32: Requirement-phase automation mappings are placeholders; executable automation will be updated after requirements stabilize. | D32: QA Team | E32: Active
A33: Partner Platform
A34: Assumption | B34: Partner Platform | C34: All test statuses default to Not Started. Status logic: Fail if any = Fail; Pass if Manual = Pass and Automation = Pass/Not Started; else Not Started. | D34: QA Team | E34: Active
A35: Assumption | B35: Partner Platform | C35: Automation mapping IDs (e.g. tests/ui/partner_001) are placeholders — replace with real script paths when automation is implemented. | D35: QA Team | E35: Active
A36: Assumption | B36: Partner Platform | C36: partner.blazeup.ai (dogfood tenant) is the test target. Auth Phase 0 hooks/mocks are used for non-auth slices; live partner auth tested only after auth gate lands. | D36: Dev Team | E36: Active
A38: 🔑 ENTRY & EXIT CRITERIA
A39: Category | B39: Module | C39: Description | D39: Owner | E39: Status
A40: Partner Platform
A41: Entry Criteria | B41: Partner Platform | C41: PRD v1.8 is baselined and available to QA team. | D41: PM | E41: Active
A42: Entry Criteria | B42: Partner Platform | C42: Test environment is deployed: Partner Portal, SA Partner Module, ms-sa-partners, dogfood CRM bridge, tenant provisioning, billing, Kafka test topics. | D42: Dev Team | E42: Active
A43: Entry Criteria | B43: Partner Platform | C43: Seed data is ready: partners, deals, clients, commissions, sandbox profiles, conflict fixtures. | D43: Dev Team | E43: Active
A44: Entry Criteria | B44: Partner Platform | C44: Auth Phase 0 test hooks or mocks are available for non-auth test slices. | D44: Dev Team | E44: Active
A45: Exit Criteria | B45: Partner Platform | C45: All P1 test cases executed with zero unresolved Critical or Major release-blocking defects. | D45: QA Team | E45: Active
A46: Exit Criteria | B46: Partner Platform | C46: Requirement coverage = 100% for all active testable PRD sections. | D46: QA Team | E46: Active
A47: Exit Criteria | B47: Partner Platform | C47: Regression Suite P1 cases pass on the release candidate build. | D47: QA Team | E47: Active
A48: Exit Criteria | B48: Partner Platform | C48: Execution Log is updated with build version, executor, result, and defect references for all executed TCs. | D48: QA Team | E48: Active

Sheet Bug_Tracker
A1: Bug ID | B1: Test Case ID | C1: Test Case Name | D1: Module | E1: Feature | F1: Severity | G1: Priority | H1: Status | I1: Summary | J1: Expected | K1: Actual | L1: Evidence / Assertion | M1: Reported By | N1: Date Opened | O1: Date Closed | P1: Notes
A2: API
A3: BUG-API-001 | B3: 2060122 | C3: PARTNER_API_PARTNER_ACCOUNT_MANAGEMENT_022 | D3: Partner | E3: Certifications | F3: Major | G3: P2 | H3: Close | I3: Re-granting the same certification to the same user creates a duplicate | J3: Re-grant is idempotent (or 409) — no second active cert | K3: Returns 201 and creates a 2nd active cert | L3: AssertionError: re-granting must not duplicate active cert | M3: Trangqle | N3: 46219
A4: BUG-API-002 | B4: 2060208 | C4: PARTNER_API_DEAL_REGISTRATION_PIPELINE_008 | D4: Partner | E4: Deal Approval | F4: Major | G4: P2 | H4: Close | I4: Approving a deal does not stamp rate / rateTableVersion | J4: Approved deal exposes rate + rateTableVersion | K4: Fields not stamped/exposed | L4: AssertionError: approved deal must stamp rate + rate table version | M4: Trangqle | N4: 46219
A5: BUG-API-003 | B5: 2060221 | C5: PARTNER_API_DEAL_REGISTRATION_PIPELINE_021 | D5: Partner | E5: Deal Registration | F5: Major | G5: P2 | H5: Close | I5: Deal registration accepts a non-existent (ghost) planId | J5: Reject 4xx when planId absent (FK validation) | K5: Returns 201 registered | L5: CHECK ghost planId (verified absent) -&gt; FAIL (status=201) | M5: Trangqle | N5: 46219 | O5: 46226 | P5: Re-check is PASS
A6: BUG-API-004 | B6: 2060713 | C6: PARTNER_API_PARTNER_USERS_013 | D6: Partner | E6: Partner Users | F6: Major | G6: P2 | H6: Close | I6: Inviting a duplicate email creates a second user | J6: Reject (409) or idempotent — no duplicate user | K6: Returns 201; two users share one login | L6: AssertionError: re-inviting must not duplicate user | M6: Trangqle | N6: 46223 | O6: 46226 | P6: Re-check is PASS
A7: BUG-API-005 | B7: 2061003 | C7: PARTNER_API_AUTH_ACCESS_CONTROL_003 | D7: Partner | E7: Auth &amp; Access Control | F7: Major | G7: P2 | H7: Close | I7: Cross-partner deal access returns 400 instead of 404/403 | J7: 404 (preferred, hides existence) or 403 for cross-partner access | K7: Returns 400 (mislabels a valid request as malformed); isolation holds (no data leak) | L7: AssertionError: cross-partner access should be 404 (preferred) or 403, got 400 | M7: Trangqle | N7: 46223 | O7: 46226 | P7: Re-check is PASS
A8: BUG-API-006 | B8: 2060231 | C8: PARTNER_API_DEAL_REGISTRATION_PIPELINE_031 | D8: Partner | E8: DEAL_REGISTRATION_PIPELINE | F8: Minor | G8: P2 | H8: Close | I8: GET deal by a well-formed but non-existent id returns 400 instead of 404 | J8: 404 Not Found for a well-formed but non-existent deal id | K8: 400 Bad Request with message "Deal 000000000000000000000000 not found" (status contradicts message) | L8: test_partner_api_deal_registration_pipeline_031 [1/2]: expected 404, got 400, msg="Deal 000000000000000000000000 not found" | M8: Trangqle | N8: 46223 | O8: 46226 | P8: Re-check is PASS
A9: BUG-API-007 | B9: 2060232 | C9: PARTNER_API_DEAL_REGISTRATION_PIPELINE_032 | D9: Partner | E9: DEAL_REGISTRATION_PIPELINE | F9: Minor | G9: P2 | H9: Close | I9: lose deal on a well-formed but non-existent id returns 400 instead of 404 | J9: 404 Not Found for a well-formed but non-existent deal id | K9: 400 Bad Request with message "Deal 000000000000000000000000 not found" (status contradicts message) | L9: test_partner_api_deal_registration_pipeline_032 [2/3]: expected 404, got 400, msg="Deal 000000000000000000000000 not found" | M9: Trangqle | N9: 46223 | O9: 46226 | P9: Re-check is PASS
A10: BUG-API-008 | B10: 2060228 | C10: PARTNER_API_DEAL_REGISTRATION_PIPELINE_028 | D10: Partner | E10: DEAL_REGISTRATION_PIPELINE | F10: Minor | G10: P2 | H10: Close | I10: approve deal on a well-formed but non-existent id returns 400 instead of 404 | J10: 404 Not Found for a well-formed but non-existent deal id | K10: 400 Bad Request with message "Deal 000000000000000000000000 not found" (status contradicts message) | L10: test_partner_api_deal_registration_pipeline_028 [1/3]: expected 404, got 400, msg="Deal 000000000000000000000000 not found" | M10: Trangqle | N10: 46223 | O10: 46226 | P10: Re-check is PASS
A11: BUG-API-009 | B11: 2060229 | C11: PARTNER_API_DEAL_REGISTRATION_PIPELINE_029 | D11: Partner | E11: DEAL_REGISTRATION_PIPELINE | F11: Minor | G11: P2 | H11: Close | I11: resolve-conflict on a well-formed but non-existent id returns 400 instead of 404 | J11: 404 Not Found for a well-formed but non-existent deal id | K11: 400 Bad Request with message "Deal 000000000000000000000000 not found" (status contradicts message) | L11: test_partner_api_deal_registration_pipeline_029 [6/6]: expected 404, got 400, msg="Deal 000000000000000000000000 not found" | M11: Trangqle | N11: 46223 | O11: 46226 | P11: Re-check is PASS
A12: BUG-API-010 | B12: 2060230 | C12: PARTNER_API_DEAL_REGISTRATION_PIPELINE_030 | D12: Partner | E12: DEAL_REGISTRATION_PIPELINE | F12: Minor | G12: P2 | H12: Close | I12: extend-protection on a well-formed but non-existent id returns 400 instead of 404 | J12: 404 Not Found for a well-formed but non-existent deal id | K12: 400 Bad Request with message "Deal 000000000000000000000000 not found" (status contradicts message) | L12: test_partner_api_deal_registration_pipeline_030 [8/8]: expected 404, got 400, msg="Deal 000000000000000000000000 not found" | M12: Trangqle | N12: 46223 | O12: 46226 | P12: Re-check is PASS
A13: BUG-API-011 | B13: 2061111 | C13: PARTNER_API_DEAL_APPROVAL_QUEUE_011 | D13: Partner | E13: DEAL_APPROVAL_QUEUE | F13: Minor | G13: P2 | H13: Close | I13: reject deal on a well-formed but non-existent id returns 400 instead of 404 | J13: 404 Not Found for a well-formed but non-existent deal id | K13: 400 Bad Request with message "Deal 000000000000000000000000 not found" (status contradicts message) | L13: test_partner_api_deal_approval_queue_011 [1/3]: expected 404, got 400, msg="Deal 000000000000000000000000 not found" | M13: Trangqle | N13: 46223 | O13: 46226 | P13: Re-check is PASS
A14: BUG-API-012 | B14: 2060113 | C14: PARTNER_API_PARTNER_ACCOUNT_MANAGEMENT_013 | D14: Partner | E14: PARTNER_ACCOUNT_MANAGEMENT | F14: Minor | G14: P2 | H14: Close | I14: approve partner: well-formed but non-existent partner id returns 400 instead of 404 | J14: 404 Not Found for a well-formed but non-existent partner id | K14: 400 Bad Request with message "Partner 000000000000000000000000 not found" (status contradicts message) | L14: test_partner_api_partner_account_management_013 [1/3]: expected 404, got 400, msg="Partner 000000000000000000000000 not found" | M14: Trangqle | N14: 46223 | O14: 46300
A15: BUG-API-013 | B15: 2060114 | C15: PARTNER_API_PARTNER_ACCOUNT_MANAGEMENT_014 | D15: Partner | E15: PARTNER_ACCOUNT_MANAGEMENT | F15: Minor | G15: P2 | H15: Close | I15: deactivate partner: well-formed but non-existent partner id returns 400 instead of 404 | J15: 404 Not Found for a well-formed but non-existent partner id | K15: 400 Bad Request with message "Partner 000000000000000000000000 not found" (status contradicts message) | L15: test_partner_api_partner_account_management_014 [1/3]: expected 404, got 400, msg="Partner 000000000000000000000000 not found" | M15: Trangqle | N15: 46223 | O15: 46300
A16: BUG-API-014 | B16: 2060115 | C16: PARTNER_API_PARTNER_ACCOUNT_MANAGEMENT_015 | D16: Partner | E16: PARTNER_ACCOUNT_MANAGEMENT | F16: Minor | G16: P2 | H16: Close | I16: change-tier partner: well-formed but non-existent partner id returns 400 instead of 404 | J16: 404 Not Found for a well-formed but non-existent partner id | K16: 400 Bad Request with message "Partner 000000000000000000000000 not found" (status contradicts message) | L16: test_partner_api_partner_account_management_015 [6/6]: expected 404, got 400, msg="Partner 000000000000000000000000 not found" | M16: Trangqle | N16: 46223 | O16: 46300
A17: BUG-API-015 | B17: 2060120 | C17: PARTNER_API_PARTNER_ACCOUNT_MANAGEMENT_020 | D17: Partner | E17: PARTNER_ACCOUNT_MANAGEMENT | F17: Minor | G17: P2 | H17: Close | I17: grant-certification on a well-formed but non-existent userId returns 400 instead of 404 | J17: 404 Not Found for a well-formed but non-existent userId | K17: 400 Bad Request with message "User 000000000000000000000000 not found" (status contradicts message) | L17: test_partner_api_partner_account_management_020 [4/4]: expected 404, got 400, msg="User 000000000000000000000000 not found" | M17: Trangqle | N17: 46223 | O17: 46300 | P17: Re-check is PASS
A18: BUG-API-016 | B18: 2060714 | C18: PARTNER_API_PARTNER_USERS_014 | D18: Partner | E18: PARTNER_USERS | F18: Minor | G18: P2 | H18: Close | I18: reset-password on a well-formed but non-existent userId returns 400 instead of 404 | J18: 404 Not Found for a well-formed but non-existent userId | K18: 400 Bad Request with message "User 000000000000000000000000 not found" (status contradicts message) | L18: test_partner_api_partner_users_014 [1/2]: expected 404, got 400, msg="User 000000000000000000000000 not found" | M18: Trangqle | N18: 46223 | O18: 46300
A19: BUG-API-017 | B19: 2060414 | C19: PARTNER_API_TERRITORIES_014 | D19: Partner | E19: TERRITORIES | F19: Minor | G19: P2 | H19: Close | I19: get-territory-by-id on a well-formed but non-existent id returns 400 instead of 404 | J19: 404 Not Found for a well-formed but non-existent / already-removed territory id | K19: 400 Bad Request with message "Territory ... not found" (status contradicts message) | L19: test_partner_api_territories_014 [1/2]: expected 404, got 400, msg="Territory 000000000000000000000000 not found" | M19: Trangqle | N19: 46223 | O19: 46300
A20: BUG-API-018 | B20: 2060415 | C20: PARTNER_API_TERRITORIES_015 | D20: Partner | E20: TERRITORIES | F20: Minor | G20: P2 | H20: Close | I20: delete territory on a non-existent / already-removed id returns 400 instead of 404 | J20: 404 Not Found for a well-formed but non-existent / already-removed territory id | K20: 400 Bad Request with message "Territory ... not found" (status contradicts message) | L20: test_partner_api_territories_015 [1/3] + [3/3]: expected 404, got 400 (ghost id AND already-removed), msg="Territory ... not found" | M20: Trangqle | N20: 46223 | O20: 46300
A21: BUG-API-019 | B21: 2060512 | C21: PARTNER_API_CERTIFICATIONS_SA_012 | D21: Partner | E21: CERTIFICATIONS_SA | F21: Minor | G21: P2 | H21: Close | I21: revoke-certification not-found targets (ghost user / cert-not-held / already-revoked) return 400 instead of 404 | K21: 400 Bad Request with a "not found" message (User ... not found / Active ... certification not found) | L21: test_partner_api_certifications_sa_012: cases 2,3,5 expected 404, got 400 (msg contains not found) | M21: Trangqle | N21: 46223 | O21: 46300
A22: BUG-API-020 | B22: 2060234 | C22: PARTNER_API_DEAL_REGISTRATION_PIPELINE_034 | D22: Partner | E22: DEAL_REGISTRATION_PIPELINE | F22: Major | G22: P2 | H22: Close | I22: Win deal: WinDealDto required fields not enforced (companyWebsite/industry/adminFirstName/adminLastName) | J22: 400 when a required win-intake field is missing (per WinDealDto required list) | K22: 201 - deal is won even with all required fields missing (empty body also wins) | L22: test_partner_api_deal_registration_pipeline_034 [1-4/8]: missing companyWebsite/industry/adminFirstName/adminLastName each returned 201 (expected 400) | M22: Trangqle | N22: 46225 | O22: 46300
A23: BUG-API-021 | C23: (no TC yet — DELETE partner is never asserted) | D23: Partner | E23: PARTNER_ACCOUNT_MANAGEMENT | F23: Major | G23: P2 | H23: Open | I23: Soft delete is INTENTIONAL (confirmed by BE) — but a deleted partner and a suspended one both end up with status='suspended', so no client can tell them apart. The business status 'suspended' has effectively lost its meaning, and QA has no way to remove test data. | J23: Keep the soft delete. Add a way to DISTINGUISH the two states — e.g. a read-only deletedAt / isDeleted field, or an optional filter on GET /v1/sa/partners. No behaviour change needed and SA can still see every partner. Separately: a supported way for QA to purge its own test data (maintenance endpoint, or an agreed manual DB cleanup). | K23: DELETE returns 200 {"message":"Partner deleted successfully"}; the record stays, status flips pending/active -&gt; 'suspended' and internalNotes -&gt; 'Deleted by SA'. That free-text note is the ONLY signal separating a deleted partner from a genuinely suspended one. Measured on stgsa 2026-08-10: 2371 of 2416 partners are 'suspended', and 2369 of those carry 'Deleted by SA' — so only 2 are real suspensions. Volume is also growing: 1808 partners on 2026-08-06 -&gt; 2416 on 2026-08-10 (+608 in 4 days), and nothing can remove them. | L23: Probe on stgsa 2026-08-06: create partner -&gt; DELETE (200) -&gt; GET /v1/sa/partners?search=&lt;name&gt; still returns it at +0s/+3s/+10s with status='suspended', internalNotes='Deleted by SA'. Reproduced from a UI run: 'CLEANUP LEAK: DELETE partner ... returned HTTP 200 but the record is STILL listed'. | M23: QA (review) | N23: 46240 | P23: BE DESIGN CONFIRMED (Khoa Nguyen, 2026-08-10): partners are never hard-deleted on purpose — SA must see every partner, and the status has to be revertible. So this is NOT a request to hard delete; the remaining ask is only a field that separates 'deleted' from 'suspended'. | Impact on automation: created_resources cleanup receives 200 and reports success while removing nothing — that is how ~2.4k QA-AUTO partners accumulated unnoticed. utils/ui_cleanup.py and utils/cleanup_staging.py now re-read the record after DELETE and report CLEANUP LEAK instead of trusting the status code. | Impact on testing: PARTNER_UI_SA_PARTNER_MODULE_016 (reactivate) needs a genuinely Suspended partner and only 2 candidates exist among 2371 rows. | Also missing, tracked here for now: no DELETE for deals, and no delete/revoke for partner-users (only certifications), so data created by PARTNER_UI_MY_PIPELINE_005 and PARTNER_UI_PARTNER_TEAM_001 cannot be cleaned by any route. | Open question back to Product: should 'application declined' and 'active partner suspended' really share one status too? deactivate serves both.
A24: BUG-API-022 | B24: 2061401 | C24: PARTNER_API_PARTNER_TEAM_001 | D24: Partner | E24: PARTNER_TEAM | F24: Major | G24: P2 | H24: Open | I24: partner team directory - invited member appears in list and detail. | J24: partner team directory - invited member appears in list and detail. | K24: FAIL | [6/6] Read the session user by id → must return THAT user (259ms) -- AssertionError: GET /directory/users/{userId} ignored the path parameter: asked for 6aaa783b5a1d688484cf3045, got 6aaa783f5a1d688484cf3059 (team.qa.auto+aaron35-aa19222eed3b@ | L24: FAIL | [6/6] Read the session user by id → must return THAT user (259ms) -- AssertionError: GET /directory/users/{userId} ignored the path parameter: asked for 6aaa783b5a1d688484cf3045, got 6aaa783f5a1d688484cf3059 (team.qa.auto+aaron35-aa19222eed3b@mailinator.com). A ghost id and a malformed id ret | M24: Trangqle | N24: 46281
A25: BUG-API-023 | B25: 2061403 | C25: PARTNER_API_PARTNER_TEAM_003 | D25: Partner | E25: PARTNER_TEAM | F25: Major | G25: P2 | H25: Open | I25: team member deals and commissions - own records, scoped. | J25: team member deals and commissions - own records, scoped. | K25: FAIL | [6/7] The rollup must DISCRIMINATE between members (547ms) -- AssertionError: GET /directory/users/{userId}/deals ignores the path parameter: the member 6aab91e1b8ca8e4baea2a4ca registered NO deals, yet asking for it returns the same 1 row(s) | L25: FAIL | [6/7] The rollup must DISCRIMINATE between members (547ms) -- AssertionError: GET /directory/users/{userId}/deals ignores the path parameter: the member 6aab91e1b8ca8e4baea2a4ca registered NO deals, yet asking for it returns the same 1 row(s) as the session user who registered them. A ghost u | M25: Trangqle | N25: 46282
A26: BUG-API-024 | B26: 2060124 | C26: PARTNER_API_PARTNER_ACCOUNT_MANAGEMENT_024 | D26: Partner | E26: PARTNER_ACCOUNT_MANAGEMENT | F26: Critical | G26: P1 | H26: Close | I26: PATCH /v1/sa/partners/:id accepts fields UpdatePartnerDto does not expose. _id -&gt; HTTP 500 leaking the MongoDB error; code and status are silently written. Writing status moves a PENDING partner straight to active. | J26: A field outside UpdatePartnerDto is ignored or refused with 400 — never a 5xx, never a write. status must change only through POST /partners/:id/approve|deactivate, so the 3-stage approval FSM (PRD §12.1 B3: SA Review -&gt; Legal Countersign -&gt; SA Final Approval) cannot be skipped. Error bodies must not expose the storage engine. | K26: PATCH {"_id": "&lt;ghost&gt;"} -&gt; 500 "Plan executor error during findAndModify :: caused by :: Performing an update on the path '_id' would modify the immutable field '_id'". PATCH {"code": "QA-HACKED"} -&gt; 200 and the partner code is overwritten. PATCH {"status": "active"} -&gt; 200 and a pending partner becomes active without approve. | L26: PARTNER_API_PARTNER_ACCOUNT_MANAGEMENT_024 step [5/5], staging 2026-09-17, BE v26 @ 0b35609. Each field sent on its own so the failing one is named. The positive TC _023 passes: the 6 declared fields persist and a repeat PATCH is idempotent. | M26: Trangqle | N26: 46282 | O26: 46300 | P26: NEEDS BE CONFIRMATION on the status part: is writing status through PATCH intended for SA, or an FSM bypass? The _id 500 and the writable code are defects either way.
A27: BUG-API-025 | B27: 2060236 | C27: PARTNER_API_DEAL_REGISTRATION_PIPELINE_036 | D27: Partner | E27: DEAL_REGISTRATION_PIPELINE | F27: Major | G27: P1 | H27: Close | I27: GET /v1/sa/deals: limit=0 and page=abc are accepted and the endpoint returns the ENTIRE result set in one page (1406 deals). limit=-1 is correctly refused with 400. | J27: Any nonsensical pagination value is refused with 400, the same way limit=-1 already is. A page size must never resolve to unbounded. | K27: GET /v1/sa/deals?limit=0 -&gt; 200, data[] holds 1406 rows. GET /v1/sa/deals?page=abc -&gt; 200, data[] holds 1406 rows. GET /v1/sa/deals?limit=-1 -&gt; 400 "Invalid pagination: limit must be a positive integer". | L27: PARTNER_API_DEAL_REGISTRATION_PIPELINE_036 step [3/4], staging 2026-09-21, BE v26 @ 0b35609. The positive TC _035 passes: partnerId, status and dealType all narrow correctly and limit=1 caps the page. | M27: Trangqle | N27: 46286 | O27: 46300 | P27: Impact is a full-table dump per request, not just a validation gap — worth checking whether other list endpoints share the same pagination guard.
A28: BUG-API-026 | B28: 2060908 | C28: PARTNER_API_PARTNER_PORTAL_008 | D28: Partner | E28: PARTNER_PORTAL | F28: Major | G28: P2 | H28: Close | I28: GET /v1/partner/portal/modules: groupByCategory=true returns rows that are only {"_id": "undefined"}, and no pagination value is validated (limit=-1, limit=0 and page=abc all answer 200 with the whole catalogue). | J28: groupByCategory=true returns usable groups (a category name and its modules). Nonsensical pagination is refused with 400 — GET /v1/sa/deals already refuses limit=-1, so the service knows how to do this. | K28: GET /portal/modules?groupByCategory=true -&gt; 200, total=23, data[] holds 10 objects each exactly {"_id": "undefined"} — the literal JS string "undefined", no name, no members. GET /portal/modules?limit=-1 -&gt; 200 (1 row); ?limit=0 and ?page=abc -&gt; 200 with all 23 rows. | L28: PARTNER_API_PARTNER_PORTAL_008 steps [4/5] and [5/5], staging 2026-09-21, BE v26 @ 0b35609. The positive TC _007 passes: the plain catalogue, the name filter, and both team-certification filters all narrow correctly. | M28: Trangqle | N28: 46286 | O28: 46300 | P28: The pagination half is the same class as BUG-API-025 on /v1/sa/deals but a different endpoint and stricter: /sa/deals at least refuses limit=-1, this one refuses nothing.
A29: BUG-API-027 | B29: 2061510 | C29: PARTNER_API_CLIENT_HEALTH_MSP_010 | D29: Partner | E29: CLIENT_HEALTH_MSP | F29: Minor | G29: P3 | H29: Close | I29: GET /v1/partner/portal/clients: limit=0 and page=abc are not validated and answer 200. limit=-1 IS refused with 400, so the guard exists on this very endpoint and simply misses the other two values. | J29: A nonsensical page size or page number is refused with 400, consistently with limit=-1 on the same endpoint and with GET /v1/sa/deals. | K29: GET /portal/clients?limit=-1 -&gt; 400 (correct). ?limit=0 -&gt; 200. ?page=abc -&gt; 200. Both returned 0 rows, but only because the caller had no clients: the value was accepted rather than rejected, so the row count proves nothing about the guard. | L29: PARTNER_API_CLIENT_HEALTH_MSP_010 step [4/4], staging 2026-09-21, BE v26 @ 0b35609. The rest of the TC passes: a ghost attribution id and a malformed id are both refused with 400 and neither refusal leaks client row fields. The positive TC _001 passes in full, including JWT scoping (a partnerId in the query does not widen the result). | M29: Trangqle | N29: 46286 | P29: Third endpoint with the same root cause, after BUG-API-025 (/v1/sa/deals) and BUG-API-026 (/v1/partner/portal/modules) — worth ONE shared fix rather than three. Severity is lower here only because this list is empty on staging (no attribution is reachable, G2); the same miss on /sa/deals dumps 1406 rows in a single page, so the impact returns as soon as a partner owns clients.
A30: BUG-API-028 | B30: 2061613 | C30: PARTNER_API_TENANT_PROVISIONING_ATTRIBUTION_013 | D30: Partner | E30: TENANT_PROVISIONING_ATTRIBUTION | F30: Major | G30: P2 | H30: Close | I30: GET /v1/sa/partner-attributions: limit=0 and page=abc are not validated and answer 200 with the whole ledger. limit=-1 IS refused with 400, so the guard exists on this very endpoint and misses the other two values. | J30: A nonsensical page size or page number is refused with 400, consistently with limit=-1 on the same endpoint. | K30: GET /v1/sa/partner-attributions?limit=-1 -&gt; 400 "Invalid pagination: limit must be a positive integer" (correct). ?limit=0 -&gt; 200 with all 10 rows. ?page=abc -&gt; 200 with all 10 rows. Unlike the portal twin this list is NOT empty, so the caller receives the entire SA-wide ledger in one page. | L30: PARTNER_API_TENANT_PROVISIONING_ATTRIBUTION_013 step [4/4], staging 2026-09-23, BE v26. The rest of the TC passes: status/clientLifecycleState outside the enum -&gt; 400 listing the allowed values, malformed partnerId and malformed attribution id -&gt; 400, ghost partnerId -&gt; 200 empty, ghost attribution id -&gt; 400. The positive TC _012 passes in full (10 rows across 6 distinct partners, partnerId filter narrows 10 -&gt; 1, detail route returns the requested row). | M30: Trangqle | N30: 46288 | O30: 46300 | P30: FOURTH endpoint with the identical root cause: BUG-API-025 (/v1/sa/deals), BUG-API-026 (/v1/partner/portal/modules), BUG-API-027 (/v1/partner/portal/clients), now this one. Every instance refuses limit=-1 and accepts limit=0 and page=abc, which points at one shared pagination validator rather than four separate misses. Recommend BE fix it once at that layer and close all four together.
A31: BUG-API-029 | B31: 2060910 | C31: PARTNER_API_PARTNER_PORTAL_010 | D31: Partner | E31: PARTNER_PORTAL | F31: Major | G31: P2 | H31: Close | I31: GET /v1/partner/portal/plans/{planId}: the path parameter named planId is the only value it will NOT accept. The route matches on the mongo _id; a plan's own planId slug answers 400 'Invalid id'. | J31: The parameter documented by the route's own @ApiParam as a 'Kebab-case plan key, e.g. pro-annual' resolves the plan. Either the implementation should query { planId: &lt;slug&gt; }, or the route, @ApiParam and the service docstring should all say _id. | K31: GET /portal/plans returns rows carrying both _id and planId. GET /portal/plans/6aa76eab1e7d8bcb2279dd3f (the _id) -&gt; 200 with the plan. GET /portal/plans/full-modules-ss (that same row's planId) -&gt; 400 "Invalid id: 'full-modules-ss'". partner-lookup.service.ts getPlanByPlanId queries { _id: planId, status: PUBLISHED } while its docstring says 'Fetches a published billing plan by its planId slug'. | L31: PARTNER_API_PARTNER_PORTAL_010 step [2/4], staging 2026-09-23, BE v26. The rest of the pair passes: _009 verifies the catalogue is published standard editions only with unique ids/slugs and an exact detail match by _id; _010 confirms a ghost key -&gt; 404 naming it and 'not-a-plan'/'%20'/'null' -&gt; 400. | M31: Trangqle | N31: 46288 | O31: 46300 | P31: Contract-level, not a crash: the deal-registration form works because it passes _id. The cost is that any client written from the OpenAPI spec fails 100% of the time, and the naming actively misleads - a reader has no way to tell from the route that planId means _id. Low fix cost either way; BE only needs to decide which side is authoritative. NOT related to the pagination family (BUG-API-025/026/027/028).
A32: BUG-API-030 | B32: 2060324 | C32: PARTNER_API_COMMISSIONS_PAYOUTS_024 | D32: Partner | E32: COMMISSIONS_PAYOUTS | F32: Minor | G32: P3 | H32: Close | I32: GET /v1/partner/portal/commissions: limit=0 and page=abc are not validated and answer 200. limit=-1 IS refused with 400 on the same endpoint. | J32: A nonsensical page size or page number is refused with 400, consistently with limit=-1 on the same endpoint. | K32: ?limit=-1 -&gt; 400 'Invalid pagination: limit must be a positive integer' (correct). ?limit=0 -&gt; 200. ?page=abc -&gt; 200. Both returned 0 rows, but only because no commission exists anywhere on staging (G1): the value was accepted rather than rejected, so the row count proves nothing about the guard. | L32: PARTNER_API_COMMISSIONS_PAYOUTS_024 step [3/3], staging 2026-09-24, BE v26. The rest of the pair passes: status='bogus' -&gt; 400 listing all eight statuses; the positive TC _020 passes in full (envelope, all 8 status values accepted, ledger agrees with its summary, a partnerId in the query does not widen the JWT scope). | M32: Trangqle | N32: 46289 | O32: 46300 | P32: FIFTH endpoint with the identical root cause: BUG-API-025 (/v1/sa/deals), 026 (/v1/partner/portal/modules), 027 (/v1/partner/portal/clients), 028 (/v1/sa/partner-attributions), now this one. Every instance refuses limit=-1 and accepts limit=0 and page=abc. Five independent misses of the same two values is not plausible - this is one shared pagination validator, and one fix at that layer should close all five together. Filed separately only so each failing TC has its own traceable row; recommend BE treat 025/026/027/028/030 as a single defect.
A33: BUG-API-031 | B33: 2061402 | C33: PARTNER_API_PARTNER_TEAM_002 | D33: Partner | E33: PARTNER_TEAM | F33: Major | G33: P2 | H33: Close | I33: Partner team directory read-by-id ignores the path parameter: a ghost (well-formed, absent) userId is not rejected, and a malformed userId is not rejected. | J33: GET /v1/partner/directory/users/{userId}: a ghost (well-formed but non-existent) userId -&gt; 404 not found; a malformed userId -&gt; 400 invalid id. | K33: ghost userId 000000000000000000000000 -&gt; HTTP 200 returning a DIFFERENT user (userId=6aba0a4b...); malformed userId 'not-an-id' -&gt; HTTP 200. The path parameter is ignored, so a caller reading a member it never asked for gets no error at all. | L33: FAIL test_partner_api_partner_team_002 (run 2026-09-28): 'Validation gaps on /v1/partner/directory/users: ghost userId 000...000 returned HTTP 200 with userId=6aba0a4b... instead of 404; malformed userId not-an-id returned HTTP 200 instead of 400.' | M33: Trangqle | N33: 46293 | O33: 46300 | P33: Negative counterpart of BUG-API-022 (2061401) - SAME root cause: GET /directory/users/{userId} ignores the path param. Fix together with BUG-API-022/023.
A34: BUG-API-032 | B34: 2061404 | C34: PARTNER_API_PARTNER_TEAM_004 | D34: Partner | E34: PARTNER_TEAM | F34: Major | G34: P2 | H34: Open | I34: Team member deals/commissions read ignores the path parameter: a ghost/malformed userId is not rejected (reads as a member with no records). | J34: GET /v1/partner/directory/users/{userId}/{deals,commissions}: a ghost userId -&gt; 404 not found; a malformed userId -&gt; 400 invalid id. | K34: ghost userId -&gt; HTTP 200 with 0 rows (expected 404); malformed userId -&gt; HTTP 200 with 0 rows (expected 400). Path param ignored -&gt; a non-existent member reads as one that simply has no records; the same call returns ANOTHER member's deals when there ARE any (see BUG-API-023 / _003) = cross-member data disclosure risk. | L34: FAIL test_partner_api_partner_team_004 (run 2026-09-28): 'Validation gaps on /v1/partner/directory/users/{userId}/{deals,commissions}: ghost userId answered 200 with 0 rows, expected 404 - the path parameter is ignored (BUG-API-023); malformed userId answered 200 with 0 rows, expected 400.' | M34: Trangqle | N34: 46293 | P34: Negative counterpart of BUG-API-023 (2061403) - SAME root cause: GET /directory/users/{userId}/{deals,commissions} ignores the path param. Fix together with BUG-API-022/023.
A35: BUG-API-033 | B35: 2061602 | C35: PARTNER_API_TENANT_PROVISIONING_ATTRIBUTION_002 | D35: Partner | E35: TENANT_PROVISIONING_ATTRIBUTION | F35: Critical | G35: P1 | H35: Close | I35: Winning a deal never provisions a tenant on staging. After a successful win (status=won, message 'tenant provisioning kicked off'), the async provision chain never completes: provisioningState stays 'awaited', wonTenantId and goLiveAt are never stamped. Across ALL staging deals byProvisioningState.resolved=0 (won=262, overdue=117, awaited=3) — i.e. 0/262 won deals have ever provisioned. | J35: After win, the event-driven chain (blazeup.partner.deal.won -&gt; ms-sa-partners -&gt; SA /internal/tenants/provision -&gt; blazeup.tenant.provisioned) completes within a bounded time: wonTenantId + goLiveAt stamped on the WON deal, provisioningState -&gt; resolved, tenant appears in SA Tenant Management, admin creds email sent. (PRD v1.8 §7.1 Referral Close -&gt; Provision Flow; partner_requirement §7.1 BE=Done.) | K35: Deal _id 6a44cd20ce54e808583cf38c (UI 583CF38C, reseller) won 2026-10-01 09:21:04Z. GET /v1/sa/deals/{id}: provisioningState='awaited', wonTenantId=null, goLiveAt=null; updatedAt frozen = closedAt (09:21:04Z) even 15+ min later -&gt; nothing written to the deal after win. GET /v1/sa/deals/stats byProvisioningState = {awaited:3, overdue:117, resolved:0, legacy_unknown:0}, won=262. | L35: GET /v1/sa/deals/{id} + GET /v1/sa/deals/stats, staging 2026-10-01, BE v26.9. approve+win both succeed via API (approve needs plan catalog _id; win needs adminPhoneNumber{number,countryCode}). TCs PARTNER_API_TENANT_PROVISIONING_ATTRIBUTION_002 and _007 BLOCKED on this. Polled 95s + re-checked 15min: no change. | M35: Trangqle | N35: 46297 | P35: Raised at Khoa's (BE) request. BLOCKER for the entire commission test group (A/B/C): provisioning is upstream of billing/payment/accrual, so commission cannot be reached until this is fixed (goLiveAt is required for the accrual eligibility window). partner_requirement §7.1 marked BE=Done but no deal provisions on staging -&gt; the provisioning worker (deal.won consumer -&gt; /internal/tenants/provision -&gt; the tenant.provisioned consumer that stamps wonTenantId/goLiveAt) appears not running/deployed on staging. No public endpoint exists to trigger provision manually; /v1/sa/deals/{id}/link-tenant only links an already-provisioned tenant.
A36: BUG-API-034 | B36: 2060413 | C36: PARTNER_API_TERRITORIES_013 | D36: Partner | E36: TERRITORIES | F36: Major | G36: P2 | H36: Close | I36: list territories invalid filter/pagination - rejected (4xx, never 5xx). | J36: list territories invalid filter/pagination - rejected (4xx, never 5xx). | K36: CHECK page=0 → FAIL (status=400, msg="['page must not be less than 1']") | L36: CHECK page=0 → FAIL (status=400, msg="['page must not be less than 1']") | M36: Trangqle | N36: 46300 | O36: 46303 | P36: CLOSED 2026-10-08 - NOT A DEFECT (invalid). BE behavior is correct: page=0/page=-1 -&gt; 400 "page must not be less than 1". The TC failed only because the test asserted a stale expected-message hint ("non-negative"); status 400 already matched. Auto-logged by AI Triage on 2026-10-05 when the BE FIXED pagination validation and the old hint stopped matching. Test hint corrected to "must not be less than 1" (2026-10-08); TC now PASSES.
A37: BUG-API-035 | B37: 2060514 | C37: PARTNER_API_CERTIFICATIONS_SA_014 | D37: Partner | E37: CERTIFICATIONS_SA | F37: Major | G37: P2 | H37: Close | I37: list SA certifications invalid filter/pagination - rejected (4xx, never 5xx). | J37: list SA certifications invalid filter/pagination - rejected (4xx, never 5xx). | K37: CHECK page=0 → FAIL (status=400, msg="['page must not be less than 1']") | L37: CHECK page=0 → FAIL (status=400, msg="['page must not be less than 1']") | M37: Trangqle | N37: 46300 | O37: 46303 | P37: CLOSED 2026-10-08 - NOT A DEFECT (invalid). BE behavior is correct: page=0/page=-1 -&gt; 400 "page must not be less than 1". The TC failed only because the test asserted a stale expected-message hint ("non-negative"); status 400 already matched. Auto-logged by AI Triage on 2026-10-05 when the BE FIXED pagination validation and the old hint stopped matching. Test hint corrected to "must not be less than 1" (2026-10-08); TC now PASSES.
A38: BUG-API-036 | B38: 2060711 | C38: PARTNER_API_PARTNER_USERS_011 | D38: Partner | E38: PARTNER_USERS | F38: Major | G38: P2 | H38: Close | I38: list partner-users invalid pagination/filter - graceful, never 5xx. | J38: list partner-users invalid pagination/filter - graceful, never 5xx. | K38: CHECK page=0 → FAIL (status=400, msg="['page must not be less than 1']") | L38: CHECK page=0 → FAIL (status=400, msg="['page must not be less than 1']") | M38: Trangqle | N38: 46300 | O38: 46303 | P38: CLOSED 2026-10-08 - NOT A DEFECT (invalid). BE behavior is correct: page=0/page=-1 -&gt; 400 "page must not be less than 1". The TC failed only because the test asserted a stale expected-message hint ("non-negative"); status 400 already matched. Auto-logged by AI Triage on 2026-10-05 when the BE FIXED pagination validation and the old hint stopped matching. Test hint corrected to "must not be less than 1" (2026-10-08); TC now PASSES.
A39: BUG-API-037 | B39: 2060102 | C39: PARTNER_API_PARTNER_ACCOUNT_MANAGEMENT_002 | D39: Partner | E39: PARTNER_ACCOUNT_MANAGEMENT | F39: Major | G39: P2 | H39: Close | I39: POST create internal partner - a pending account is created. | J39: status (201,) | K39: 400: {"statusCode":400,"message":"The requester cannot be an approver on their own request","error":"Bad Request","timestamp":"2026-10-05T09:26:43.400Z","pat | L39: FAIL | [1/5] Call API: POST /v1/sa/partners (create 'QA-AUTO Obrien, Burton and Grant') (393ms) -- AssertionError: Expected status (201,), got 400: {"statusCode":400,"message":"The requester cannot be an approver on their own request","error":"Bad Request","timestamp":"2026-10-05T09:26:43.400Z","pat | M39: Trangqle | N39: 46300
A40: BUG-API-038 | B40: 2060103 | C40: PARTNER_API_PARTNER_ACCOUNT_MANAGEMENT_003 | D40: Partner | E40: PARTNER_ACCOUNT_MANAGEMENT | F40: Major | G40: P2 | H40: Close | I40: POST partner approve - activation + approval event are created. | J40: status (201,) | K40: 400: {"statusCode":400,"message":"The requester cannot be an approver on their own request","error":"Bad Request","timestamp":"2026-10-05T09:26:43.400Z","pat | L40: FAIL | [1/5] Call API: POST /v1/sa/partners (create 'QA-AUTO Obrien, Burton and Grant') (393ms) -- AssertionError: Expected status (201,), got 400: {"statusCode":400,"message":"The requester cannot be an approver on their own request","error":"Bad Request","timestamp":"2026-10-05T09:26:43.400Z","pat | M40: Trangqle | N40: 46300
A41: BUG-API-039 | B41: 2060201 | C41: PARTNER_API_DEAL_REGISTRATION_PIPELINE_001 | D41: Partner | E41: DEAL_REGISTRATION_PIPELINE | F41: Major | G41: P2 | H41: Close | I41: register a partner deal - deal is created (registered). | J41: status (201,) | K41: 400: {"statusCode":400,"message":"The requester cannot be an approver on their own request","error":"Bad Request","timestamp":"2026-10-05T09:26:43.400Z","pat | L41: FAIL | [1/5] Call API: POST /v1/sa/partners (create 'QA-AUTO Obrien, Burton and Grant') (393ms) -- AssertionError: Expected status (201,), got 400: {"statusCode":400,"message":"The requester cannot be an approver on their own request","error":"Bad Request","timestamp":"2026-10-05T09:26:43.400Z","pat | M41: Trangqle | N41: 46300
A42: BUG-API-040 | B42: 2060208 | C42: PARTNER_API_DEAL_REGISTRATION_PIPELINE_008 | D42: Partner | E42: DEAL_REGISTRATION_PIPELINE | F42: Major | G42: P2 | H42: Close | I42: internal deal approve - approved + rate/rate-table version stamped. | J42: status (201,) | K42: 400: {"statusCode":400,"message":"The requester cannot be an approver on their own request","error":"Bad Request","timestamp":"2026-10-05T09:26:43.400Z","pat | L42: FAIL | [1/5] Call API: POST /v1/sa/partners (create 'QA-AUTO Obrien, Burton and Grant') (393ms) -- AssertionError: Expected status (201,), got 400: {"statusCode":400,"message":"The requester cannot be an approver on their own request","error":"Bad Request","timestamp":"2026-10-05T09:26:43.400Z","pat | M42: Trangqle | N42: 46300
A43: BUG-API-041 | B43: 2060218 | C43: PARTNER_API_DEAL_REGISTRATION_PIPELINE_018 | D43: Partner | E43: DEAL_REGISTRATION_PIPELINE | F43: Major | G43: P2 | H43: Close | I43: SA marks an approved deal as won - status 'won' + provisioning/commission events emitted. | J43: status (201,) | K43: 400: {"statusCode":400,"message":"The requester cannot be an approver on their own request","error":"Bad Request","timestamp":"2026-10-05T09:26:43.400Z","pat | L43: FAIL | [1/5] Call API: POST /v1/sa/partners (create 'QA-AUTO Obrien, Burton and Grant') (393ms) -- AssertionError: Expected status (201,), got 400: {"statusCode":400,"message":"The requester cannot be an approver on their own request","error":"Bad Request","timestamp":"2026-10-05T09:26:43.400Z","pat | M43: Trangqle | N43: 46300
A44: BUG-API-042 | B44: 2061510 | C44: PARTNER_API_CLIENT_HEALTH_MSP_010 | D44: Partner | E44: CLIENT_HEALTH_MSP | F44: Minor | G44: P3 | H44: Open | I44: GET /v1/partner/portal/clients/:id returns 404 for a MALFORMED (non-ObjectId) id instead of 400. The route skips id-format validation and treats a malformed id as 'not found', inconsistent with the SA :id routes. | J44: A malformed (non-ObjectId) path id is rejected with 400 'Invalid id' (format validated before the existence/ownership check), consistent with /sa/partners/:id and the deal :id routes. A 400 for a malformed id does NOT weaken the no-existence-oracle property, which only requires ghost == foreign == 404. | K44: GET /v1/partner/portal/clients/not-an-id -&gt; 404 'Client not-an-id not found' (staging 2026-10-06). A well-formed ghost id and a real foreign id both correctly return 404; only the malformed-id case is wrong (should be 400). | L44: PARTNER_API_CLIENT_HEALTH_MSP_010 step [3/5], staging 2026-10-06 (run_20261006_134511). Rest of the TC passes (ghost-&gt;404, foreign-&gt;404 identical no-oracle, pagination limit=-1/0 &amp; page=abc-&gt;400). -- [3/5] a malformed attribution id answered 404, expected 400 | M44: Trangqle | N44: 46301 | P44: Split from BUG-API-027 (pagination limit=0/page=abc -&gt; 200), which is now FIXED (limit=0 -&gt; 400) -&gt; close BUG-API-027. This is the DISTINCT remaining cause on the same TC (2061510), surfaced by the triage 'signature changed' detection. Low severity: no data leak, no crash -- a status-code/contract inconsistency only (should mirror the SA endpoints' 400 'Invalid id'). Confirm with BE whether portal /clients/:id should validate id format (400) or intentionally returns 404 uniformly.
A45: BUG-API-043 | B45: 2061602 | C45: PARTNER_API_TENANT_PROVISIONING_ATTRIBUTION_002 | D45: Partner | E45: TENANT_PROVISIONING_ATTRIBUTION | F45: Critical | G45: P1 | H45: Open | I45: POST /v1/sa/deals/{id}/win is UNCALLABLE: billingCycle case mismatch between WinDealDto (lowercase monthly|annual) and the downstream provisioning intake (UPPERCASE MONTHLY|ANNUAL). No value satisfies both validators, so an approved deal can no longer be won at all. | J45: Winning an approved deal with the DTO-documented billingCycle ('annual') returns 201 and status 'won' — the BE normalizes/maps the value when building the provisioning intake (e.g. toUpperCase), or the two enums use the same casing. | K45: billingCycle='annual' -&gt; 400 'Tenant provisioning failed: [INVALID_PAYLOAD] intake.billingCycle: billingCycle must be one of the following values: MONTHLY, ANNUAL'. billingCycle='ANNUAL' -&gt; 400 'billingCycle must be one of the following values: monthly, annual' (WinDealDto refuses it before provisioning). Both verified on staging 2026-10-06. | L45: PARTNER_API_TENANT_PROVISIONING_ATTRIBUTION_002 step [1/4], staging 2026-10-06 (run_20261006_154346). Sending 'ANNUAL' instead is refused by WinDealDto itself: 400 ['billingCycle must be one of the following values: monthly, annual'] (run_20261006_155040), so no value satisfies both validators. FAIL | [1/4] Mark the approved deal as won (win intake incl. required adminPhoneNumber) -&gt; status 'won' (321ms) -- AssertionError: Expected status (201,), got 400: {"statusCode":400,"message":"Tenant provisioning failed: [INVALID_PAYLOAD] intake.billingCycle: billingCycle must be one of the following values: MONTHLY, ANNUAL","error":"Tenant provisioning failed: [INVALID_PAYLOAD] intake.billingCycle: billingCycle must be one of the following values: MONTHLY, ANNUAL","timestamp":"2026-10-06T08:43:53.300Z","path":"/sa-partners-api/v1/sa/deals/6ac4b4c8d1eeecba2e946c97/win"} | M45: Trangqle | N45: 46301 | P45: REGRESSION: win returned 201 and reached status 'won' on 2026-10-02 (same TC). The BE has since wired the provisioning call into /win and now surfaces its INVALID_PAYLOAD, but the two enums disagree on case. BLOCKS the whole won -&gt; provision -&gt; bill -&gt; commission chain, and blocks re-verifying BUG-API-033 (provisioning never completes) because win can no longer succeed. Also note register stores billingCycle lowercase ('annual'), so the lowercase form is the one the deal itself carries. Fix: normalize the value when mapping WinDealDto -&gt; provisioning intake, or align the enums. Surfaced by the triage 'signature changed' detection (the old BUG-API-033 cause no longer reproduces).
A46: BUG-API-044 | B46: 2060221 | C46: PARTNER_API_DEAL_REGISTRATION_PIPELINE_021 | D46: Partner | E46: DEAL_REGISTRATION_PIPELINE | F46: Major | G46: P2 | H46: Close | I46: register deal invalid/missing fields - rejected with 400. | J46: register deal invalid/missing fields - rejected with 400. | K46: CHECK ghost planId (verified absent above) → FAIL (status=403, msg='Partner account is not active') | L46: CHECK ghost planId (verified absent above) → FAIL (status=403, msg='Partner account is not active') | M46: Trangqle | N46: 46303
A47: BUG-API-045 | B47: 2061009 | C47: PARTNER_API_AUTH_ACCESS_CONTROL_009 | D47: Partner | E47: AUTH_ACCESS_CONTROL | F47: Minor | G47: P2 | H47: Open | I47: Partner login answers 400 instead of 401 for invalid credentials (wrong or no-longer-valid password). | J47: POST /v1/partner/auth/login with a wrong or no-longer-valid password -&gt; 401 Unauthorized (failed authentication). This is what it returned until 2026-10-09, and what the rest of the partner auth module still returns: change-password with a wrong current password -&gt; 401, invalid refresh token -&gt; 401, missing token -&gt; 401. | K47: 400 Bad Request {"message":"Invalid credentials"}. The credential IS rejected - only the status code is wrong. Seen on every failed partner login in run_20261014_133423 (5 TCs). Account lockout also answers 400 ("Too many failed login attempts"). | L47: FAIL | [4/4] The OLD password is rejected (401) (746ms) -- AssertionError: old password must be rejected (401), got 400 (run 2026-10-14) | M47: Trangqle | N47: 46309 | P47: ALSO FAILS: TC-2061405 (PARTNER_API_PARTNER_TEAM_005) step [4/8] 'The OLD password must stop working' - rejected with 400 instead of 401 after an admin password reset. Same root cause, so one bug. Changed between 2026-10-09 (401; both TCs PASSED) and 2026-10-13. Swagger documents only 200 for login, so no contract states 400. Minor: behaviour is correct (the old password is refused), the status code is not.
A49: UI
A50: BUG-UI-001 | B50: 12060101 | C50: PARTNER_UI_PARTNER_PORTAL_SHELL_001 | D50: Partner | E50: PARTNER_PORTAL_SHELL | F50: Major | G50: P2 | H50: Close | I50: Partner Portal /apps (My Apps): app-list fails to load — "Failed to load your apps" banner (data-fetch/backend defect) | J50: Every primary nav page loads its content with no error banner — /apps shows the app list (or a valid empty state). | K50: /apps shell renders (title "My Apps" + tabs + Submit button) but the app-list data-fetch fails -> red banner "Failed to load your apps. Please refresh and try again." | L50: Page [apps] FAILED - Partner Portal section 'apps' rendered its shell but the CONTENT failed to load: banner 'Failed to load' is visible in &lt;main&gt;. Data-fetch/backend issue for this page — confirm with BE. | M50: Trangqle | N50: 46226 | O50: 46296
A51: BUG-UI-002 | B51: 12060102 | C51: PARTNER_UI_PARTNER_PORTAL_SHELL_002 | D51: Partner | E51: PARTNER_PORTAL_SHELL | F51: Major | G51: P2 | H51: Close | I51: portal stays usable at mobile width (no h-overflow, nav reachable). | J51: portal stays usable at mobile width (no h-overflow, nav reachable). | K51: Page [deals] FAILED - 'deals' overflows the mobile viewport by 162px (content does not fit 375px → responsive-layout defect; confirm with FE) | L51: Page [deals] FAILED - 'deals' overflows the mobile viewport by 162px (content does not fit 375px → responsive-layout defect; confirm with FE) | M51: Trangqle | N51: 46227 | O51: 46296
A52: BUG-UI-003 | B52: 12060203 | C52: PARTNER_UI_MY_PIPELINE_003 | D52: Partner | E52: MY_PIPELINE | F52: Major | G52: P2 | H52: Close | I52: an invalid domain must be rejected with a format error. | J52: an invalid domain must be rejected with a format error. | K52: FAIL | [1/1] Each malformed domain must be rejected (block Next / flag field) (246ms) -- AssertionError: wizard accepts invalid domain(s) ["'@@@' (field kept '@@@', Next enabled, not flagged)", "'ab cd' (field kept 'ab cd', Next enabled, not flagged) | L52: FAIL | [1/1] Each malformed domain must be rejected (block Next / flag field) (246ms) -- AssertionError: wizard accepts invalid domain(s) ["'@@@' (field kept '@@@', Next enabled, not flagged)", "'ab cd' (field kept 'ab cd', Next enabled, not flagged)", "'notadomain' (field kept 'notadomain', Next en | M52: Trangqle | N52: 46230 | O52: 46296
A53: BUG-UI-004 | B53: 12060207 | C53: PARTNER_UI_MY_PIPELINE_007 | D53: Partner | E53: MY_PIPELINE | F53: Major | G53: P2 | H53: Close | I53: a malformed contact email must be rejected with a format error. | J53: a malformed contact email must be rejected with a format error. | K53: FAIL | [1/1] Each malformed email must be rejected (block Next / flag field) (246ms) -- AssertionError: wizard accepts malformed email(s) ["'notanemail' (field kept 'notanemail', Next enabled, not flagged)", "'abc@' (field kept 'abc@', Next enabled, | L53: FAIL | [1/1] Each malformed email must be rejected (block Next / flag field) (246ms) -- AssertionError: wizard accepts malformed email(s) ["'notanemail' (field kept 'notanemail', Next enabled, not flagged)", "'abc@' (field kept 'abc@', Next enabled, not flagged)", "'abc@x' (field kept 'abc@x', Next | M53: Trangqle | N53: 46230 | O53: 46238 | P53: Re-check is PASS
A54: BUG-UI-005 | B54: 12060507 | C54: PARTNER_UI_SA_PARTNER_MODULE_007 | D54: Partner | E54: SA_PARTNER_MODULE | F54: Major | G54: P2 | H54: Close | I54: SA Deal Approval Queue (/partners/deals): deal-list API INTERMITTENTLY returns "Server Error - Invalid id: pro-v1" instead of the deals. | J54: GET deal-list for /partners/deals always returns the deals (200); the queue table shows deal rows. No "Invalid id" error. | K54: INTERMITTENT: the SAME deal-list endpoint sometimes returns the deals (UI shows rows -&gt; test PASS) and sometimes returns "Server Error - Invalid id: pro-v1" (UI shows "No Data Found" -&gt; test FAIL). Not deterministic run-to-run. | L54: FAIL | [3/3] The Pending Approval + Conflicts queues load without a server error (3161ms) -- AssertionError: the deal approval queues must load their deals, but the deal-list fetch fails with a backend error on: ['Pending Approval: "Server Error Invalid id: \'pro-v1\' Server Error Invalid id: \'"', | M54: Trangqle | N54: 46232 | O54: 46244 | P54: Re-check is PASS
A55: BUG-UI-006 | B55: 12060511 | C55: PARTNER_UI_SA_PARTNER_MODULE_011 | D55: Partner | E55: SA_PARTNER_MODULE | F55: Major | G55: P2 | H55: Close | I55: the SA partner-programme analytics dashboard. | J55: the SA partner-programme analytics dashboard. | K55: FAIL | [3/3] The analytics data loads without a server error (44ms) -- AssertionError: the analytics dashboard must load its data, but a query fails with a backend error: 'Server Error limit must not be greater than 100 Server Error Invalid p'. The d | L55: FAIL | [3/3] The analytics data loads without a server error (44ms) -- AssertionError: the analytics dashboard must load its data, but a query fails with a backend error: 'Server Error limit must not be greater than 100 Server Error Invalid p'. The dashboard shell renders but a paginated analytics q | M55: Trangqle | N55: 46232 | O55: 46296
A56: BUG-UI-007 | B56: 12060405 | C56: PARTNER_UI_DASHBOARD_005 | D56: Partner | E56: DASHBOARD | F56: Major | G56: P2 | H56: Open | I56: tier-qualification math (T12M ARR threshold + next-tier delta). | J56: tier-qualification math (T12M ARR threshold + next-tier delta). | K56: FAIL | [2/3] Next-tier T12M ARR threshold target + remaining delta are shown (0ms) -- AssertionError: the next-tier T12M ARR threshold target and remaining delta must be shown in Tier Progress, but only current tier/ARR/deal-count are rendered (panel | L56: FAIL | [2/3] Next-tier T12M ARR threshold target + remaining delta are shown (0ms) -- AssertionError: the next-tier T12M ARR threshold target and remaining delta must be shown in Tier Progress, but only current tier/ARR/deal-count are rendered (panel='Tier &amp; Performance SELECT T12M ARR USD 0 Tier Pr | M56: Trangqle | N56: 46233
A57: BUG-UI-008 | B57: 12060515 | C57: PARTNER_UI_SA_PARTNER_MODULE_015 | D57: Partner | E57: SA_PARTNER_MODULE | F57: Major | G57: P2 | H57: Close | I57: suspend (deactivate) an active partner. | J57: SA can suspend an Active partner from Partner Detail -&gt; Partner actions -&gt; Deactivate: partner transitions to Suspended/Inactive and loses portal access. | K57: Deactivate fails. The "Deactivate Partner" confirm dialog collects NO reason, so the FE calls the deactivate API without one; BE returns 400 Server Error ("reason should not be empty / reason must be a string / reason must be &lt;= 2000 characters"). Partner stays Active. No SA can suspend a partner via the UI. | L57: FAIL | [2/2] The partner is suspended and no error is shown (0ms) -- AssertionError: Deactivate failed — the BE rejected the request: 'Failed to deactivate partner Server Error reason must be shorter than or equal to 2000 charactersreason should not be emptyreason must be a string Partner approved Q | M57: Trangqle | N57: 46234 | O57: 46296
A58: BUG-UI-009 | B58: 12060201 | C58: PARTNER_UI_MY_PIPELINE_001 | D58: Partner | E58: MY_PIPELINE | F58: Critical | G58: P1 | H58: Close | I58: Register-a-Deal wizard: Country dropdown is empty ('No options') on Chrome/Chromium (works on Edge). The wizard's countries lookup is sent WITHOUT an Authorization header -&gt; 401, so no country can be selected and a deal cannot be registered. | J58: On every browser (incl. Chrome) the Country dropdown lists countries; partner completes Step 1 and registers a deal. | K58: On Chrome/Chromium (manual AND automation), GET /sa-partners-api/v1/partner/portal/countries is sent with NO Authorization header -&gt; 401 -&gt; dropdown shows 'No options' -&gt; Step 1 cannot be completed. On Edge (manual) the same request carries the bearer token -&gt; 200 -&gt; options load. | L58: countries request hasAuth=false -&gt; 401 on Chromium (Playwright) and manual Chrome; 200 on manual Edge. Shell /partner/auth/refresh + /auth/me return 200, so the shell is authenticated but the token is not attached to the MFE's countries call. Manual repro: Chrome FAIL / Edge PASS. | M58: Trangqle | N58: 46293 | O58: 46296 | P58: Browser-specific (Chrome/Chromium FAIL, Edge PASS) at BOTH manual and automation level. Affects all 11 register-wizard TCs: 12060201-12060208, 12060211-12060213 (automation runs on Chromium -&gt; all fail). Leading hypothesis for FE: Chrome's stricter storage-partitioning / third-party-context defaults block the deals micro-frontend (partnerDealsApp, which has its own token-store bundle) from reading the auth token (pp_refresh_token in sessionStorage) -&gt; token not attached to the countries request. FE to verify how partnerDealsApp obtains/attaches the access token on Chrome. NOTE: AI triage mislabels these as [FLAKY] (Locator.click-timeout heuristic) - they are deterministic, not flaky.
A59: BUG-UI-010 | B59: 12060102 | C59: PARTNER_UI_PARTNER_PORTAL_SHELL_002 | D59: Partner | E59: PARTNER_PORTAL_SHELL | F59: Major | G59: P2 | H59: Close | I59: Partner Portal /directory overflows horizontally at mobile width (375px): the 'Invite User' button and the member table do not fit, so the whole page scrolls sideways. | J59: At 375×812 the Directory page fits the viewport (horizontal overflow ≤ 5px); the member table scrolls inside its own container if it is wider than the screen. | K59: The page overflows by +93px (scrollWidth 468 vs 375): the 'Invite User' button sticks out 93px and the member table (MEMBER / ROLE / STATUS / LAST LOGIN) is ~607px wider than the viewport with no overflow-x wrapper. | L59: Page [directory] FAILED - 'directory' overflows the mobile viewport by 93px (content does not fit 375px → responsive-layout defect; confirm with FE) | probe: documentElement.scrollWidth=468 vs clientWidth=375; 'Invite User' button right edge +93px; member &lt;table&gt; right edge +607px (no overflow-x container) | M59: Trangqle | N59: 46295 | O59: 46300 | P59: Distinct from BUG-UI-002 (Deals overflow, now fixed) — same TC, different page/cause, kept as its own bug. Other pages (dashboard/deals/commissions/resources) fit. Fix: wrap the member table in an overflow-x:auto container and let the header action bar wrap/stack on small screens.
A60: BUG-UI-011 | B60: 12060514 | C60: PARTNER_UI_SA_PARTNER_MODULE_014 | D60: Partner | E60: SA_PARTNER_MODULE | F60: Major | G60: P2 | H60: Close | I60: add a portal user (member) to a partner. | J60: add a portal user (member) to a partner. | K60: FAIL | Setup: onboard a throwaway partner and approve it to Active (41791ms) -- AssertionError: Onboard Partner did not settle within 30000 ms (no success toast and the form is still open). | L60: FAIL | Setup: onboard a throwaway partner and approve it to Active (41791ms) -- AssertionError: Onboard Partner did not settle within 30000 ms (no success toast and the form is still open). | M60: Trangqle | N60: 46300
A61: BUG-UI-012 | B61: 12060515 | C61: PARTNER_UI_SA_PARTNER_MODULE_015 | D61: Partner | E61: SA_PARTNER_MODULE | F61: Major | G61: P2 | H61: Close | I61: suspend (deactivate) an active partner. | J61: suspend (deactivate) an active partner. | K61: FAIL | Setup: onboard a throwaway partner and approve it to Active (41791ms) -- AssertionError: Onboard Partner did not settle within 30000 ms (no success toast and the form is still open). | L61: FAIL | Setup: onboard a throwaway partner and approve it to Active (41791ms) -- AssertionError: Onboard Partner did not settle within 30000 ms (no success toast and the form is still open). | M61: Trangqle | N61: 46300
A62: BUG-UI-013 | B62: 12060514 | C62: PARTNER_UI_SA_PARTNER_MODULE_014 | D62: Partner | E62: SA_PARTNER_MODULE | F62: Major | G62: P2 | H62: Close | I62: add a portal user (member) to a partner. | J62: add a portal user (member) to a partner. | K62: FAIL | Setup: onboard a throwaway partner and approve it to Active (40048ms) -- TimeoutError: Locator.click: Timeout 30000ms exceeded. | L62: FAIL | Setup: onboard a throwaway partner and approve it to Active (40048ms) -- TimeoutError: Locator.click: Timeout 30000ms exceeded. | M62: Trangqle | N62: 46304
A63: BUG-UI-014 | B63: 12060403 | C63: PARTNER_UI_DASHBOARD_003 | D63: Partner | E63: DASHBOARD | F63: Major | G63: P2 | H63: Open | I63: Partner dashboard is missing the Tier Progress card - PRD 4.3 design rule 'Tier progress bar is always visible' is not met. | J63: /dashboard shows a Tier Progress card: progress bar, current tier -&gt; next tier, and '$&lt;T12M ARR&gt; of $&lt;next-tier threshold&gt; &lt;next tier&gt;' (PRD 4.3; requirement sheet 4.3 'Tier progress bar'; backlog PP002 'Header: tier badge + T12M ARR progress'). | K63: Since the 2026-10 dashboard redesign no Tier Progress element is rendered anywhere on /dashboard. Only the header tier badge ('Registered') remains; the new 'Performance' panel shows deal counts + win rate only. Last seen rendered 2026-10-09 (old 'Tier &amp; Performance' panel). | L63: FAIL | [1/2] Tier Progress shows current tier + 'working towards' next tier (15ms) -- AssertionError: the Tier Progress component must be present (run_20261013_114021) | M63: Trangqle | N63: 46308 | P63: Same root cause also fails TC-12060407 step [3/3] ('Tier Progress' must still be highlighted). Kept SEPARATE from BUG-UI-007 (TC-12060405: tier card present but threshold/delta not shown) - 1 bug per distinct failure. Likely FE-only: GET /v1/partner/portal/dashboard already returns partner.tier='registered' + totalArrCents (run_20261013_103101); tier thresholds are fixed by requirement 2.1 (Select $50K / Advanced $200K / Premier $750K).
