Workbook

Sheet Summary
A1: TEST PLAN SUMMARY
A2: partner-platform-prd-v1.8 | Generated: 2026-05-20
A3: No. | B3: BLOCK | C3: TOTAL | D3: COMPLETED | E3: PASSED | G3: FAILED | I3: NOT STARTED | K3: IN PROGRESS | M3: BLOCKED
E4: Number | F4: Percent | G4: Number | H4: Percent | I4: Number | J4: Percent | K4: Number | L4: Percent | M4: Number | N4: Percent | O4: COMMENT | P4: OWNER
A5: 1 | B5: Partner Platform | C5: =COUNTA('Partner Platform'!C79:C1130) -> 163 | D5: =(E5+G5)/C5 -> 0.14110429 | E5: =COUNTIF('Partner Platform'!K79:K1130,"PASSED") -> 19 | F5: =E5/C5 -> 0.11656442 | G5: =COUNTIF('Partner Platform'!K79:K1130,"FAILED") -> 4 | H5: =G5/C5 -> 0.024539877 | I5: =COUNTIF('Partner Platform'!K79:K1130,"NOT_STARTED") -> 141 | J5: =I5/C5 -> 0.86503067 | K5: =COUNTIF('Partner Platform'!K79:K1130,"IN_PROGRESS") -> 0 | L5: =K5/C5 -> 0 | M5: =COUNTIF('Partner Platform'!K79:K1130,"BLOCKED") -> 0 | N5: =M5/C5 -> 0 | P5: Trang Le
B6: TOTAL | C6: =SUM(C5) -> 163 | D6: =(E6+G6)/C6 -> 0.14110429 | E6: =SUM(E5) -> 19 | F6: =E6/C6 -> 0.11656442 | G6: =SUM(G5) -> 4 | H6: =G6/C6 -> 0.024539877 | I6: =SUM(H5) -> 0.024539877 | J6: =I6/C6 -> 0.00015055139 | K6: =SUM(K5) -> 0 | L6: =K6/C6 -> 0 | M6: =SUM(M5) -> 0 | N6: =M6/C6 -> 0
A22: Status | B22: Count
A23: Pass | B23: =COUNTIF('Partner Platform'!G:G,"Pass") -> 0
A24: Fail | B24: =COUNTIF('Partner Platform'!G:G,"Fail") -> 0
A25: Not Started | B25: =COUNTIF('Partner Platform'!G:G,"Not Started") -> 0
A26: In Progress | B26: =COUNTIF('Partner Platform'!G:G,"In Progress") -> 0
A27: Type | B27: Count
A28: Type | B28: Count
A29: UI | B29: =COUNTA('Partner Platform'!B79:B94) -> 8
A30: API | B30: =COUNTA('Partner Platform'!A222:A295) -> 2
A31: Coverage | B31: Count
A32: Automation | B32: Count
A33: Automated | B33: 138
A34: Manual Only | B34: 6
A36: Priority | B36: Count
A37: P1 | B37: =COUNTIF('Partner Platform'!E:E,"P1") -> 0
A38: P2 | B38: =COUNTIF('Partner Platform'!E:E,"P2") -> 0
A39: P3 | B39: =COUNTIF('Partner Platform'!E:E,"P3") -> 0
A40: P4 | B40: =COUNTIF('Partner Platform'!E:E,"P4") -> 0

Sheet Partner Platform
A1: PARTNER PLATFORM — MODULE STATUS SUMMARY
A2: Item | B2: Description | C2: Summary | D2: Manual | E2: Automation
A3: TOTAL | B3: Total number of tests | C3: =SUM(C4:C8) -> 164 | D3: =SUM(D4:D8) -> 164 | E3: =SUM(E4:E8) -> 22
A4: PASSED | B4: Number of tests PASSED | C4: =COUNTIF('Partner Platform'!H79:H1130,"PASSED") -> 18 | D4: =COUNTIF('Partner Platform'!I79:I1130,"PASSED") -> 0 | E4: =COUNTIFS('Partner Platform'!K79:K1130,"PASSED",'Partner Platform'!J79:J1130,"YES") -> 18
A5: FAILED | B5: Number of tests FAILED | C5: =COUNTIF('Partner Platform'!H79:H1130,"FAILED") -> 4 | D5: =COUNTIF('Partner Platform'!I79:I1130,"FAILED") -> 0 | E5: =COUNTIFS('Partner Platform'!K79:K1130,"FAILED",'Partner Platform'!J79:J1130,"YES") -> 4
A6: NOT_STARTED | B6: Number of tests that have not been started | C6: =COUNTIF('Partner Platform'!H79:H1130,"NOT_STARTED") -> 126 | D6: =COUNTIF('Partner Platform'!I79:I1130,"NOT_STARTED") -> 148 | E6: =COUNTIFS('Partner Platform'!K79:K1130,"NOT_STARTED",'Partner Platform'!J79:J1130,"YES") -> 0
A7: IN_PROGRESS | B7: Number of tests currently being tested | C7: =COUNTIF('Partner Platform'!H79:H1130,"IN_PROGRESS") -> 0 | D7: =COUNTIF('Partner Platform'!I79:I1130,"IN_PROGRESS") -> 0 | E7: =COUNTIFS('Partner Platform'!K79:K1130,"IN_PROGRESS",'Partner Platform'!J79:J1130,"YES") -> 0
A8: BLOCKED | B8: Tests that could not be executed | C8: =COUNTIF('Partner Platform'!H79:H1130,"BLOCKED") -> 16 | D8: =COUNTIF('Partner Platform'!I79:I1130,"BLOCKED") -> 16 | E8: =COUNTIFS('Partner Platform'!K79:K1130,"BLOCKED",'Partner Platform'!J79:J1130,"YES") -> 0
A11: UI Test Cases
A12: Main Section | B12: Main Feature/Function | C12: Testcasename | D12: Testcase | E12: Test Type | F12: Priority | G12: Severity | H12: Status | I12: Manual Status | J12: Auto | K12: Automation Status | L12: Requirement Ref | M12: Docs Refer | N12: Bug ID | O12: Owner | P12: Note | Q12: Test Description | R12: Test Step | S12: Primary Ref
A13: Commissions | B13: Commissions & Payouts | C13: PARTNER_UI_COMMISSIONS_001 | D13: Calculate - Type estimated annual value - Commission projection updates live | E13: Functional | F13: P1 | G13: Critical | H13: =IF(J13="No",I13,IF(OR(I13="FAILED",K13="FAILED"),"FAILED",IF(OR(I13="PASSED",K13="PASSED"),"PASSED",IF(OR(I13="IN_PROGRESS",K13="IN_PROGRESS"),"IN_PROGRESS",IF(OR(I13="BLOCKED",K13="BLOCKED"),"BLOCKED","NOT_STARTED"))))) -> NOT_STARTED | I13: NOT_STARTED | J13: NO | K13: NOT_STARTED | L13: §4.4, Risk R2 | M13: partner-platform-prd-v1.8.md | O13: Trang Le | Q13: Validate the UI flow for type estimated annual value so that commission projection updates live. Scope covers the commission ledger, payout, dispute, waiver, clawback, rate, and approval behavior, authenticated partner/SA role access as applicable, visible copy/state, primary CTA behavior, and PRD coverage §4.4, Risk R2. Out of scope: unrelated modules and deep backend calculation beyond the data needed to prove this case. | R13: 1. Open the deal registration commercial/value step. 2. Select a partner tier/deal type fixture with known configured rate. 3. Type or change the estimated annual value/ACV. 4. Verify projected commission updates live with the correct currency, rate, and pending/estimated copy. 5. Confirm the projection carries through to review/confirmation and is not shown as final payout. | S13: 4.4
C14: PARTNER_UI_COMMISSIONS_002 | D14: View - Commissions page - Earned pending and paid totals are visible | E14: Functional | F14: P1 | G14: Major | H14: =IF(J14="No",I14,IF(OR(I14="FAILED",K14="FAILED"),"FAILED",IF(OR(I14="PASSED",K14="PASSED"),"PASSED",IF(OR(I14="IN_PROGRESS",K14="IN_PROGRESS"),"IN_PROGRESS",IF(OR(I14="BLOCKED",K14="BLOCKED"),"BLOCKED","NOT_STARTED"))))) -> NOT_STARTED | I14: NOT_STARTED | J14: NO | K14: NOT_STARTED | L14: §4.7 | M14: partner-platform-prd-v1.8.md | O14: Trang Le | Q14: Validate the UI flow for commissions page so that earned pending and paid totals are visible. Scope covers the commission ledger, payout, dispute, waiver, clawback, rate, and approval behavior, authenticated partner/SA role access as applicable, visible copy/state, primary CTA behavior, and PRD coverage §4.7. Out of scope: unrelated modules and deep backend calculation beyond the data needed to prove this case. | R14: 1. Navigate to Commissions with earned, pending, paid, and disputed ledger fixtures. 2. Review summary totals and ledger rows. 3. Open the target commission row if detail is required. 4. Verify deal, close, rate/version, approval, payout, clawback/waiver, and payment status fields. 5. Confirm totals reconcile to visible rows for the fixture. | S14: 4.7
C15: PARTNER_UI_COMMISSIONS_003 | D15: Trace - Commission row detail - Deal close to payment details are visible | E15: Functional | F15: P1 | G15: Major | H15: =IF(J15="No",I15,IF(OR(I15="FAILED",K15="FAILED"),"FAILED",IF(OR(I15="PASSED",K15="PASSED"),"PASSED",IF(OR(I15="IN_PROGRESS",K15="IN_PROGRESS"),"IN_PROGRESS",IF(OR(I15="BLOCKED",K15="BLOCKED"),"BLOCKED","NOT_STARTED"))))) -> NOT_STARTED | I15: NOT_STARTED | J15: NO | K15: NOT_STARTED | L15: §4.7, §5.6 | M15: partner-platform-prd-v1.8.md | O15: Trang Le | Q15: Validate the UI flow for commission row detail so that deal close to payment details are visible. Scope covers the commission ledger, payout, dispute, waiver, clawback, rate, and approval behavior, authenticated partner/SA role access as applicable, visible copy/state, primary CTA behavior, and PRD coverage §4.7, §5.6. Out of scope: unrelated modules and deep backend calculation beyond the data needed to prove this case. | R15: 1. Navigate to Commissions with earned, pending, paid, and disputed ledger fixtures. 2. Review summary totals and ledger rows. 3. Open the target commission row if detail is required. 4. Verify deal, close, rate/version, approval, payout, clawback/waiver, and payment status fields. 5. Confirm totals reconcile to visible rows for the fixture. | S15: 4.7
C16: PARTNER_UI_COMMISSIONS_004 | D16: Submit - Commission dispute - Dispute is created from one text field | E16: Functional | F16: P1 | G16: Major | H16: =IF(J16="No",I16,IF(OR(I16="FAILED",K16="FAILED"),"FAILED",IF(OR(I16="PASSED",K16="PASSED"),"PASSED",IF(OR(I16="IN_PROGRESS",K16="IN_PROGRESS"),"IN_PROGRESS",IF(OR(I16="BLOCKED",K16="BLOCKED"),"BLOCKED","NOT_STARTED"))))) -> NOT_STARTED | I16: NOT_STARTED | J16: NO | K16: NOT_STARTED | L16: §4.7 | M16: partner-platform-prd-v1.8.md | O16: Trang Le | Q16: Validate the UI flow for commission dispute so that dispute is created from one text field. Scope covers the commission ledger, payout, dispute, waiver, clawback, rate, and approval behavior, authenticated partner/SA role access as applicable, visible copy/state, primary CTA behavior, and PRD coverage §4.7. Out of scope: unrelated modules and deep backend calculation beyond the data needed to prove this case. | R16: 1. Open Commissions using a fixture eligible for the requested action. 2. Start the action: Commission dispute. 3. Enter the minimum required information or evidence/payment fields. 4. Submit and verify validation, confirmation, and new status/history entry. 5. Confirm dispute is created from one text field and sensitive details are masked or region-appropriate where applicable. | S16: 4.7
C17: PARTNER_UI_COMMISSIONS_005 | D17: Submit - Product failure waiver - Evidence can be linked and request submitted | E17: Functional | F17: P1 | G17: Critical | H17: =IF(J17="No",I17,IF(OR(I17="FAILED",K17="FAILED"),"FAILED",IF(OR(I17="PASSED",K17="PASSED"),"PASSED",IF(OR(I17="IN_PROGRESS",K17="IN_PROGRESS"),"IN_PROGRESS",IF(OR(I17="BLOCKED",K17="BLOCKED"),"BLOCKED","NOT_STARTED"))))) -> NOT_STARTED | I17: NOT_STARTED | J17: NO | K17: NOT_STARTED | L17: §4.7, §5.3 | M17: partner-platform-prd-v1.8.md | O17: Trang Le | Q17: Validate the UI flow for product failure waiver so that evidence can be linked and request submitted. Scope covers the commission ledger, payout, dispute, waiver, clawback, rate, and approval behavior, authenticated partner/SA role access as applicable, visible copy/state, primary CTA behavior, and PRD coverage §4.7, §5.3. Out of scope: unrelated modules and deep backend calculation beyond the data needed to prove this case. | R17: 1. Open Commissions using a fixture eligible for the requested action. 2. Start the action: Product failure waiver. 3. Enter the minimum required information or evidence/payment fields. 4. Submit and verify validation, confirmation, and new status/history entry. 5. Confirm evidence can be linked and request submitted and sensitive details are masked or region-appropriate where applicable. | S17: 4.7
C18: PARTNER_UI_COMMISSIONS_006 | D18: Approve - Commission payout over $10K - Two-eye approval is enforced | E18: Security | F18: P1 | G18: Critical | H18: =IF(J18="No",I18,IF(OR(I18="FAILED",K18="FAILED"),"FAILED",IF(OR(I18="PASSED",K18="PASSED"),"PASSED",IF(OR(I18="IN_PROGRESS",K18="IN_PROGRESS"),"IN_PROGRESS",IF(OR(I18="BLOCKED",K18="BLOCKED"),"BLOCKED","NOT_STARTED"))))) -> NOT_STARTED | I18: NOT_STARTED | J18: NO | K18: NOT_STARTED | L18: §5.6, §7.5 | M18: partner-platform-prd-v1.8.md | O18: Trang Le | Q18: Validate the UI flow for commission payout over $10k so that two-eye approval is enforced. Scope covers the commission ledger, payout, dispute, waiver, clawback, rate, and approval behavior, authenticated partner/SA role access as applicable, visible copy/state, primary CTA behavior, and PRD coverage §5.6, §7.5. Out of scope: unrelated modules and deep backend calculation beyond the data needed to prove this case. | R18: 1. Log in as an active channel partner user with fixture data that supports this scenario. 2. Open /commissions and confirm the expected partner/SA shell is loaded. 3. Perform the action: approve / Commission payout over $10K. 4. Verify that two-eye approval is enforced and that no unrelated page state regresses. 5. Capture any validation message, status badge, audit indicator, or navigation result required by §5.6, §7.5. | S18: 5.6
C19: PARTNER_UI_COMMISSIONS_007 | D19: Display - Clawback notification - Policy terms and product-failure waiver path are visible | E19: Functional | F19: P1 | G19: Major | H19: =IF(J19="No",I19,IF(OR(I19="FAILED",K19="FAILED"),"FAILED",IF(OR(I19="PASSED",K19="PASSED"),"PASSED",IF(OR(I19="IN_PROGRESS",K19="IN_PROGRESS"),"IN_PROGRESS",IF(OR(I19="BLOCKED",K19="BLOCKED"),"BLOCKED","NOT_STARTED"))))) -> NOT_STARTED | I19: NOT_STARTED | J19: NO | K19: NOT_STARTED | L19: §4.7, §5.3 | M19: partner-platform-prd-v1.8.md | O19: Trang Le | P19: Terms must be shown at approval/notification, not as a surprise. | Q19: Validate the UI flow for clawback notification so that policy terms and product-failure waiver path are visible. Scope covers the commission ledger, payout, dispute, waiver, clawback, rate, and approval behavior, authenticated partner/SA role access as applicable, visible copy/state, primary CTA behavior, and PRD coverage §4.7, §5.3. Out of scope: unrelated modules and deep backend calculation beyond the data needed to prove this case. | R19: 1. Open Commissions using a fixture eligible for the requested action. 2. Start the action: Clawback notification. 3. Enter the minimum required information or evidence/payment fields. 4. Submit and verify validation, confirmation, and new status/history entry. 5. Confirm policy terms and product-failure waiver path are visible and sensitive details are masked or region-appropriate where applicable. | S19: 4.7
C20: PARTNER_UI_COMMISSIONS_008 | D20: Ask - Blazey commission question - Contextual answer is returned | E20: Functional | F20: P2 | G20: Major | H20: =IF(J20="No",I20,IF(OR(I20="FAILED",K20="FAILED"),"FAILED",IF(OR(I20="PASSED",K20="PASSED"),"PASSED",IF(OR(I20="IN_PROGRESS",K20="IN_PROGRESS"),"IN_PROGRESS",IF(OR(I20="BLOCKED",K20="BLOCKED"),"BLOCKED","NOT_STARTED"))))) -> NOT_STARTED | I20: NOT_STARTED | J20: NO | K20: NOT_STARTED | L20: §4.3, §10 | M20: partner-platform-prd-v1.8.md | O20: Trang Le | P20: Blazey assistant requirement; §10 is effort estimate only. | Q20: Validate the UI flow for blazey commission question so that contextual answer is returned. Scope covers the commission ledger, payout, dispute, waiver, clawback, rate, and approval behavior, authenticated partner/SA role access as applicable, visible copy/state, primary CTA behavior, and PRD coverage §4.3, §10. Out of scope: unrelated modules and deep backend calculation beyond the data needed to prove this case. | R20: 1. Open Dashboard or Commissions page where Blazey assistant is available. 2. Ask a commission-related question using the partner fixture context. 3. Verify the answer references the correct deal/tier/rate context without exposing other partners. 4. Confirm the response includes actionable next step or explanation, not a generic fallback. 5. Check that assistant loading/error states remain usable. | S20: 46305
C21: PARTNER_UI_COMMISSIONS_009 | D21: Edit - Payout details by region - Correct payment methods are available | E21: Security | F21: P2 | G21: Major | H21: =IF(J21="No",I21,IF(OR(I21="FAILED",K21="FAILED"),"FAILED",IF(OR(I21="PASSED",K21="PASSED"),"PASSED",IF(OR(I21="IN_PROGRESS",K21="IN_PROGRESS"),"IN_PROGRESS",IF(OR(I21="BLOCKED",K21="BLOCKED"),"BLOCKED","NOT_STARTED"))))) -> NOT_STARTED | I21: NOT_STARTED | J21: NO | K21: NOT_STARTED | L21: §4.7 | M21: partner-platform-prd-v1.8.md | O21: Trang Le | P21: SWIFT, ACH, NEFT/IMPS, Vietnam bank transfer. | Q21: Validate the UI flow for payout details by region so that correct payment methods are available. Scope covers the commission ledger, payout, dispute, waiver, clawback, rate, and approval behavior, authenticated partner/SA role access as applicable, visible copy/state, primary CTA behavior, and PRD coverage §4.7. Out of scope: unrelated modules and deep backend calculation beyond the data needed to prove this case. | R21: 1. Open Commissions using a fixture eligible for the requested action. 2. Start the action: Payout details by region. 3. Enter the minimum required information or evidence/payment fields. 4. Submit and verify validation, confirmation, and new status/history entry. 5. Confirm correct payment methods are available and sensitive details are masked or region-appropriate where applicable. | S21: 4.7
B22: Commission Display | C22: PARTNER_UI_COMMISSIONS_010 | D22: Display - Reseller deal commission - Reseller rate shown, not referral rate | E22: Functional | F22: P1 | G22: Major | H22: =IF(J22="No",I22,IF(OR(I22="FAILED",K22="FAILED"),"FAILED",IF(OR(I22="PASSED",K22="PASSED"),"PASSED",IF(OR(I22="IN_PROGRESS",K22="IN_PROGRESS"),"IN_PROGRESS",IF(OR(I22="BLOCKED",K22="BLOCKED"),"BLOCKED","NOT_STARTED"))))) -> NOT_STARTED | I22: NOT_STARTED | J22: NO | K22: NOT_STARTED | L22: §3 Scenario B, §4.7, §5.3 | M22: partner-platform-prd-v1.8.md | O22: Trang Le | P22: Reseller commission rate differs from Pure Referral rate — must not show referral rate | Q22: Validate the UI flow for reseller deal commission display so that reseller rate is shown and referral rate is not applied. Scope covers the Commissions & Payouts page, deal-level commission breakdown, rate label, and PRD coverage §3 Scenario B, §4.7, §5.3. Out of scope: payout processing and ledger export. | R22: 1. Log in as reseller partner with a Won reseller deal. 2. Navigate to Commissions & Payouts. 3. Locate the commission entry for the reseller deal. 4. Verify commission rate shown is the configured reseller rate (not referral/co-sell rate). 5. Confirm rate label clearly identifies it as reseller commission. 6. Verify referral rate is not applied to this deal. | S22: 46207
B23: Invoice & Billing | C23: PARTNER_UI_COMMISSIONS_011 | D23: Invoice - Reseller deal close - Invoice generated for partner not end-client | E23: Functional | F23: P1 | G23: Critical | H23: =IF(J23="No",I23,IF(OR(I23="FAILED",K23="FAILED"),"FAILED",IF(OR(I23="PASSED",K23="PASSED"),"PASSED",IF(OR(I23="IN_PROGRESS",K23="IN_PROGRESS"),"IN_PROGRESS",IF(OR(I23="BLOCKED",K23="BLOCKED"),"BLOCKED","NOT_STARTED"))))) -> NOT_STARTED | I23: NOT_STARTED | J23: NO | K23: NOT_STARTED | L23: §3 Scenario B, §5.3 | M23: partner-platform-prd-v1.8.md | O23: Trang Le | P23: Locked decision: BlazeUp invoices the PARTNER, never the end-client, for reseller deals | Q23: Validate the UI flow for reseller deal invoice so that invoice is generated for partner not end-client. Scope covers the Commissions & Payouts page, invoice/billing section, invoice recipient display, and PRD coverage §3 Scenario B, §5.3. Out of scope: actual payment processing. | R23: 1. Log in as reseller partner with a Won reseller deal that has passed commission processing. 2. Navigate to Commissions & Payouts. 3. Locate the invoice or billing record for the reseller deal. 4. Verify invoice recipient is the partner entity, not the end-client. 5. Confirm no invoice referencing the end-client name or billing details is visible. 6. Verify invoice amount matches the partner's reseller rate on the deal value. | S23: 3-B
A24: Dashboard | B24: Home KPIs & Actions | C24: PARTNER_UI_DASHBOARD_001 | D24: View - Partner shell loads for channel partner - Dashboard is displayed | E24: Functional | F24: P1 | G24: Critical | H24: =IF(J24="No",I24,IF(OR(I24="FAILED",K24="FAILED"),"FAILED",IF(OR(I24="PASSED",K24="PASSED"),"PASSED",IF(OR(I24="IN_PROGRESS",K24="IN_PROGRESS"),"IN_PROGRESS",IF(OR(I24="BLOCKED",K24="BLOCKED"),"BLOCKED","NOT_STARTED"))))) -> NOT_STARTED | I24: NOT_STARTED | J24: NO | K24: NOT_STARTED | L24: §4.1, §4.2 | M24: partner-platform-prd-v1.8.md | O24: Trang Le | P24: Verify partner.blazeup.ai shell, navigation, and federated dashboard. | Q24: Validate the UI flow for partner shell loads for channel partner so that dashboard is displayed. Scope covers the partner dashboard KPI, action-required, pipeline snapshot, and tier-progress experience, authenticated partner/SA role access as applicable, visible copy/state, primary CTA behavior, and PRD coverage §4.1, §4.2. Out of scope: unrelated modules and deep backend calculation beyond the data needed to prove this case. | R24: 1. Log in as an active channel partner user. 2. Navigate to partner portal root `/`. 3. Confirm the Partner shell, brand, demo/banner area, help/profile controls, and navigation render. 4. Verify Dashboard is the active page and no tenant/SA-only navigation is exposed. 5. Confirm seeded dashboard content is visible without loading or authorization errors. | S24: 46057
C25: PARTNER_UI_DASHBOARD_002 | D25: Render - Dashboard KPI cards available - Actionable metrics are visible | E25: Functional | F25: P1 | G25: Major | H25: =IF(J25="No",I25,IF(OR(I25="FAILED",K25="FAILED"),"FAILED",IF(OR(I25="PASSED",K25="PASSED"),"PASSED",IF(OR(I25="IN_PROGRESS",K25="IN_PROGRESS"),"IN_PROGRESS",IF(OR(I25="BLOCKED",K25="BLOCKED"),"BLOCKED","NOT_STARTED"))))) -> NOT_STARTED | I25: NOT_STARTED | J25: NO | K25: NOT_STARTED | L25: §4.3 | M25: partner-platform-prd-v1.8.md | O25: Trang Le | P25: Pipeline, commission, active clients, and tier progress cards. | Q25: Validate the UI flow for dashboard kpi cards available so that actionable metrics are visible. Scope covers the partner dashboard KPI, action-required, pipeline snapshot, and tier-progress experience, authenticated partner/SA role access as applicable, visible copy/state, primary CTA behavior, and PRD coverage §4.3. Out of scope: unrelated modules and deep backend calculation beyond the data needed to prove this case. | R25: 1. Open the Dashboard as a partner with seeded pipeline, commission, client, and tier data. 2. Locate the KPI cards for Pipeline, Commission, Active Clients, and Tier. 3. Verify values, sublabels, icons/status styling, and clickable affordances are visible. 4. Compare displayed values to the fixture dataset used for the test. 5. Confirm loading skeletons are gone and no KPI is blank or duplicated. | S25: 4.3
C26: PARTNER_UI_DASHBOARD_003 | D26: Render - Tier progress exists on dashboard - Progress to next tier is visible | E26: Functional | F26: P1 | G26: Major | H26: =IF(J26="No",I26,IF(OR(I26="FAILED",K26="FAILED"),"FAILED",IF(OR(I26="PASSED",K26="PASSED"),"PASSED",IF(OR(I26="IN_PROGRESS",K26="IN_PROGRESS"),"IN_PROGRESS",IF(OR(I26="BLOCKED",K26="BLOCKED"),"BLOCKED","NOT_STARTED"))))) -> NOT_STARTED | I26: NOT_STARTED | J26: NO | K26: NOT_STARTED | L26: §2.1, §4.3 | M26: partner-platform-prd-v1.8.md | O26: Trang Le | Q26: Validate the UI flow for tier progress exists on dashboard so that progress to next tier is visible. Scope covers the partner dashboard KPI, action-required, pipeline snapshot, and tier-progress experience, authenticated partner/SA role access as applicable, visible copy/state, primary CTA behavior, and PRD coverage §2.1, §4.3. Out of scope: unrelated modules and deep backend calculation beyond the data needed to prove this case. | R26: 1. Open Dashboard using a partner fixture with current tier, T12M ARR, and next-tier threshold. 2. Locate the Tier Progress component. 3. Verify current tier, threshold target, progress bar, current ARR, and remaining delta are shown. 4. Change fixture or use a partner near threshold if supported and refresh. 5. Confirm progress and next-tier copy follow PRD tier rules and remain readable. | S26: 4.3
C27: PARTNER_UI_DASHBOARD_004 | D27: Render - Action Required list has pending tasks - Partner sees next actions | E27: Functional | F27: P1 | G27: Major | H27: =IF(J27="No",I27,IF(OR(I27="FAILED",K27="FAILED"),"FAILED",IF(OR(I27="PASSED",K27="PASSED"),"PASSED",IF(OR(I27="IN_PROGRESS",K27="IN_PROGRESS"),"IN_PROGRESS",IF(OR(I27="BLOCKED",K27="BLOCKED"),"BLOCKED","NOT_STARTED"))))) -> NOT_STARTED | I27: NOT_STARTED | J27: NO | K27: NOT_STARTED | L27: §4.3 | M27: partner-platform-prd-v1.8.md | O27: Trang Le | Q27: Validate the UI flow for action required list has pending tasks so that partner sees next actions. Scope covers the partner dashboard KPI, action-required, pipeline snapshot, and tier-progress experience, authenticated partner/SA role access as applicable, visible copy/state, primary CTA behavior, and PRD coverage §4.3. Out of scope: unrelated modules and deep backend calculation beyond the data needed to prove this case. | R27: 1. Open Dashboard with fixture data containing at least one renewal/action item. 2. Locate the Action Required section. 3. Verify each item shows clear context, client/deal name, urgency/status, and the correct CTA. 4. Click the relevant CTA when applicable. 5. Confirm navigation or detail state matches the item type and no stale action remains visible. | S27: 4.3
C28: PARTNER_UI_DASHBOARD_005 | D28: Calculate - Tier qualification dashboard - T12M ARR threshold and next-tier delta are visible | E28: Functional | F28: P1 | G28: Major | H28: =IF(J28="No",I28,IF(OR(I28="FAILED",K28="FAILED"),"FAILED",IF(OR(I28="PASSED",K28="PASSED"),"PASSED",IF(OR(I28="IN_PROGRESS",K28="IN_PROGRESS"),"IN_PROGRESS",IF(OR(I28="BLOCKED",K28="BLOCKED"),"BLOCKED","NOT_STARTED"))))) -> NOT_STARTED | I28: NOT_STARTED | J28: NO | K28: NOT_STARTED | L28: §2.1, §4.3 | M28: partner-platform-prd-v1.8.md | O28: Trang Le | P28: Requirement-phase case; automation mapping later. | Q28: Validate the UI flow for tier qualification dashboard so that t12m arr threshold and next-tier delta are visible. Scope covers the partner dashboard KPI, action-required, pipeline snapshot, and tier-progress experience, authenticated partner/SA role access as applicable, visible copy/state, primary CTA behavior, and PRD coverage §2.1, §4.3. Out of scope: unrelated modules and deep backend calculation beyond the data needed to prove this case. | R28: 1. Open Dashboard using a partner fixture with current tier, T12M ARR, and next-tier threshold. 2. Locate the Tier Progress component. 3. Verify current tier, threshold target, progress bar, current ARR, and remaining delta are shown. 4. Change fixture or use a partner near threshold if supported and refresh. 5. Confirm progress and next-tier copy follow PRD tier rules and remain readable. | S28: 4.3
B29: Tier Progress | C29: PARTNER_UI_DASHBOARD_006 | D29: Warn - Tier downgrade pending - 30-day notice and grace quarter are displayed | E29: Functional | F29: P1 | G29: Major | H29: =IF(J29="No",I29,IF(OR(I29="FAILED",K29="FAILED"),"FAILED",IF(OR(I29="PASSED",K29="PASSED"),"PASSED",IF(OR(I29="IN_PROGRESS",K29="IN_PROGRESS"),"IN_PROGRESS",IF(OR(I29="BLOCKED",K29="BLOCKED"),"BLOCKED","NOT_STARTED"))))) -> NOT_STARTED | I29: NOT_STARTED | J29: NO | K29: NOT_STARTED | L29: §2.1, §5.5 | M29: partner-platform-prd-v1.8.md | O29: Trang Le | P29: Covers downgrade psychology and grace-quarter rule. | Q29: Validate the UI flow for tier downgrade pending so that 30-day notice and grace quarter are displayed. Scope covers the partner dashboard KPI, action-required, pipeline snapshot, and tier-progress experience, authenticated partner/SA role access as applicable, visible copy/state, primary CTA behavior, and PRD coverage §2.1, §5.5. Out of scope: unrelated modules and deep backend calculation beyond the data needed to prove this case. | R29: 1. Log in as an active channel partner user with fixture data that supports this scenario. 2. Open / and confirm the expected partner/SA shell is loaded. 3. Perform the action: warn / Tier downgrade pending. 4. Verify that 30-day notice and grace quarter are displayed and that no unrelated page state regresses. 5. Capture any validation message, status badge, audit indicator, or navigation result required by §2.1, §5.5. | S29: 5.5
B30: Home KPIs & Actions | C30: PARTNER_UI_DASHBOARD_007 | D30: Validate - Dashboard hides vanity metrics - Only actionable/clickable values are shown | E30: Negative | F30: P3 | G30: Minor | H30: =IF(J30="No",I30,IF(OR(I30="FAILED",K30="FAILED"),"FAILED",IF(OR(I30="PASSED",K30="PASSED"),"PASSED",IF(OR(I30="IN_PROGRESS",K30="IN_PROGRESS"),"IN_PROGRESS",IF(OR(I30="BLOCKED",K30="BLOCKED"),"BLOCKED","NOT_STARTED"))))) -> NOT_STARTED | I30: NOT_STARTED | J30: NO | K30: NOT_STARTED | L30: §4.3 | M30: partner-platform-prd-v1.8.md | O30: Trang Le | Q30: Validate the UI flow for dashboard hides vanity metrics so that only actionable/clickable values are shown. Scope covers the partner dashboard KPI, action-required, pipeline snapshot, and tier-progress experience, authenticated partner/SA role access as applicable, visible copy/state, primary CTA behavior, and PRD coverage §4.3. Out of scope: unrelated modules and deep backend calculation beyond the data needed to prove this case. | R30: 1. Open Dashboard with standard partner fixture data. 2. Review all visible metrics and cards. 3. Confirm each displayed value is actionable, navigable, or decision-supporting per PRD. 4. Verify non-actionable vanity metrics are absent from the first dashboard view. 5. Confirm page hierarchy still highlights action items, tier progress, and pipeline snapshot. | S30: 4.3
B31: Blazey AI Assistant | C31: PARTNER_UI_DASHBOARD_008 | D31: Ask - Blazey deal status question on dashboard - Current deal stage and assigned rep contact are returned | E31: Functional | F31: P2 | G31: Major | H31: =IF(J31="No",I31,IF(OR(I31="FAILED",K31="FAILED"),"FAILED",IF(OR(I31="PASSED",K31="PASSED"),"PASSED",IF(OR(I31="IN_PROGRESS",K31="IN_PROGRESS"),"IN_PROGRESS",IF(OR(I31="BLOCKED",K31="BLOCKED"),"BLOCKED","NOT_STARTED"))))) -> NOT_STARTED | I31: NOT_STARTED | J31: NO | K31: NOT_STARTED | L31: §4.3, §10.10 | M31: partner-platform-prd-v1.8.md | O31: Trang Le | P31: [FIX ADDED 2026-05-27] §10.10 Blazey "deal status" tool not covered — added TC | Q31: Validate the Blazey AI assistant on the dashboard correctly handles deal status queries so that current deal stage and assigned rep contact are returned. | R31: 1. Log in as an active channel partner. 2. On the dashboard, open the Blazey AI assistant widget. 3. Type a deal status query e.g. "What is the status of my deal with Acme Corp?". 4. Verify the response includes: current deal stage, next action, and BlazeUp rep contact. 5. Confirm the response is scoped to the logged-in partner deals only. | S31: 4.3
C32: PARTNER_UI_DASHBOARD_009 | D32: Ask - Blazey tier projection question on dashboard - ARR needed and timeline to next tier are displayed | E32: Functional | F32: P2 | G32: Major | H32: =IF(J32="No",I32,IF(OR(I32="FAILED",K32="FAILED"),"FAILED",IF(OR(I32="PASSED",K32="PASSED"),"PASSED",IF(OR(I32="IN_PROGRESS",K32="IN_PROGRESS"),"IN_PROGRESS",IF(OR(I32="BLOCKED",K32="BLOCKED"),"BLOCKED","NOT_STARTED"))))) -> NOT_STARTED | I32: NOT_STARTED | J32: NO | K32: NOT_STARTED | L32: §4.3, §10.10 | M32: partner-platform-prd-v1.8.md | O32: Trang Le | P32: [FIX ADDED 2026-05-27] §10.10 Blazey "tier projection" tool not covered — added TC | Q32: Validate the Blazey AI assistant on the dashboard correctly handles tier projection queries so that ARR needed and timeline to next tier are displayed. | R32: 1. Log in as an active channel partner. 2. On the dashboard, open the Blazey AI assistant widget. 3. Type a tier projection query e.g. "How much more ARR do I need to reach Premier?". 4. Verify the response includes: current tier, T12M ARR, ARR gap to next tier, and estimated timeline. 5. Confirm figures match the tier progress bar data displayed on dashboard. | S32: 4.3
A33: My Clients | B33: Client Health & MSP | C33: PARTNER_UI_MY_CLIENTS_001 | D33: Click - Action Required renewal CTA - Renewal registration flow opens | E33: Functional | F33: P1 | G33: Major | H33: =IF(J33="No",I33,IF(OR(I33="FAILED",K33="FAILED"),"FAILED",IF(OR(I33="PASSED",K33="PASSED"),"PASSED",IF(OR(I33="IN_PROGRESS",K33="IN_PROGRESS"),"IN_PROGRESS",IF(OR(I33="BLOCKED",K33="BLOCKED"),"BLOCKED","NOT_STARTED"))))) -> NOT_STARTED | I33: NOT_STARTED | J33: NO | K33: NOT_STARTED | L33: §4.3, §4.6 | M33: partner-platform-prd-v1.8.md | O33: Trang Le | Q33: Validate the UI flow for action required renewal cta so that renewal registration flow opens. Scope covers the post-close client list, client health detail, renewal actions, and MSP consent/access behavior, authenticated partner/SA role access as applicable, visible copy/state, primary CTA behavior, and PRD coverage §4.3, §4.6. Out of scope: unrelated modules and deep backend calculation beyond the data needed to prove this case. | R33: 1. Open Dashboard as a partner with a fixture containing a client renewal action item (e.g. Meridian Ltd renewal in 18 days). 2. Locate the Action Required section and confirm the renewal item shows client name, renewal date, and a Register renewal deal CTA. 3. Click the Register renewal deal CTA on the renewal action item. 4. Verify the deal registration wizard opens in renewal/expansion context with the client name and tenant reference prefilled. 5. Confirm the registration form does not require re-entering company details already known from the existing client record. | S33: 4.6
C34: PARTNER_UI_MY_CLIENTS_002 | D34: List - Open My Clients - Post-close clients are displayed | E34: Functional | F34: P1 | G34: Major | H34: =IF(J34="No",I34,IF(OR(I34="FAILED",K34="FAILED"),"FAILED",IF(OR(I34="PASSED",K34="PASSED"),"PASSED",IF(OR(I34="IN_PROGRESS",K34="IN_PROGRESS"),"IN_PROGRESS",IF(OR(I34="BLOCKED",K34="BLOCKED"),"BLOCKED","NOT_STARTED"))))) -> NOT_STARTED | I34: NOT_STARTED | J34: NO | K34: NOT_STARTED | L34: §4.6 | M34: partner-platform-prd-v1.8.md | O34: Trang Le | Q34: Validate the UI flow for open my clients so that post-close clients are displayed. Scope covers the post-close client list, client health detail, renewal actions, and MSP consent/access behavior, authenticated partner/SA role access as applicable, visible copy/state, primary CTA behavior, and PRD coverage §4.6. Out of scope: unrelated modules and deep backend calculation beyond the data needed to prove this case. | R34: 1. Navigate to My Clients with active client fixtures including healthy, at-risk, and renewing clients. 2. Apply the action/filter/search: Open My Clients. 3. Verify client rows show name, ARR, health, renewal date, and modules. 4. Confirm post-close clients are displayed and counts/tabs match the fixture. 5. Clear filters and confirm the complete client list returns. | S34: 4.6
C35: PARTNER_UI_MY_CLIENTS_003 | D35: Open - Client health detail - ARR, renewal, usage, tickets, and CSM are visible | E35: Functional | F35: P1 | G35: Critical | H35: =IF(J35="No",I35,IF(OR(I35="FAILED",K35="FAILED"),"FAILED",IF(OR(I35="PASSED",K35="PASSED"),"PASSED",IF(OR(I35="IN_PROGRESS",K35="IN_PROGRESS"),"IN_PROGRESS",IF(OR(I35="BLOCKED",K35="BLOCKED"),"BLOCKED","NOT_STARTED"))))) -> NOT_STARTED | I35: NOT_STARTED | J35: NO | K35: NOT_STARTED | L35: §1.3, §4.6 | M35: partner-platform-prd-v1.8.md | O35: Trang Le | Q35: Validate the UI flow for client health detail so that arr, renewal, usage, tickets, and csm are visible. Scope covers the post-close client list, client health detail, renewal actions, and MSP consent/access behavior, authenticated partner/SA role access as applicable, visible copy/state, primary CTA behavior, and PRD coverage §1.3, §4.6. Out of scope: unrelated modules and deep backend calculation beyond the data needed to prove this case. | R35: 1. Open My Clients and select a seeded client such as Meridian Ltd. 2. Navigate to the Client Health Detail page. 3. Verify ARR, renewal, adoption/usage, module health, ticket summary, and CSM/owner context are visible. 4. Confirm Blazey insight or renewal recommendation appears when the fixture is at risk. 5. Verify CTA behavior does not expose restricted client data. | S35: 4.6
C36: PARTNER_UI_MY_CLIENTS_004 | D36: Register - Renewal deal from client detail - Renewal context is prefilled | E36: Functional | F36: P1 | G36: Major | H36: =IF(J36="No",I36,IF(OR(I36="FAILED",K36="FAILED"),"FAILED",IF(OR(I36="PASSED",K36="PASSED"),"PASSED",IF(OR(I36="IN_PROGRESS",K36="IN_PROGRESS"),"IN_PROGRESS",IF(OR(I36="BLOCKED",K36="BLOCKED"),"BLOCKED","NOT_STARTED"))))) -> NOT_STARTED | I36: NOT_STARTED | J36: NO | K36: NOT_STARTED | L36: §3 Scenario F, §4.6 | M36: partner-platform-prd-v1.8.md | O36: Trang Le | Q36: Validate the UI flow for renewal deal from client detail so that renewal context is prefilled. Scope covers the post-close client list, client health detail, renewal actions, and MSP consent/access behavior, authenticated partner/SA role access as applicable, visible copy/state, primary CTA behavior, and PRD coverage §3 Scenario F, §4.6. Out of scope: unrelated modules and deep backend calculation beyond the data needed to prove this case. | R36: 1. Open Dashboard or Client Health Detail with Meridian Ltd renewal fixture. 2. Click the Register renewal deal CTA. 3. Confirm the deal-registration flow opens in renewal/expansion context. 4. Verify client name, tenant/client reference, renewal date, and existing module context are prefilled. 5. Confirm the user can continue without re-entering unrelated new-logo data. | S36: 4.6
C37: PARTNER_UI_MY_CLIENTS_005 | D37: Add - MSP managed client - Provisioning form is shown | E37: Functional | F37: P1 | G37: Critical | H37: =IF(J37="No",I37,IF(OR(I37="FAILED",K37="FAILED"),"FAILED",IF(OR(I37="PASSED",K37="PASSED"),"PASSED",IF(OR(I37="IN_PROGRESS",K37="IN_PROGRESS"),"IN_PROGRESS",IF(OR(I37="BLOCKED",K37="BLOCKED"),"BLOCKED","NOT_STARTED"))))) -> NOT_STARTED | I37: NOT_STARTED | J37: NO | K37: NOT_STARTED | L37: §3 Scenario G, §7.3 | M37: partner-platform-prd-v1.8.md | O37: Trang Le | Q37: Validate the UI flow for msp managed client so that provisioning form is shown. Scope covers the post-close client list, client health detail, renewal actions, and MSP consent/access behavior, authenticated partner/SA role access as applicable, visible copy/state, primary CTA behavior, and PRD coverage §3 Scenario G, §7.3. Out of scope: unrelated modules and deep backend calculation beyond the data needed to prove this case. | R37: 1. Log in as an MSP partner with managed-client fixtures. 2. Open My Clients or client provisioning flow for: MSP managed client. 3. Verify ticket-content consent is off by default unless explicitly granted. 4. Confirm counts/severity are visible but body/content is hidden without consent. 5. Complete the action and verify provisioning form is shown with audit-friendly consent state. | S37: 3-G
C38: PARTNER_UI_MY_CLIENTS_006 | D38: Toggle - MSP ticket consent default - Consent is off by default | E38: Security | F38: P1 | G38: Major | H38: =IF(J38="No",I38,IF(OR(I38="FAILED",K38="FAILED"),"FAILED",IF(OR(I38="PASSED",K38="PASSED"),"PASSED",IF(OR(I38="IN_PROGRESS",K38="IN_PROGRESS"),"IN_PROGRESS",IF(OR(I38="BLOCKED",K38="BLOCKED"),"BLOCKED","NOT_STARTED"))))) -> NOT_STARTED | I38: NOT_STARTED | J38: NO | K38: NOT_STARTED | L38: §3 Scenario G, §7.3, §9.2 | M38: partner-platform-prd-v1.8.md | O38: Trang Le | Q38: Validate the UI flow for msp ticket consent default so that consent is off by default. Scope covers the post-close client list, client health detail, renewal actions, and MSP consent/access behavior, authenticated partner/SA role access as applicable, visible copy/state, primary CTA behavior, and PRD coverage §3 Scenario G, §7.3, §9.2. Out of scope: unrelated modules and deep backend calculation beyond the data needed to prove this case. | R38: 1. Log in as an MSP partner with managed-client fixtures. 2. Open My Clients or client provisioning flow for: MSP ticket consent default. 3. Verify ticket-content consent is off by default unless explicitly granted. 4. Confirm counts/severity are visible but body/content is hidden without consent. 5. Complete the action and verify consent is off by default with audit-friendly consent state. | S38: 3-G
C39: PARTNER_UI_MY_CLIENTS_007 | D39: Filter - Renewal This Quarter - Only qualifying clients are shown | E39: Functional | F39: P2 | G39: Major | H39: =IF(J39="No",I39,IF(OR(I39="FAILED",K39="FAILED"),"FAILED",IF(OR(I39="PASSED",K39="PASSED"),"PASSED",IF(OR(I39="IN_PROGRESS",K39="IN_PROGRESS"),"IN_PROGRESS",IF(OR(I39="BLOCKED",K39="BLOCKED"),"BLOCKED","NOT_STARTED"))))) -> NOT_STARTED | I39: NOT_STARTED | J39: NO | K39: NOT_STARTED | L39: §4.6 | M39: partner-platform-prd-v1.8.md | O39: Trang Le | Q39: Validate the UI flow for renewal this quarter so that only qualifying clients are shown. Scope covers the post-close client list, client health detail, renewal actions, and MSP consent/access behavior, authenticated partner/SA role access as applicable, visible copy/state, primary CTA behavior, and PRD coverage §4.6. Out of scope: unrelated modules and deep backend calculation beyond the data needed to prove this case. | R39: 1. Navigate to My Clients with active client fixtures including healthy, at-risk, and renewing clients. 2. Apply the action/filter/search: Renewal This Quarter. 3. Verify client rows show name, ARR, health, renewal date, and modules. 4. Confirm only qualifying clients are shown and counts/tabs match the fixture. 5. Clear filters and confirm the complete client list returns. | S39: 4.6
C40: PARTNER_UI_MY_CLIENTS_008 | D40: Filter - Health At Risk - At-risk clients are shown | E40: Functional | F40: P2 | G40: Major | H40: =IF(J40="No",I40,IF(OR(I40="FAILED",K40="FAILED"),"FAILED",IF(OR(I40="PASSED",K40="PASSED"),"PASSED",IF(OR(I40="IN_PROGRESS",K40="IN_PROGRESS"),"IN_PROGRESS",IF(OR(I40="BLOCKED",K40="BLOCKED"),"BLOCKED","NOT_STARTED"))))) -> NOT_STARTED | I40: NOT_STARTED | J40: NO | K40: NOT_STARTED | L40: §1.3, §4.6 | M40: partner-platform-prd-v1.8.md | O40: Trang Le | Q40: Validate the UI flow for health at risk so that at-risk clients are shown. Scope covers the post-close client list, client health detail, renewal actions, and MSP consent/access behavior, authenticated partner/SA role access as applicable, visible copy/state, primary CTA behavior, and PRD coverage §1.3, §4.6. Out of scope: unrelated modules and deep backend calculation beyond the data needed to prove this case. | R40: 1. Navigate to My Clients with active client fixtures including healthy, at-risk, and renewing clients. 2. Apply the action/filter/search: Health At Risk. 3. Verify client rows show name, ARR, health, renewal date, and modules. 4. Confirm at-risk clients are shown and counts/tabs match the fixture. 5. Clear filters and confirm the complete client list returns. | S40: 4.6
C41: PARTNER_UI_MY_CLIENTS_009 | D41: Search - Find client by name - Matching clients are displayed | E41: Functional | F41: P2 | G41: Major | H41: =IF(J41="No",I41,IF(OR(I41="FAILED",K41="FAILED"),"FAILED",IF(OR(I41="PASSED",K41="PASSED"),"PASSED",IF(OR(I41="IN_PROGRESS",K41="IN_PROGRESS"),"IN_PROGRESS",IF(OR(I41="BLOCKED",K41="BLOCKED"),"BLOCKED","NOT_STARTED"))))) -> NOT_STARTED | I41: NOT_STARTED | J41: NO | K41: NOT_STARTED | L41: §4.6 | M41: partner-platform-prd-v1.8.md | O41: Trang Le | Q41: Validate the UI flow for find client by name so that matching clients are displayed. Scope covers the post-close client list, client health detail, renewal actions, and MSP consent/access behavior, authenticated partner/SA role access as applicable, visible copy/state, primary CTA behavior, and PRD coverage §4.6. Out of scope: unrelated modules and deep backend calculation beyond the data needed to prove this case. | R41: 1. Navigate to My Clients with active client fixtures including healthy, at-risk, and renewing clients. 2. Apply the action/filter/search: Find client by name. 3. Verify client rows show name, ARR, health, renewal date, and modules. 4. Confirm matching clients are displayed and counts/tabs match the fixture. 5. Clear filters and confirm the complete client list returns. | S41: 4.6
C42: PARTNER_UI_MY_CLIENTS_010 | D42: Display - Blazey client insight - Adoption recommendation appears | E42: Functional | F42: P2 | G42: Major | H42: =IF(J42="No",I42,IF(OR(I42="FAILED",K42="FAILED"),"FAILED",IF(OR(I42="PASSED",K42="PASSED"),"PASSED",IF(OR(I42="IN_PROGRESS",K42="IN_PROGRESS"),"IN_PROGRESS",IF(OR(I42="BLOCKED",K42="BLOCKED"),"BLOCKED","NOT_STARTED"))))) -> NOT_STARTED | I42: NOT_STARTED | J42: NO | K42: NOT_STARTED | L42: §1.3, §4.6 | M42: partner-platform-prd-v1.8.md | O42: Trang Le | Q42: Validate the UI flow for blazey client insight so that adoption recommendation appears. Scope covers the post-close client list, client health detail, renewal actions, and MSP consent/access behavior, authenticated partner/SA role access as applicable, visible copy/state, primary CTA behavior, and PRD coverage §1.3, §4.6. Out of scope: unrelated modules and deep backend calculation beyond the data needed to prove this case. | R42: 1. Open My Clients and select a seeded client such as Meridian Ltd. 2. Navigate to the Client Health Detail page. 3. Verify ARR, renewal, adoption/usage, module health, ticket summary, and CSM/owner context are visible. 4. Confirm Blazey insight or renewal recommendation appears when the fixture is at risk. 5. Verify CTA behavior does not expose restricted client data. | S42: 4.6
B43: Expansion Deal | C43: PARTNER_UI_MY_CLIENTS_011 | D43: Register - Expansion deal from My Clients - Existing client pre-filled in wizard | E43: Functional | F43: P1 | G43: Critical | H43: =IF(J43="No",I43,IF(OR(I43="FAILED",K43="FAILED"),"FAILED",IF(OR(I43="PASSED",K43="PASSED"),"PASSED",IF(OR(I43="IN_PROGRESS",K43="IN_PROGRESS"),"IN_PROGRESS",IF(OR(I43="BLOCKED",K43="BLOCKED"),"BLOCKED","NOT_STARTED"))))) -> NOT_STARTED | I43: NOT_STARTED | J43: NO | K43: NOT_STARTED | L43: §3 Scenario F, §4.6, §4.4 | M43: partner-platform-prd-v1.8.md | O43: Trang Le | P43: Expansion starts from My Clients — existing client context must pre-fill wizard, not blank form | Q43: Validate the UI flow for expansion deal registration from My Clients so that existing client details are pre-filled in the deal wizard. Scope covers the My Clients list, client detail page, expansion deal CTA, deal registration wizard pre-fill behavior, and PRD coverage §3 Scenario F, §4.6, §4.4. Out of scope: commission calculation and tenant provisioning. | R43: 1. Log in as an active partner with at least one existing closed client in My Clients. 2. Navigate to My Clients and open the client detail page. 3. Locate and click the "Register Expansion Deal" CTA. 4. Verify the deal registration wizard opens with company name, domain, and tenant reference pre-filled from the existing client record. 5. Confirm the wizard does not require re-entering client details already on file. 6. Submit the expansion deal and verify it appears in My Pipeline. | S43: 3-F
C44: PARTNER_UI_MY_CLIENTS_012 | D44: Display - Blazey client insight - Adoption recommendation appears | E44: Functional | F44: P1 | G44: Critical | H44: =IF(J44="No",I44,IF(OR(I44="FAILED",K44="FAILED"),"FAILED",IF(OR(I44="PASSED",K44="PASSED"),"PASSED",IF(OR(I44="IN_PROGRESS",K44="IN_PROGRESS"),"IN_PROGRESS",IF(OR(I44="BLOCKED",K44="BLOCKED"),"BLOCKED","NOT_STARTED"))))) -> NOT_STARTED | I44: NOT_STARTED | J44: NO | K44: NOT_STARTED | L44: §3 Scenario F, §7.4 | M44: partner-platform-prd-v1.8.md | O44: Trang Le | P44: Key invariant: expansion must reuse existing tenant_id — new tenant must NOT be provisioned | Q44: Validate the UI flow for expansion deal submission so that existing tenant_id is reused and no new tenant is created. Scope covers the deal registration wizard review step, submission confirmation, deal detail page tenant reference, and PRD coverage §3 Scenario F, §7.4. Out of scope: commission calculation and billing. | R44: 1. Submit an expansion deal for an existing client via the registration wizard (from TC_011 or equivalent fixture). 2. Open the submitted deal in My Pipeline and navigate to deal detail. 3. Verify the deal detail shows the existing client's tenant_id (not a new one). 4. Confirm no new tenant provisioning task or pending-tenant state is shown. 5. Verify the expansion deal is linked to the same client record in My Clients. | S44: 3-F
C45: PARTNER_UI_MY_CLIENTS_013 | D45: Display - Blazey client insight - Adoption recommendation appears | E45: Functional | F45: P1 | G45: Major | H45: =IF(J45="No",I45,IF(OR(I45="FAILED",K45="FAILED"),"FAILED",IF(OR(I45="PASSED",K45="PASSED"),"PASSED",IF(OR(I45="IN_PROGRESS",K45="IN_PROGRESS"),"IN_PROGRESS",IF(OR(I45="BLOCKED",K45="BLOCKED"),"BLOCKED","NOT_STARTED"))))) -> NOT_STARTED | I45: NOT_STARTED | J45: NO | K45: NOT_STARTED | L45: §3 Scenario F, §4.6, §7.4 | M45: partner-platform-prd-v1.8.md | O45: Trang Le | P45: After expansion close, ARR on client card must reflect the expanded value | Q45: Validate the UI flow for post-close expansion deal so that ARR is updated in the My Clients client detail card. Scope covers the My Clients list, client detail page, ARR metric display, and PRD coverage §3 Scenario F, §4.6, §7.4. Out of scope: commission payout and new tenant provisioning. | R45: 1. Log in as a partner with a Won expansion deal fixture for an existing client. 2. Navigate to My Clients and open the client detail page for that client. 3. Verify the ARR displayed on the client detail card reflects the updated value after the expansion close. 4. Confirm the ARR increase matches the expansion deal value. 5. Verify no duplicate client record was created — the same client entry shows the expanded ARR. | S45: 3-F
A46: My Pipeline | B46: Deal Registration | C46: PARTNER_UI_MY_PIPELINE_001 | D46: Register - Enter valid company details - Wizard advances to contact step | E46: Functional | F46: P1 | G46: Critical | H46: =IF(J46="No",I46,IF(OR(I46="FAILED",K46="FAILED"),"FAILED",IF(OR(I46="PASSED",K46="PASSED"),"PASSED",IF(OR(I46="IN_PROGRESS",K46="IN_PROGRESS"),"IN_PROGRESS",IF(OR(I46="BLOCKED",K46="BLOCKED"),"BLOCKED","NOT_STARTED"))))) -> NOT_STARTED | I46: NOT_STARTED | J46: NO | K46: NOT_STARTED | L46: §4.4 | M46: partner-platform-prd-v1.8.md | O46: Trang Le | Q46: Validate the UI flow for enter valid company details so that wizard advances to contact step. Scope covers the deal registration wizard, validation, billing/deal-type capture, confirmation, and submission flow, authenticated partner/SA role access as applicable, visible copy/state, primary CTA behavior, and PRD coverage §4.4. Out of scope: unrelated modules and deep backend calculation beyond the data needed to prove this case. | R46: 1. Open `/deals/register` as a partner allowed to register deals. 2. Enter valid company name, domain, region, and basic prospect details. 3. Click Next or continue to the contact step. 4. Verify the wizard advances and preserves the company data. 5. Confirm no validation error appears for valid inputs. | S46: 4.4
C47: PARTNER_UI_MY_PIPELINE_002 | D47: Validate - Leave company name blank - Required field error is shown | E47: Negative | F47: P1 | G47: Major | H47: =IF(J47="No",I47,IF(OR(I47="FAILED",K47="FAILED"),"FAILED",IF(OR(I47="PASSED",K47="PASSED"),"PASSED",IF(OR(I47="IN_PROGRESS",K47="IN_PROGRESS"),"IN_PROGRESS",IF(OR(I47="BLOCKED",K47="BLOCKED"),"BLOCKED","NOT_STARTED"))))) -> NOT_STARTED | I47: NOT_STARTED | J47: NO | K47: NOT_STARTED | L47: §4.4 | M47: partner-platform-prd-v1.8.md | O47: Trang Le | Q47: Validate the UI flow for leave company name blank so that required field error is shown. Scope covers the deal registration wizard, validation, billing/deal-type capture, confirmation, and submission flow, authenticated partner/SA role access as applicable, visible copy/state, primary CTA behavior, and PRD coverage §4.4. Out of scope: unrelated modules and deep backend calculation beyond the data needed to prove this case. | R47: 1. Open `/deals/register` and navigate to the step containing the target field in this negative case. 2. Fill all other required fields with valid fixture data. 3. Enter or leave the invalid value described by the test case: Leave company name blank. 4. Attempt to continue or submit the step. 5. Verify required field error is shown, focus/field highlighting is clear, and no deal is created. | S47: 4.4
C48: PARTNER_UI_MY_PIPELINE_003 | D48: Validate - Enter invalid domain - Domain format error is shown | E48: Negative | F48: P1 | G48: Major | H48: =IF(J48="No",I48,IF(OR(I48="FAILED",K48="FAILED"),"FAILED",IF(OR(I48="PASSED",K48="PASSED"),"PASSED",IF(OR(I48="IN_PROGRESS",K48="IN_PROGRESS"),"IN_PROGRESS",IF(OR(I48="BLOCKED",K48="BLOCKED"),"BLOCKED","NOT_STARTED"))))) -> NOT_STARTED | I48: NOT_STARTED | J48: NO | K48: NOT_STARTED | L48: §4.4 | M48: partner-platform-prd-v1.8.md | O48: Trang Le | Q48: Validate the UI flow for enter invalid domain so that domain format error is shown. Scope covers the deal registration wizard, validation, billing/deal-type capture, confirmation, and submission flow, authenticated partner/SA role access as applicable, visible copy/state, primary CTA behavior, and PRD coverage §4.4. Out of scope: unrelated modules and deep backend calculation beyond the data needed to prove this case. | R48: 1. Open `/deals/register` and navigate to the step containing the target field in this negative case. 2. Fill all other required fields with valid fixture data. 3. Enter or leave the invalid value described by the test case: Enter invalid domain. 4. Attempt to continue or submit the step. 5. Verify domain format error is shown, focus/field highlighting is clear, and no deal is created. | S48: 4.4
C49: PARTNER_UI_MY_PIPELINE_004 | D49: Warn - Domain already exists - Inline active-account warning is shown | E49: Functional | F49: P1 | G49: Critical | H49: =IF(J49="No",I49,IF(OR(I49="FAILED",K49="FAILED"),"FAILED",IF(OR(I49="PASSED",K49="PASSED"),"PASSED",IF(OR(I49="IN_PROGRESS",K49="IN_PROGRESS"),"IN_PROGRESS",IF(OR(I49="BLOCKED",K49="BLOCKED"),"BLOCKED","NOT_STARTED"))))) -> NOT_STARTED | I49: NOT_STARTED | J49: NO | K49: NOT_STARTED | L49: §3 Scenario D, §4.4 | M49: partner-platform-prd-v1.8.md | O49: Trang Le | Q49: Validate the UI flow for domain already exists so that inline active-account warning is shown. Scope covers the deal registration wizard, validation, billing/deal-type capture, confirmation, and submission flow, authenticated partner/SA role access as applicable, visible copy/state, primary CTA behavior, and PRD coverage §3 Scenario D, §4.4. Out of scope: unrelated modules and deep backend calculation beyond the data needed to prove this case. | R49: 1. Open deal registration with a domain already owned or registered in the fixture set. 2. Enter the existing domain and trigger validation/enrichment. 3. Confirm the inline warning explains active account/conflict status. 4. Submit the registration only if the scenario requires submission. 5. Verify the deal status moves to conflict queue or the conflict decision UI captures written reasoning as expected. | S49: 4.4
C50: PARTNER_UI_MY_PIPELINE_005 | D50: Submit - Existing domain with warning - Deal enters conflict queue | E50: Functional | F50: P1 | G50: Critical | H50: =IF(J50="No",I50,IF(OR(I50="FAILED",K50="FAILED"),"FAILED",IF(OR(I50="PASSED",K50="PASSED"),"PASSED",IF(OR(I50="IN_PROGRESS",K50="IN_PROGRESS"),"IN_PROGRESS",IF(OR(I50="BLOCKED",K50="BLOCKED"),"BLOCKED","NOT_STARTED"))))) -> NOT_STARTED | I50: NOT_STARTED | J50: NO | K50: NOT_STARTED | L50: §3 Scenario D, §5.2 | M50: partner-platform-prd-v1.8.md | O50: Trang Le | Q50: Validate the UI flow for existing domain with warning so that deal enters conflict queue. Scope covers the deal registration wizard, validation, billing/deal-type capture, confirmation, and submission flow, authenticated partner/SA role access as applicable, visible copy/state, primary CTA behavior, and PRD coverage §3 Scenario D, §5.2. Out of scope: unrelated modules and deep backend calculation beyond the data needed to prove this case. | R50: 1. Open deal registration with a domain already owned or registered in the fixture set. 2. Enter the existing domain and trigger validation/enrichment. 3. Confirm the inline warning explains active account/conflict status. 4. Submit the registration only if the scenario requires submission. 5. Verify the deal status moves to conflict queue or the conflict decision UI captures written reasoning as expected. | S50: 3-D
C51: PARTNER_UI_MY_PIPELINE_006 | D51: Validate - Enter contact without email - Required field error is shown | E51: Negative | F51: P1 | G51: Major | H51: =IF(J51="No",I51,IF(OR(I51="FAILED",K51="FAILED"),"FAILED",IF(OR(I51="PASSED",K51="PASSED"),"PASSED",IF(OR(I51="IN_PROGRESS",K51="IN_PROGRESS"),"IN_PROGRESS",IF(OR(I51="BLOCKED",K51="BLOCKED"),"BLOCKED","NOT_STARTED"))))) -> NOT_STARTED | I51: NOT_STARTED | J51: NO | K51: NOT_STARTED | L51: §4.4 | M51: partner-platform-prd-v1.8.md | O51: Trang Le | Q51: Validate the UI flow for enter contact without email so that required field error is shown. Scope covers the deal registration wizard, validation, billing/deal-type capture, confirmation, and submission flow, authenticated partner/SA role access as applicable, visible copy/state, primary CTA behavior, and PRD coverage §4.4. Out of scope: unrelated modules and deep backend calculation beyond the data needed to prove this case. | R51: 1. Open `/deals/register` and navigate to the step containing the target field in this negative case. 2. Fill all other required fields with valid fixture data. 3. Enter or leave the invalid value described by the test case: Enter contact without email. 4. Attempt to continue or submit the step. 5. Verify required field error is shown, focus/field highlighting is clear, and no deal is created. | S51: 4.4
C52: PARTNER_UI_MY_PIPELINE_007 | D52: Validate - Enter malformed email - Email error is shown | E52: Negative | F52: P1 | G52: Major | H52: =IF(J52="No",I52,IF(OR(I52="FAILED",K52="FAILED"),"FAILED",IF(OR(I52="PASSED",K52="PASSED"),"PASSED",IF(OR(I52="IN_PROGRESS",K52="IN_PROGRESS"),"IN_PROGRESS",IF(OR(I52="BLOCKED",K52="BLOCKED"),"BLOCKED","NOT_STARTED"))))) -> NOT_STARTED | I52: NOT_STARTED | J52: NO | K52: NOT_STARTED | L52: §4.4 | M52: partner-platform-prd-v1.8.md | O52: Trang Le | Q52: Validate the UI flow for enter malformed email so that email error is shown. Scope covers the deal registration wizard, validation, billing/deal-type capture, confirmation, and submission flow, authenticated partner/SA role access as applicable, visible copy/state, primary CTA behavior, and PRD coverage §4.4. Out of scope: unrelated modules and deep backend calculation beyond the data needed to prove this case. | R52: 1. Open `/deals/register` and navigate to the step containing the target field in this negative case. 2. Fill all other required fields with valid fixture data. 3. Enter or leave the invalid value described by the test case: Enter malformed email. 4. Attempt to continue or submit the step. 5. Verify email error is shown, focus/field highlighting is clear, and no deal is created. | S52: 4.4
C53: PARTNER_UI_MY_PIPELINE_008 | D53: Select - Choose referral deal type - Direct billing model is implied | E53: Functional | F53: P1 | G53: Major | H53: =IF(J53="No",I53,IF(OR(I53="FAILED",K53="FAILED"),"FAILED",IF(OR(I53="PASSED",K53="PASSED"),"PASSED",IF(OR(I53="IN_PROGRESS",K53="IN_PROGRESS"),"IN_PROGRESS",IF(OR(I53="BLOCKED",K53="BLOCKED"),"BLOCKED","NOT_STARTED"))))) -> NOT_STARTED | I53: NOT_STARTED | J53: NO | K53: NOT_STARTED | L53: §2.2, §2.3, §4.4 | M53: partner-platform-prd-v1.8.md | O53: Trang Le | Q53: Validate the UI flow for choose referral deal type so that direct billing model is implied. Scope covers the deal registration wizard, validation, billing/deal-type capture, confirmation, and submission flow, authenticated partner/SA role access as applicable, visible copy/state, primary CTA behavior, and PRD coverage §2.2, §2.3, §4.4. Out of scope: unrelated modules and deep backend calculation beyond the data needed to prove this case. | R53: 1. Open the deal registration wizard and complete required prior fields. 2. Perform the selection described by the case: Choose referral deal type. 3. Continue to the next step and then to the review page. 4. Verify direct billing model is implied and selected values remain persisted after navigation. 5. Confirm incompatible options or billing models are hidden/disabled according to the selected deal type. | S53: 4.4
C54: PARTNER_UI_MY_PIPELINE_009 | D54: Select - Choose reseller deal type - Reseller billing path is available | E54: Functional | F54: P1 | G54: Major | H54: =IF(J54="No",I54,IF(OR(I54="FAILED",K54="FAILED"),"FAILED",IF(OR(I54="PASSED",K54="PASSED"),"PASSED",IF(OR(I54="IN_PROGRESS",K54="IN_PROGRESS"),"IN_PROGRESS",IF(OR(I54="BLOCKED",K54="BLOCKED"),"BLOCKED","NOT_STARTED"))))) -> NOT_STARTED | I54: NOT_STARTED | J54: NO | K54: NOT_STARTED | L54: §2.2, §3 Scenario B, §4.4 | M54: partner-platform-prd-v1.8.md | O54: Trang Le | Q54: Validate the UI flow for choose reseller deal type so that reseller billing path is available. Scope covers the deal registration wizard, validation, billing/deal-type capture, confirmation, and submission flow, authenticated partner/SA role access as applicable, visible copy/state, primary CTA behavior, and PRD coverage §2.2, §3 Scenario B, §4.4. Out of scope: unrelated modules and deep backend calculation beyond the data needed to prove this case. | R54: 1. Open the deal registration wizard and complete required prior fields. 2. Perform the selection described by the case: Choose reseller deal type. 3. Continue to the next step and then to the review page. 4. Verify reseller billing path is available and selected values remain persisted after navigation. 5. Confirm incompatible options or billing models are hidden/disabled according to the selected deal type. | S54: 4.4
C55: PARTNER_UI_MY_PIPELINE_010 | D55: Select - Choose co-sell deal type - Co-sell option is captured | E55: Functional | F55: P1 | G55: Major | H55: =IF(J55="No",I55,IF(OR(I55="FAILED",K55="FAILED"),"FAILED",IF(OR(I55="PASSED",K55="PASSED"),"PASSED",IF(OR(I55="IN_PROGRESS",K55="IN_PROGRESS"),"IN_PROGRESS",IF(OR(I55="BLOCKED",K55="BLOCKED"),"BLOCKED","NOT_STARTED"))))) -> NOT_STARTED | I55: NOT_STARTED | J55: NO | K55: NOT_STARTED | L55: §2.3, §3 Scenario C, §4.4 | M55: partner-platform-prd-v1.8.md | O55: Trang Le | Q55: Validate the UI flow for choose co-sell deal type so that co-sell option is captured. Scope covers the deal registration wizard, validation, billing/deal-type capture, confirmation, and submission flow, authenticated partner/SA role access as applicable, visible copy/state, primary CTA behavior, and PRD coverage §2.3, §3 Scenario C, §4.4. Out of scope: unrelated modules and deep backend calculation beyond the data needed to prove this case. | R55: 1. Open the deal registration wizard and complete required prior fields. 2. Perform the selection described by the case: Choose co-sell deal type. 3. Continue to the next step and then to the review page. 4. Verify co-sell option is captured and selected values remain persisted after navigation. 5. Confirm incompatible options or billing models are hidden/disabled according to the selected deal type. | S55: 4.4
C56: PARTNER_UI_MY_PIPELINE_011 | D56: Confirm - Review registration summary - All entered data is displayed | E56: Functional | F56: P1 | G56: Major | H56: =IF(J56="No",I56,IF(OR(I56="FAILED",K56="FAILED"),"FAILED",IF(OR(I56="PASSED",K56="PASSED"),"PASSED",IF(OR(I56="IN_PROGRESS",K56="IN_PROGRESS"),"IN_PROGRESS",IF(OR(I56="BLOCKED",K56="BLOCKED"),"BLOCKED","NOT_STARTED"))))) -> NOT_STARTED | I56: NOT_STARTED | J56: NO | K56: NOT_STARTED | L56: §4.4 | M56: partner-platform-prd-v1.8.md | O56: Trang Le | Q56: Validate the UI flow for review registration summary so that all entered data is displayed. Scope covers the deal registration wizard, validation, billing/deal-type capture, confirmation, and submission flow, authenticated partner/SA role access as applicable, visible copy/state, primary CTA behavior, and PRD coverage §4.4. Out of scope: unrelated modules and deep backend calculation beyond the data needed to prove this case. | R56: 1. Start a new deal registration in desktop viewport with valid referral/reseller/co-sell fixture data. 2. Complete company, contact, modules, deal type, ACV, and expected close date steps. 3. Open the review/confirmation step and compare all fields to the inputs. 4. Submit the registration. 5. Verify all entered data is displayed, response timing if applicable, and the new deal appears in pipeline with the correct initial status. | S56: 4.4
C57: PARTNER_UI_MY_PIPELINE_012 | D57: Submit - Valid deal registration - Success response appears within 2 seconds | E57: Performance | F57: P1 | G57: Critical | H57: =IF(J57="No",I57,IF(OR(I57="FAILED",K57="FAILED"),"FAILED",IF(OR(I57="PASSED",K57="PASSED"),"PASSED",IF(OR(I57="IN_PROGRESS",K57="IN_PROGRESS"),"IN_PROGRESS",IF(OR(I57="BLOCKED",K57="BLOCKED"),"BLOCKED","NOT_STARTED"))))) -> NOT_STARTED | I57: NOT_STARTED | J57: NO | K57: NOT_STARTED | L57: §4.4 | M57: partner-platform-prd-v1.8.md | O57: Trang Le | P57: Measure perceived response time. | Q57: Validate the UI flow for valid deal registration so that success response appears within 2 seconds. Scope covers the deal registration wizard, validation, billing/deal-type capture, confirmation, and submission flow, authenticated partner/SA role access as applicable, visible copy/state, primary CTA behavior, and PRD coverage §4.4. Out of scope: unrelated modules and deep backend calculation beyond the data needed to prove this case. | R57: 1. Start a new deal registration in desktop viewport with valid referral/reseller/co-sell fixture data. 2. Complete company, contact, modules, deal type, ACV, and expected close date steps. 3. Open the review/confirmation step and compare all fields to the inputs. 4. Submit the registration. 5. Verify success response appears within 2 seconds, response timing if applicable, and the new deal appears in pipeline with the correct initial status. | S57: 4.4
C58: PARTNER_UI_MY_PIPELINE_013 | D58: Complete - Registration on mobile viewport - Flow can finish under 90 seconds | E58: Performance | F58: P1 | G58: Critical | H58: =IF(J58="No",I58,IF(OR(I58="FAILED",K58="FAILED"),"FAILED",IF(OR(I58="PASSED",K58="PASSED"),"PASSED",IF(OR(I58="IN_PROGRESS",K58="IN_PROGRESS"),"IN_PROGRESS",IF(OR(I58="BLOCKED",K58="BLOCKED"),"BLOCKED","NOT_STARTED"))))) -> NOT_STARTED | I58: NOT_STARTED | J58: NO | K58: NOT_STARTED | L58: §4.4 | M58: partner-platform-prd-v1.8.md | O58: Trang Le | P58: Mobile standing-in-car-park target. | Q58: Validate the UI flow for registration on mobile viewport so that flow can finish under 90 seconds. Scope covers the deal registration wizard, validation, billing/deal-type capture, confirmation, and submission flow, authenticated partner/SA role access as applicable, visible copy/state, primary CTA behavior, and PRD coverage §4.4. Out of scope: unrelated modules and deep backend calculation beyond the data needed to prove this case. | R58: 1. Start a new deal registration in mobile viewport with valid referral/reseller/co-sell fixture data. 2. Complete company, contact, modules, deal type, ACV, and expected close date steps. 3. Open the review/confirmation step and compare all fields to the inputs. 4. Submit the registration. 5. Verify flow can finish under 90 seconds, response timing if applicable, and the new deal appears in pipeline with the correct initial status. | S58: 4.4
B59: Pipeline Management | C59: PARTNER_UI_MY_PIPELINE_014 | D59: List - Open My Pipeline - All deal stages and counts are visible | E59: Functional | F59: P1 | G59: Major | H59: =IF(J59="No",I59,IF(OR(I59="FAILED",K59="FAILED"),"FAILED",IF(OR(I59="PASSED",K59="PASSED"),"PASSED",IF(OR(I59="IN_PROGRESS",K59="IN_PROGRESS"),"IN_PROGRESS",IF(OR(I59="BLOCKED",K59="BLOCKED"),"BLOCKED","NOT_STARTED"))))) -> NOT_STARTED | I59: NOT_STARTED | J59: NO | K59: NOT_STARTED | L59: §4.5 | M59: partner-platform-prd-v1.8.md | O59: Trang Le | Q59: Validate the UI flow for open my pipeline so that all deal stages and counts are visible. Scope covers the partner pipeline list, deal detail, collaboration, protection, and co-sell workflow, authenticated partner/SA role access as applicable, visible copy/state, primary CTA behavior, and PRD coverage §4.5. Out of scope: unrelated modules and deep backend calculation beyond the data needed to prove this case. | R59: 1. Navigate to My Pipeline with fixture deals across Registered, Approved, In Progress, Won, and Lost stages. 2. Verify stage tabs/counts and total open deal summary are visible. 3. Confirm each row/card shows company, ACV, type, stage, age, and close date. 4. Compare counts to fixture data after switching tabs. 5. Confirm Register Deal CTA remains available. | S59: 4.5
C60: PARTNER_UI_MY_PIPELINE_015 | D60: Open - Deal detail timeline - Registration and approval history is shown | E60: Functional | F60: P1 | G60: Major | H60: =IF(J60="No",I60,IF(OR(I60="FAILED",K60="FAILED"),"FAILED",IF(OR(I60="PASSED",K60="PASSED"),"PASSED",IF(OR(I60="IN_PROGRESS",K60="IN_PROGRESS"),"IN_PROGRESS",IF(OR(I60="BLOCKED",K60="BLOCKED"),"BLOCKED","NOT_STARTED"))))) -> NOT_STARTED | I60: NOT_STARTED | J60: NO | K60: NOT_STARTED | L60: §4.5, §9.4 | M60: partner-platform-prd-v1.8.md | O60: Trang Le | Q60: Validate the UI flow for deal detail timeline so that registration and approval history is shown. Scope covers the partner pipeline list, deal detail, collaboration, protection, and co-sell workflow, authenticated partner/SA role access as applicable, visible copy/state, primary CTA behavior, and PRD coverage §4.5, §9.4. Out of scope: unrelated modules and deep backend calculation beyond the data needed to prove this case. | R60: 1. Open My Pipeline and select a deal fixture with detail history. 2. Perform the case action: Deal detail timeline. 3. Verify deal detail shows timeline, collaboration data, documents, or rep profile as applicable. 4. Confirm registration and approval history is shown with correct author, timestamp, metadata, or CTA. 5. Refresh the detail view and confirm persisted data remains visible. | S60: 4.5
C61: PARTNER_UI_MY_PIPELINE_016 | D61: Accept - Co-sell override proposal - Partner acceptance is recorded | E61: Functional | F61: P1 | G61: Critical | H61: =IF(J61="No",I61,IF(OR(I61="FAILED",K61="FAILED"),"FAILED",IF(OR(I61="PASSED",K61="PASSED"),"PASSED",IF(OR(I61="IN_PROGRESS",K61="IN_PROGRESS"),"IN_PROGRESS",IF(OR(I61="BLOCKED",K61="BLOCKED"),"BLOCKED","NOT_STARTED"))))) -> NOT_STARTED | I61: NOT_STARTED | J61: NO | K61: NOT_STARTED | L61: §3 Scenario C, §5.2, §8.5 | M61: partner-platform-prd-v1.8.md | O61: Trang Le | Q61: Validate the UI flow for co-sell override proposal so that partner acceptance is recorded. Scope covers the partner pipeline list, deal detail, collaboration, protection, and co-sell workflow, authenticated partner/SA role access as applicable, visible copy/state, primary CTA behavior, and PRD coverage §3 Scenario C, §5.2, §8.5. Out of scope: unrelated modules and deep backend calculation beyond the data needed to prove this case. | R61: 1. Open a co-sell deal fixture with ACV and approval state matching the scenario. 2. Review the proposed split/override area. 3. Attempt the acceptance or override action described by the test case. 4. Verify written partner agreement is required/recorded when ACV is above $100K and unavailable when at or below $100K. 5. Confirm the approved split is locked and visible in the deal record. | S61: 3-C
C62: PARTNER_UI_MY_PIPELINE_017 | D62: Block - Co-sell override under or equal $100K ACV - Override option is unavailable | E62: Negative | F62: P1 | G62: Major | H62: =IF(J62="No",I62,IF(OR(I62="FAILED",K62="FAILED"),"FAILED",IF(OR(I62="PASSED",K62="PASSED"),"PASSED",IF(OR(I62="IN_PROGRESS",K62="IN_PROGRESS"),"IN_PROGRESS",IF(OR(I62="BLOCKED",K62="BLOCKED"),"BLOCKED","NOT_STARTED"))))) -> NOT_STARTED | I62: NOT_STARTED | J62: NO | K62: NOT_STARTED | L62: §3 Scenario C, §5.2 | M62: partner-platform-prd-v1.8.md | O62: Trang Le | P62: Default 70/30 should apply without override path. | Q62: Validate the UI flow for co-sell override under or equal $100k acv so that override option is unavailable. Scope covers the partner pipeline list, deal detail, collaboration, protection, and co-sell workflow, authenticated partner/SA role access as applicable, visible copy/state, primary CTA behavior, and PRD coverage §3 Scenario C, §5.2. Out of scope: unrelated modules and deep backend calculation beyond the data needed to prove this case. | R62: 1. Open a co-sell deal fixture with ACV and approval state matching the scenario. 2. Review the proposed split/override area. 3. Attempt the acceptance or override action described by the test case. 4. Verify written partner agreement is required/recorded when ACV is above $100K and unavailable when at or below $100K. 5. Confirm the approved split is locked and visible in the deal record. | S62: 3-C
C63: PARTNER_UI_MY_PIPELINE_018 | D63: Require - Co-sell override above $100K ACV - Partner written agreement is required | E63: Functional | F63: P1 | G63: Critical | H63: =IF(J63="No",I63,IF(OR(I63="FAILED",K63="FAILED"),"FAILED",IF(OR(I63="PASSED",K63="PASSED"),"PASSED",IF(OR(I63="IN_PROGRESS",K63="IN_PROGRESS"),"IN_PROGRESS",IF(OR(I63="BLOCKED",K63="BLOCKED"),"BLOCKED","NOT_STARTED"))))) -> NOT_STARTED | I63: NOT_STARTED | J63: NO | K63: NOT_STARTED | L63: §3 Scenario C, §5.2 | M63: partner-platform-prd-v1.8.md | O63: Trang Le | P63: Override cannot be imposed unilaterally by BlazeUp. | Q63: Validate the UI flow for co-sell override above $100k acv so that partner written agreement is required. Scope covers the partner pipeline list, deal detail, collaboration, protection, and co-sell workflow, authenticated partner/SA role access as applicable, visible copy/state, primary CTA behavior, and PRD coverage §3 Scenario C, §5.2. Out of scope: unrelated modules and deep backend calculation beyond the data needed to prove this case. | R63: 1. Open a co-sell deal fixture with ACV and approval state matching the scenario. 2. Review the proposed split/override area. 3. Attempt the acceptance or override action described by the test case. 4. Verify written partner agreement is required/recorded when ACV is above $100K and unavailable when at or below $100K. 5. Confirm the approved split is locked and visible in the deal record. | S63: 3-C
B64: Deal Registration | C64: PARTNER_UI_MY_PIPELINE_019 | D64: Enrich - Blur valid domain - Company enrichment data is populated | E64: Functional | F64: P2 | G64: Major | H64: =IF(J64="No",I64,IF(OR(I64="FAILED",K64="FAILED"),"FAILED",IF(OR(I64="PASSED",K64="PASSED"),"PASSED",IF(OR(I64="IN_PROGRESS",K64="IN_PROGRESS"),"IN_PROGRESS",IF(OR(I64="BLOCKED",K64="BLOCKED"),"BLOCKED","NOT_STARTED"))))) -> NOT_STARTED | I64: NOT_STARTED | J64: NO | K64: NOT_STARTED | L64: §4.4, §8.5 | M64: partner-platform-prd-v1.8.md | O64: Trang Le | Q64: Validate the UI flow for blur valid domain so that company enrichment data is populated. Scope covers the deal registration wizard, validation, billing/deal-type capture, confirmation, and submission flow, authenticated partner/SA role access as applicable, visible copy/state, primary CTA behavior, and PRD coverage §4.4, §8.5. Out of scope: unrelated modules and deep backend calculation beyond the data needed to prove this case. | R64: 1. Log in as an active channel partner user with fixture data that supports this scenario. 2. Open /deals/register and confirm the expected partner/SA shell is loaded. 3. Perform the action: enrich / Blur valid domain. 4. Verify that company enrichment data is populated and that no unrelated page state regresses. 5. Capture any validation message, status badge, audit indicator, or navigation result required by §4.4, §8.5. | S64: 4.4
C65: PARTNER_UI_MY_PIPELINE_020 | D65: Select - Choose modules of interest - Selected modules persist to confirmation | E65: Functional | F65: P2 | G65: Major | H65: =IF(J65="No",I65,IF(OR(I65="FAILED",K65="FAILED"),"FAILED",IF(OR(I65="PASSED",K65="PASSED"),"PASSED",IF(OR(I65="IN_PROGRESS",K65="IN_PROGRESS"),"IN_PROGRESS",IF(OR(I65="BLOCKED",K65="BLOCKED"),"BLOCKED","NOT_STARTED"))))) -> NOT_STARTED | I65: NOT_STARTED | J65: NO | K65: NOT_STARTED | L65: §4.4 | M65: partner-platform-prd-v1.8.md | O65: Trang Le | Q65: Validate the UI flow for choose modules of interest so that selected modules persist to confirmation. Scope covers the deal registration wizard, validation, billing/deal-type capture, confirmation, and submission flow, authenticated partner/SA role access as applicable, visible copy/state, primary CTA behavior, and PRD coverage §4.4. Out of scope: unrelated modules and deep backend calculation beyond the data needed to prove this case. | R65: 1. Open the deal registration wizard and complete required prior fields. 2. Perform the selection described by the case: Choose modules of interest. 3. Continue to the next step and then to the review page. 4. Verify selected modules persist to confirmation and selected values remain persisted after navigation. 5. Confirm incompatible options or billing models are hidden/disabled according to the selected deal type. | S65: 4.4
C66: PARTNER_UI_MY_PIPELINE_021 | D66: Register - Conflict-lost prospect after 90 days - New registration path is available | E66: Functional | F66: P2 | G66: Major | H66: =IF(J66="No",I66,IF(OR(I66="FAILED",K66="FAILED"),"FAILED",IF(OR(I66="PASSED",K66="PASSED"),"PASSED",IF(OR(I66="IN_PROGRESS",K66="IN_PROGRESS"),"IN_PROGRESS",IF(OR(I66="BLOCKED",K66="BLOCKED"),"BLOCKED","NOT_STARTED"))))) -> NOT_STARTED | I66: NOT_STARTED | J66: NO | K66: NOT_STARTED | L66: §3 Scenario D, §4.4 | M66: partner-platform-prd-v1.8.md | O66: Trang Le | P66: Allowed only if no deal closed with winning party. | Q66: Validate the UI flow for conflict-lost prospect after 90 days so that new registration path is available. Scope covers the deal registration wizard, validation, billing/deal-type capture, confirmation, and submission flow, authenticated partner/SA role access as applicable, visible copy/state, primary CTA behavior, and PRD coverage §3 Scenario D, §4.4. Out of scope: unrelated modules and deep backend calculation beyond the data needed to prove this case. | R66: 1. Log in as an active channel partner user with fixture data that supports this scenario. 2. Open /deals/register and confirm the expected partner/SA shell is loaded. 3. Perform the action: register / Conflict-lost prospect after 90 days. 4. Verify that new registration path is available and that no unrelated page state regresses. 5. Capture any validation message, status badge, audit indicator, or navigation result required by §3 Scenario D, §4.4. | S66: 4.4
C67: PARTNER_UI_MY_PIPELINE_022 | D67: Block - No deal registration by either partner - Commission is not awarded to any party | E67: Negative | F67: P2 | G67: Major | H67: =IF(J67="No",I67,IF(OR(I67="FAILED",K67="FAILED"),"FAILED",IF(OR(I67="PASSED",K67="PASSED"),"PASSED",IF(OR(I67="IN_PROGRESS",K67="IN_PROGRESS"),"IN_PROGRESS",IF(OR(I67="BLOCKED",K67="BLOCKED"),"BLOCKED","NOT_STARTED"))))) -> NOT_STARTED | I67: NOT_STARTED | J67: NO | K67: NOT_STARTED | L67: §3 Scenario I | M67: partner-platform-prd-v1.8.md | O67: Trang Le | P67: Incentive to register: no registration = no attribution, no exceptions (§3 Scenario I). Prevents retroactive dispute claims. | Q67: Validate the UI flow for multi-partner influenced deal with no registration so that commission is not awarded to any party. Scope covers the deal registration policy enforcement per §3 Scenario I — when neither partner registers a formal deal, no attribution or commission is created regardless of partner involvement in the sales cycle. Out of scope: registered deal flows covered in Scenarios A–D. | R67: 1. Set up a fixture where two partners both have activity notes on a prospect but neither has submitted a deal registration for that prospect's domain.\n2. Log in as the first partner and navigate to My Pipeline.\n3. Verify the prospect does not appear in the pipeline (no registration = no pipeline entry).\n4. Log in as the second partner and confirm the same — prospect is not in their pipeline either.\n5. Confirm that after a trial/deal closes for this prospect (simulated by SA), neither partner portal shows a commission entry or attributed client for this prospect. | S67: 3-I
C68: PARTNER_UI_MY_PIPELINE_023 | D68: Register - Reseller deal type - End-client price field is absent | E68: Functional | F68: P1 | G68: Critical | H68: =IF(J68="No",I68,IF(OR(I68="FAILED",K68="FAILED"),"FAILED",IF(OR(I68="PASSED",K68="PASSED"),"PASSED",IF(OR(I68="IN_PROGRESS",K68="IN_PROGRESS"),"IN_PROGRESS",IF(OR(I68="BLOCKED",K68="BLOCKED"),"BLOCKED","NOT_STARTED"))))) -> NOT_STARTED | I68: NOT_STARTED | J68: NO | K68: NOT_STARTED | L68: §1.2, §3 Scenario B, §4.4 | M68: partner-platform-prd-v1.8.md | O68: Trang Le | P68: Locked decision: end-client price must NOT be captured in any system field (Renil) | Q68: Validate the UI flow for reseller deal registration so that end-client price field is absent. Scope covers the deal registration wizard, billing model selection, visible form fields, field visibility rules, and PRD coverage §1.2, §3 Scenario B, §4.4. Out of scope: commission calculation and backend price storage. | R68: 1. Open the deal registration wizard as an active reseller partner. 2. Select "Reseller" as deal type / billing model. 3. Advance through all wizard steps. 4. Verify no field for end-client price or end-user pricing exists at any step. 5. Confirm wizard completes without requiring price input. 6. Assert submitted deal record does not contain any end-client price field. | S68: 3-B
B69: Pipeline Management | C69: PARTNER_UI_MY_PIPELINE_024 | D69: Click - Pipeline snapshot deal card - Deal detail opens | E69: Functional | F69: P2 | G69: Major | H69: =IF(J69="No",I69,IF(OR(I69="FAILED",K69="FAILED"),"FAILED",IF(OR(I69="PASSED",K69="PASSED"),"PASSED",IF(OR(I69="IN_PROGRESS",K69="IN_PROGRESS"),"IN_PROGRESS",IF(OR(I69="BLOCKED",K69="BLOCKED"),"BLOCKED","NOT_STARTED"))))) -> NOT_STARTED | I69: NOT_STARTED | J69: NO | K69: NOT_STARTED | L69: §4.3, §4.5 | M69: partner-platform-prd-v1.8.md | O69: Trang Le | Q69: Validate the UI flow for pipeline snapshot deal card so that deal detail opens. Scope covers the partner pipeline list, deal detail, collaboration, protection, and co-sell workflow, authenticated partner/SA role access as applicable, visible copy/state, primary CTA behavior, and PRD coverage §4.3, §4.5. Out of scope: unrelated modules and deep backend calculation beyond the data needed to prove this case. | R69: 1. Open Dashboard with pipeline snapshot data. 2. Click a visible deal card such as Nexus Corp. 3. Confirm navigation to the corresponding deal detail view. 4. Verify company, ACV, stage, type, timeline, and assigned owner data match the selected card. 5. Return to Dashboard and confirm the snapshot state is preserved. | S69: 4.3
C70: PARTNER_UI_MY_PIPELINE_025 | D70: Search - Filter deals by company text - Matching deals are displayed | E70: Functional | F70: P2 | G70: Major | H70: =IF(J70="No",I70,IF(OR(I70="FAILED",K70="FAILED"),"FAILED",IF(OR(I70="PASSED",K70="PASSED"),"PASSED",IF(OR(I70="IN_PROGRESS",K70="IN_PROGRESS"),"IN_PROGRESS",IF(OR(I70="BLOCKED",K70="BLOCKED"),"BLOCKED","NOT_STARTED"))))) -> NOT_STARTED | I70: NOT_STARTED | J70: NO | K70: NOT_STARTED | L70: §4.5 | M70: partner-platform-prd-v1.8.md | O70: Trang Le | Q70: Validate the UI flow for filter deals by company text so that matching deals are displayed. Scope covers the partner pipeline list, deal detail, collaboration, protection, and co-sell workflow, authenticated partner/SA role access as applicable, visible copy/state, primary CTA behavior, and PRD coverage §4.5. Out of scope: unrelated modules and deep backend calculation beyond the data needed to prove this case. | R70: 1. Open My Pipeline with multiple deals across companies, types, modules, and stages. 2. Apply the filter/search action: Filter deals by company text. 3. Verify only matching deals remain visible and counts update if designed. 4. Clear the filter/search input. 5. Confirm the full list returns without stale filters. | S70: 4.5
C71: PARTNER_UI_MY_PIPELINE_026 | D71: Filter - Select deal type - Pipeline list is filtered | E71: Functional | F71: P2 | G71: Major | H71: =IF(J71="No",I71,IF(OR(I71="FAILED",K71="FAILED"),"FAILED",IF(OR(I71="PASSED",K71="PASSED"),"PASSED",IF(OR(I71="IN_PROGRESS",K71="IN_PROGRESS"),"IN_PROGRESS",IF(OR(I71="BLOCKED",K71="BLOCKED"),"BLOCKED","NOT_STARTED"))))) -> NOT_STARTED | I71: NOT_STARTED | J71: NO | K71: NOT_STARTED | L71: §4.5 | M71: partner-platform-prd-v1.8.md | O71: Trang Le | Q71: Validate the UI flow for select deal type so that pipeline list is filtered. Scope covers the partner pipeline list, deal detail, collaboration, protection, and co-sell workflow, authenticated partner/SA role access as applicable, visible copy/state, primary CTA behavior, and PRD coverage §4.5. Out of scope: unrelated modules and deep backend calculation beyond the data needed to prove this case. | R71: 1. Open My Pipeline with multiple deals across companies, types, modules, and stages. 2. Apply the filter/search action: Select deal type. 3. Verify only matching deals remain visible and counts update if designed. 4. Clear the filter/search input. 5. Confirm the full list returns without stale filters. | S71: 4.5
C72: PARTNER_UI_MY_PIPELINE_027 | D72: Filter - Select module - Pipeline list is filtered | E72: Functional | F72: P2 | G72: Major | H72: =IF(J72="No",I72,IF(OR(I72="FAILED",K72="FAILED"),"FAILED",IF(OR(I72="PASSED",K72="PASSED"),"PASSED",IF(OR(I72="IN_PROGRESS",K72="IN_PROGRESS"),"IN_PROGRESS",IF(OR(I72="BLOCKED",K72="BLOCKED"),"BLOCKED","NOT_STARTED"))))) -> NOT_STARTED | I72: NOT_STARTED | J72: NO | K72: NOT_STARTED | L72: §4.5 | M72: partner-platform-prd-v1.8.md | O72: Trang Le | Q72: Validate the UI flow for select module so that pipeline list is filtered. Scope covers the partner pipeline list, deal detail, collaboration, protection, and co-sell workflow, authenticated partner/SA role access as applicable, visible copy/state, primary CTA behavior, and PRD coverage §4.5. Out of scope: unrelated modules and deep backend calculation beyond the data needed to prove this case. | R72: 1. Open My Pipeline with multiple deals across companies, types, modules, and stages. 2. Apply the filter/search action: Select module. 3. Verify only matching deals remain visible and counts update if designed. 4. Clear the filter/search input. 5. Confirm the full list returns without stale filters. | S72: 4.5
C73: PARTNER_UI_MY_PIPELINE_028 | D73: Add - Deal shared note - Note appears with author and timestamp | E73: Functional | F73: P2 | G73: Major | H73: =IF(J73="No",I73,IF(OR(I73="FAILED",K73="FAILED"),"FAILED",IF(OR(I73="PASSED",K73="PASSED"),"PASSED",IF(OR(I73="IN_PROGRESS",K73="IN_PROGRESS"),"IN_PROGRESS",IF(OR(I73="BLOCKED",K73="BLOCKED"),"BLOCKED","NOT_STARTED"))))) -> NOT_STARTED | I73: NOT_STARTED | J73: NO | K73: NOT_STARTED | L73: §3 Scenario C, §4.5 | M73: partner-platform-prd-v1.8.md | O73: Trang Le | Q73: Validate the UI flow for deal shared note so that note appears with author and timestamp. Scope covers the partner pipeline list, deal detail, collaboration, protection, and co-sell workflow, authenticated partner/SA role access as applicable, visible copy/state, primary CTA behavior, and PRD coverage §3 Scenario C, §4.5. Out of scope: unrelated modules and deep backend calculation beyond the data needed to prove this case. | R73: 1. Open My Pipeline and select a deal fixture with detail history. 2. Perform the case action: Deal shared note. 3. Verify deal detail shows timeline, collaboration data, documents, or rep profile as applicable. 4. Confirm note appears with author and timestamp with correct author, timestamp, metadata, or CTA. 5. Refresh the detail view and confirm persisted data remains visible. | S73: 3-C
C74: PARTNER_UI_MY_PIPELINE_029 | D74: Upload - Deal document - Document appears in deal detail | E74: Functional | F74: P2 | G74: Major | H74: =IF(J74="No",I74,IF(OR(I74="FAILED",K74="FAILED"),"FAILED",IF(OR(I74="PASSED",K74="PASSED"),"PASSED",IF(OR(I74="IN_PROGRESS",K74="IN_PROGRESS"),"IN_PROGRESS",IF(OR(I74="BLOCKED",K74="BLOCKED"),"BLOCKED","NOT_STARTED"))))) -> NOT_STARTED | I74: NOT_STARTED | J74: NO | K74: NOT_STARTED | L74: §4.5 | M74: partner-platform-prd-v1.8.md | O74: Trang Le | Q74: Validate the UI flow for deal document so that document appears in deal detail. Scope covers the partner pipeline list, deal detail, collaboration, protection, and co-sell workflow, authenticated partner/SA role access as applicable, visible copy/state, primary CTA behavior, and PRD coverage §4.5. Out of scope: unrelated modules and deep backend calculation beyond the data needed to prove this case. | R74: 1. Open My Pipeline and select a deal fixture with detail history. 2. Perform the case action: Deal document. 3. Verify deal detail shows timeline, collaboration data, documents, or rep profile as applicable. 4. Confirm document appears in deal detail with correct author, timestamp, metadata, or CTA. 5. Refresh the detail view and confirm persisted data remains visible. | S74: 4.5
C75: PARTNER_UI_MY_PIPELINE_030 | D75: View - Assigned BlazeUp rep - Name, photo, email, and scheduling CTA are visible | E75: Functional | F75: P2 | G75: Major | H75: =IF(J75="No",I75,IF(OR(I75="FAILED",K75="FAILED"),"FAILED",IF(OR(I75="PASSED",K75="PASSED"),"PASSED",IF(OR(I75="IN_PROGRESS",K75="IN_PROGRESS"),"IN_PROGRESS",IF(OR(I75="BLOCKED",K75="BLOCKED"),"BLOCKED","NOT_STARTED"))))) -> NOT_STARTED | I75: NOT_STARTED | J75: NO | K75: NOT_STARTED | L75: §3 Scenario A, §4.5 | M75: partner-platform-prd-v1.8.md | O75: Trang Le | Q75: Validate the UI flow for assigned blazeup rep so that name, photo, email, and scheduling cta are visible. Scope covers the partner pipeline list, deal detail, collaboration, protection, and co-sell workflow, authenticated partner/SA role access as applicable, visible copy/state, primary CTA behavior, and PRD coverage §3 Scenario A, §4.5. Out of scope: unrelated modules and deep backend calculation beyond the data needed to prove this case. | R75: 1. Open My Pipeline and select a deal fixture with detail history. 2. Perform the case action: Assigned BlazeUp rep. 3. Verify deal detail shows timeline, collaboration data, documents, or rep profile as applicable. 4. Confirm name, photo, email, and scheduling cta are visible with correct author, timestamp, metadata, or CTA. 5. Refresh the detail view and confirm persisted data remains visible. | S75: 3-A
C76: PARTNER_UI_MY_PIPELINE_031 | D76: Request - Manual protection extension - Request is submitted with reason | E76: Functional | F76: P2 | G76: Major | H76: =IF(J76="No",I76,IF(OR(I76="FAILED",K76="FAILED"),"FAILED",IF(OR(I76="PASSED",K76="PASSED"),"PASSED",IF(OR(I76="IN_PROGRESS",K76="IN_PROGRESS"),"IN_PROGRESS",IF(OR(I76="BLOCKED",K76="BLOCKED"),"BLOCKED","NOT_STARTED"))))) -> NOT_STARTED | I76: NOT_STARTED | J76: NO | K76: NOT_STARTED | L76: §5.2, §8.5 | M76: partner-platform-prd-v1.8.md | O76: Trang Le | Q76: Validate the UI flow for manual protection extension so that request is submitted with reason. Scope covers the partner pipeline list, deal detail, collaboration, protection, and co-sell workflow, authenticated partner/SA role access as applicable, visible copy/state, primary CTA behavior, and PRD coverage §5.2, §8.5. Out of scope: unrelated modules and deep backend calculation beyond the data needed to prove this case. | R76: 1. Open a deal fixture with active deal protection close to expiry. 2. Click Request protection extension. 3. Enter a valid business reason and submit. 4. Verify the request is queued for SA review with timestamp/status. 5. Confirm protection clock/status reflects pending extension without granting duplicate auto-extension. | S76: 5.2
B77: Deal Management | C77: PARTNER_UI_MY_PIPELINE_032 | D77: Won - Reseller marks deal Won - Partner self-confirms close without SA approval | E77: Functional | F77: P1 | G77: Critical | H77: =IF(J77="No",I77,IF(OR(I77="FAILED",K77="FAILED"),"FAILED",IF(OR(I77="PASSED",K77="PASSED"),"PASSED",IF(OR(I77="IN_PROGRESS",K77="IN_PROGRESS"),"IN_PROGRESS",IF(OR(I77="BLOCKED",K77="BLOCKED"),"BLOCKED","NOT_STARTED"))))) -> NOT_STARTED | I77: NOT_STARTED | J77: NO | K77: NOT_STARTED | L77: §3 Scenario B, §4.4, §5.2 | M77: partner-platform-prd-v1.8.md | O77: Trang Le | P77: Reseller close: partner controls Won — no SA approval gate in flow | Q77: Validate the UI flow for reseller deal Won so that partner self-confirms close without SA approval gate. Scope covers the deal detail page, Won action CTA, approval state machine, deal status update, and PRD coverage §3 Scenario B, §4.4, §5.2. Out of scope: commission calculation and tenant provisioning. | R77: 1. Log in as reseller partner with an active registered deal. 2. Open the deal detail page. 3. Click "Mark as Won" CTA. 4. Verify no SA approval step or pending-approval state is shown — action completes immediately. 5. Verify deal status updates to Won. 6. Confirm partner receives in-portal confirmation. | S77: 3-B
B78: Deal List View | C78: PARTNER_UI_MY_PIPELINE_033 | D78: Display - Pipeline deal card - Reseller billing model tag is visible | E78: Functional | F78: P1 | G78: Major | H78: =IF(J78="No",I78,IF(OR(I78="FAILED",K78="FAILED"),"FAILED",IF(OR(I78="PASSED",K78="PASSED"),"PASSED",IF(OR(I78="IN_PROGRESS",K78="IN_PROGRESS"),"IN_PROGRESS",IF(OR(I78="BLOCKED",K78="BLOCKED"),"BLOCKED","NOT_STARTED"))))) -> NOT_STARTED | I78: NOT_STARTED | J78: NO | K78: NOT_STARTED | L78: §3 Scenario B, §4.5 | M78: partner-platform-prd-v1.8.md | O78: Trang Le | P78: Validate the UI flow for pipeline deal card display so that reseller billing model tag is visible. Scope covers the My Pipeline list view, deal card component, billing model indicator, and PRD coverage §3 Scenario B, §4.5. Out of scope: deal registration and commission calculation. | Q78: Validate the UI flow for pipeline deal card display so that reseller billing model tag is visible. Scope covers the My Pipeline list view, deal card component, billing model indicator, and PRD coverage §3 Scenario B, §4.5. Out of scope: deal registration and commission calculation. | R78: 1. Log in as reseller partner with at least one registered reseller deal. 2. Navigate to My Pipeline. 3. Locate the reseller deal card. 4. Verify deal card shows "Reseller" billing model tag/label. 5. Confirm tag is absent on non-reseller deal cards in the same list. | S78: 3-B
A79: Partner Portal Shell | B79: Navigation & Shell | C79: PARTNER_UI_PARTNER_PORTAL_SHELL_001 | D79: Navigate - Open main menu routes - Correct page content is shown | E79: Functional | F79: P1 | G79: Major | H79: =IF(J79="No",I79,IF(OR(I79="FAILED",K79="FAILED"),"FAILED",IF(OR(I79="PASSED",K79="PASSED"),"PASSED",IF(OR(I79="IN_PROGRESS",K79="IN_PROGRESS"),"IN_PROGRESS",IF(OR(I79="BLOCKED",K79="BLOCKED"),"BLOCKED","NOT_STARTED"))))) -> NOT_STARTED | I79: NOT_STARTED | J79: NO | K79: NOT_STARTED | L79: §4.2 | M79: partner-platform-prd-v1.8.md | O79: Trang Le | P79: Dashboard, deals, clients, commissions, training, resources, team, settings, support. | Q79: Validate the UI flow for open main menu routes so that correct page content is shown. Scope covers the Partner Portal Shell / Navigation & Shell behavior, authenticated partner/SA role access as applicable, visible copy/state, primary CTA behavior, and PRD coverage §4.2. Out of scope: unrelated modules and deep backend calculation beyond the data needed to prove this case. | R79: 1. Log in as an active channel partner user. 2. Click each primary nav item: Dashboard, My Pipeline, My Clients, Commissions, and Training. 3. Confirm the active tab updates and the expected page heading/content appears for each route. 4. Use browser back/forward or route navigation to confirm state remains stable. 5. Verify inaccessible or not-yet-enabled routes do not appear as broken pages. | S79: 4.2
B80: Responsive Layout | C80: PARTNER_UI_PARTNER_PORTAL_SHELL_002 | D80: Responsive - Partner portal mobile layout - Controls remain usable | E80: Functional | F80: P2 | G80: Major | H80: =IF(J80="No",I80,IF(OR(I80="FAILED",K80="FAILED"),"FAILED",IF(OR(I80="PASSED",K80="PASSED"),"PASSED",IF(OR(I80="IN_PROGRESS",K80="IN_PROGRESS"),"IN_PROGRESS",IF(OR(I80="BLOCKED",K80="BLOCKED"),"BLOCKED","NOT_STARTED"))))) -> NOT_STARTED | I80: NOT_STARTED | J80: NO | K80: NOT_STARTED | L80: §4.1, §4.4 | M80: partner-platform-prd-v1.8.md | O80: Trang Le | Q80: Validate the UI flow for partner portal mobile layout so that controls remain usable. Scope covers the Partner Portal Shell / Responsive Layout behavior, authenticated partner/SA role access as applicable, visible copy/state, primary CTA behavior, and PRD coverage §4.1, §4.4. Out of scope: unrelated modules and deep backend calculation beyond the data needed to prove this case. | R80: 1. Open the partner portal in desktop viewport and identify the target controls. 2. Resize or run the case in common mobile viewport widths. 3. Verify navigation, filters, tables/cards, CTAs, and forms remain visible and tappable. 4. Exercise one key workflow such as opening a deal or client detail. 5. Confirm no text overlap, clipped buttons, or inaccessible horizontal content blocks the workflow. | S80: 4.1
B81: Dual Account Switcher | C81: PARTNER_UI_PARTNER_PORTAL_SHELL_003 | D81: Switch - Dual account partner activates account switcher - Pack and Channel dashboards toggle correctly | E81: Functional | F81: P2 | G81: Major | H81: =IF(J81="No",I81,IF(OR(I81="FAILED",K81="FAILED"),"FAILED",IF(OR(I81="PASSED",K81="PASSED"),"PASSED",IF(OR(I81="IN_PROGRESS",K81="IN_PROGRESS"),"IN_PROGRESS",IF(OR(I81="BLOCKED",K81="BLOCKED"),"BLOCKED","NOT_STARTED"))))) -> NOT_STARTED | I81: NOT_STARTED | J81: NO | K81: NOT_STARTED | L81: §3-H | M81: partner-platform-prd-v1.8.md | O81: Trang Le | P81: [FIX ADDED 2026-05-27] §3-H Dual Account had no UI TC — covers account switcher between Pack and Channel dashboards | Q81: Validate the UI flow for a dual account partner switching between Pack and Channel dashboards so that each dashboard correctly reflects the right account context. | R81: 1. Log in as a partner with both Pack and Channel account types. 2. Locate the account switcher control in the portal shell. 3. Click to switch to Pack dashboard — verify Pack-specific content is displayed. 4. Switch back to Channel dashboard — verify Channel-specific content is displayed. 5. Confirm no data from Pack account leaks into Channel view and vice versa. | S81: 3-H
A82: Partner Team | B82: Team & Referral Links | C82: PARTNER_UI_PARTNER_TEAM_001 | D82: Invite - Partner team member - Invitation is sent with role | E82: Functional | F82: P2 | G82: Major | H82: =IF(J82="No",I82,IF(OR(I82="FAILED",K82="FAILED"),"FAILED",IF(OR(I82="PASSED",K82="PASSED"),"PASSED",IF(OR(I82="IN_PROGRESS",K82="IN_PROGRESS"),"IN_PROGRESS",IF(OR(I82="BLOCKED",K82="BLOCKED"),"BLOCKED","NOT_STARTED"))))) -> NOT_STARTED | I82: NOT_STARTED | J82: NO | K82: NOT_STARTED | L82: §4.10 | M82: partner-platform-prd-v1.8.md | O82: Trang Le | Q82: Validate the UI flow for partner team member so that invitation is sent with role. Scope covers the partner team administration and referral-link tracking behavior, authenticated partner/SA role access as applicable, visible copy/state, primary CTA behavior, and PRD coverage §4.10. Out of scope: unrelated modules and deep backend calculation beyond the data needed to prove this case. | R82: 1. Navigate to Partner Team or Settings referral-link area. 2. Perform the action: Partner team member. 3. Verify role/campaign/link fields validate and save correctly. 4. Confirm invitation is sent with role and the new row/link is visible. 5. For copy action, verify clipboard success message and link format include the partner slug/campaign identifier. | S82: 4.10
C83: PARTNER_UI_PARTNER_TEAM_002 | D83: Create - Campaign referral link - Link and analytics row are created | E83: Functional | F83: P2 | G83: Major | H83: =IF(J83="No",I83,IF(OR(I83="FAILED",K83="FAILED"),"FAILED",IF(OR(I83="PASSED",K83="PASSED"),"PASSED",IF(OR(I83="IN_PROGRESS",K83="IN_PROGRESS"),"IN_PROGRESS",IF(OR(I83="BLOCKED",K83="BLOCKED"),"BLOCKED","NOT_STARTED"))))) -> NOT_STARTED | I83: NOT_STARTED | J83: NO | K83: NOT_STARTED | L83: §4.10, §8.4 | M83: partner-platform-prd-v1.8.md | O83: Trang Le | Q83: Validate the UI flow for campaign referral link so that link and analytics row are created. Scope covers the partner team administration and referral-link tracking behavior, authenticated partner/SA role access as applicable, visible copy/state, primary CTA behavior, and PRD coverage §4.10, §8.4. Out of scope: unrelated modules and deep backend calculation beyond the data needed to prove this case. | R83: 1. Navigate to Partner Team or Settings referral-link area. 2. Perform the action: Campaign referral link. 3. Verify role/campaign/link fields validate and save correctly. 4. Confirm link and analytics row are created and the new row/link is visible. 5. For copy action, verify clipboard success message and link format include the partner slug/campaign identifier. | S83: 4.10
C84: PARTNER_UI_PARTNER_TEAM_003 | D84: Copy - Referral link - Clipboard action succeeds | E84: Functional | F84: P3 | G84: Minor | H84: =IF(J84="No",I84,IF(OR(I84="FAILED",K84="FAILED"),"FAILED",IF(OR(I84="PASSED",K84="PASSED"),"PASSED",IF(OR(I84="IN_PROGRESS",K84="IN_PROGRESS"),"IN_PROGRESS",IF(OR(I84="BLOCKED",K84="BLOCKED"),"BLOCKED","NOT_STARTED"))))) -> NOT_STARTED | I84: NOT_STARTED | J84: NO | K84: NOT_STARTED | L84: §4.10 | M84: partner-platform-prd-v1.8.md | O84: Trang Le | Q84: Validate the UI flow for referral link so that clipboard action succeeds. Scope covers the partner team administration and referral-link tracking behavior, authenticated partner/SA role access as applicable, visible copy/state, primary CTA behavior, and PRD coverage §4.10. Out of scope: unrelated modules and deep backend calculation beyond the data needed to prove this case. | R84: 1. Navigate to Partner Team or Settings referral-link area. 2. Perform the action: Referral link. 3. Verify role/campaign/link fields validate and save correctly. 4. Confirm clipboard action succeeds and the new row/link is visible. 5. For copy action, verify clipboard success message and link format include the partner slug/campaign identifier. | S84: 4.10
A85: Resources | B85: Resources & Sandbox | C85: PARTNER_UI_RESOURCES_001 | D85: Reset - Demo sandbox - Profile selection and reset confirmation are shown | E85: Functional | F85: P2 | G85: Major | H85: =IF(J85="No",I85,IF(OR(I85="FAILED",K85="FAILED"),"FAILED",IF(OR(I85="PASSED",K85="PASSED"),"PASSED",IF(OR(I85="IN_PROGRESS",K85="IN_PROGRESS"),"IN_PROGRESS",IF(OR(I85="BLOCKED",K85="BLOCKED"),"BLOCKED","NOT_STARTED"))))) -> NOT_STARTED | I85: NOT_STARTED | J85: NO | K85: NOT_STARTED | L85: §4.9, §8.3, §12.1 B5 | M85: partner-platform-prd-v1.8.md | O85: Trang Le | Q85: Validate the UI flow for demo sandbox so that profile selection and reset confirmation are shown. Scope covers the partner resources, co-branded collateral, ROI calculator, and demo sandbox reset behavior, authenticated partner/SA role access as applicable, visible copy/state, primary CTA behavior, and PRD coverage §4.9, §8.3, §12.1 B5. Out of scope: unrelated modules and deep backend calculation beyond the data needed to prove this case. | R85: 1. Navigate to Resources/Sandbox with partner profile and logo fixtures configured. 2. Perform the action: Demo sandbox. 3. Verify the correct file, generated asset, calculator output, or sandbox reset confirmation is produced. 4. Confirm profile selection and reset confirmation are shown and selected sandbox profile/reset warning are clear where applicable. 5. Validate generated/downloaded content uses partner branding and does not include another partner data. | S85: 4.9
C86: PARTNER_UI_RESOURCES_002 | D86: Configure - Demo sandbox weekly auto-reset - Toggle is default off with reset warning | E86: Functional | F86: P2 | G86: Major | H86: =IF(J86="No",I86,IF(OR(I86="FAILED",K86="FAILED"),"FAILED",IF(OR(I86="PASSED",K86="PASSED"),"PASSED",IF(OR(I86="IN_PROGRESS",K86="IN_PROGRESS"),"IN_PROGRESS",IF(OR(I86="BLOCKED",K86="BLOCKED"),"BLOCKED","NOT_STARTED"))))) -> NOT_STARTED | I86: NOT_STARTED | J86: NO | K86: NOT_STARTED | L86: §4.9, §8.3, §12.1 B5 | M86: partner-platform-prd-v1.8.md | O86: Trang Le | P86: On-demand reset remains primary; weekly reset optional. | Q86: Validate the UI flow for demo sandbox weekly auto-reset so that toggle is default off with reset warning. Scope covers the partner resources, co-branded collateral, ROI calculator, and demo sandbox reset behavior, authenticated partner/SA role access as applicable, visible copy/state, primary CTA behavior, and PRD coverage §4.9, §8.3, §12.1 B5. Out of scope: unrelated modules and deep backend calculation beyond the data needed to prove this case. | R86: 1. Navigate to Resources/Sandbox with partner profile and logo fixtures configured. 2. Perform the action: Demo sandbox weekly auto-reset. 3. Verify the correct file, generated asset, calculator output, or sandbox reset confirmation is produced. 4. Confirm toggle is default off with reset warning and selected sandbox profile/reset warning are clear where applicable. 5. Validate generated/downloaded content uses partner branding and does not include another partner data. | S86: 4.9
C87: PARTNER_UI_RESOURCES_003 | D87: Download - Marketing resource - Correct file is served | E87: Functional | F87: P3 | G87: Minor | H87: =IF(J87="No",I87,IF(OR(I87="FAILED",K87="FAILED"),"FAILED",IF(OR(I87="PASSED",K87="PASSED"),"PASSED",IF(OR(I87="IN_PROGRESS",K87="IN_PROGRESS"),"IN_PROGRESS",IF(OR(I87="BLOCKED",K87="BLOCKED"),"BLOCKED","NOT_STARTED"))))) -> NOT_STARTED | I87: NOT_STARTED | J87: NO | K87: NOT_STARTED | L87: §4.9 | M87: partner-platform-prd-v1.8.md | O87: Trang Le | Q87: Validate the UI flow for marketing resource so that correct file is served. Scope covers the partner resources, co-branded collateral, ROI calculator, and demo sandbox reset behavior, authenticated partner/SA role access as applicable, visible copy/state, primary CTA behavior, and PRD coverage §4.9. Out of scope: unrelated modules and deep backend calculation beyond the data needed to prove this case. | R87: 1. Navigate to Resources/Sandbox with partner profile and logo fixtures configured. 2. Perform the action: Marketing resource. 3. Verify the correct file, generated asset, calculator output, or sandbox reset confirmation is produced. 4. Confirm correct file is served and selected sandbox profile/reset warning are clear where applicable. 5. Validate generated/downloaded content uses partner branding and does not include another partner data. | S87: 4.9
C88: PARTNER_UI_RESOURCES_004 | D88: Generate - Co-branded pitch deck - Partner logo is inserted | E88: Functional | F88: P3 | G88: Minor | H88: =IF(J88="No",I88,IF(OR(I88="FAILED",K88="FAILED"),"FAILED",IF(OR(I88="PASSED",K88="PASSED"),"PASSED",IF(OR(I88="IN_PROGRESS",K88="IN_PROGRESS"),"IN_PROGRESS",IF(OR(I88="BLOCKED",K88="BLOCKED"),"BLOCKED","NOT_STARTED"))))) -> NOT_STARTED | I88: NOT_STARTED | J88: NO | K88: NOT_STARTED | L88: §4.9 | M88: partner-platform-prd-v1.8.md | O88: Trang Le | Q88: Validate the UI flow for co-branded pitch deck so that partner logo is inserted. Scope covers the partner resources, co-branded collateral, ROI calculator, and demo sandbox reset behavior, authenticated partner/SA role access as applicable, visible copy/state, primary CTA behavior, and PRD coverage §4.9. Out of scope: unrelated modules and deep backend calculation beyond the data needed to prove this case. | R88: 1. Navigate to Resources/Sandbox with partner profile and logo fixtures configured. 2. Perform the action: Co-branded pitch deck. 3. Verify the correct file, generated asset, calculator output, or sandbox reset confirmation is produced. 4. Confirm partner logo is inserted and selected sandbox profile/reset warning are clear where applicable. 5. Validate generated/downloaded content uses partner branding and does not include another partner data. | S88: 4.9
C89: PARTNER_UI_RESOURCES_005 | D89: Open - ROI calculator - Prospect PDF can be generated | E89: Functional | F89: P3 | G89: Minor | H89: =IF(J89="No",I89,IF(OR(I89="FAILED",K89="FAILED"),"FAILED",IF(OR(I89="PASSED",K89="PASSED"),"PASSED",IF(OR(I89="IN_PROGRESS",K89="IN_PROGRESS"),"IN_PROGRESS",IF(OR(I89="BLOCKED",K89="BLOCKED"),"BLOCKED","NOT_STARTED"))))) -> NOT_STARTED | I89: NOT_STARTED | J89: NO | K89: NOT_STARTED | L89: §4.9 | M89: partner-platform-prd-v1.8.md | O89: Trang Le | Q89: Validate the UI flow for roi calculator so that prospect pdf can be generated. Scope covers the partner resources, co-branded collateral, ROI calculator, and demo sandbox reset behavior, authenticated partner/SA role access as applicable, visible copy/state, primary CTA behavior, and PRD coverage §4.9. Out of scope: unrelated modules and deep backend calculation beyond the data needed to prove this case. | R89: 1. Navigate to Resources/Sandbox with partner profile and logo fixtures configured. 2. Perform the action: ROI calculator. 3. Verify the correct file, generated asset, calculator output, or sandbox reset confirmation is produced. 4. Confirm prospect pdf can be generated and selected sandbox profile/reset warning are clear where applicable. 5. Validate generated/downloaded content uses partner branding and does not include another partner data. | S89: 4.9
A90: SA Partner Module | B90: Deal Conflict Queue | C90: PARTNER_UI_SA_PARTNER_MODULE_001 | D90: Resolve - Conflict queue with reasoning - Decision is saved and parties notified | E90: Functional | F90: P1 | G90: Critical | H90: =IF(J90="No",I90,IF(OR(I90="FAILED",K90="FAILED"),"FAILED",IF(OR(I90="PASSED",K90="PASSED"),"PASSED",IF(OR(I90="IN_PROGRESS",K90="IN_PROGRESS"),"IN_PROGRESS",IF(OR(I90="BLOCKED",K90="BLOCKED"),"BLOCKED","NOT_STARTED"))))) -> NOT_STARTED | I90: NOT_STARTED | J90: NO | K90: NOT_STARTED | L90: §3 Scenario D, §5.2, §9.4 | M90: partner-platform-prd-v1.8.md | O90: Trang Le | Q90: Validate the UI flow for conflict queue with reasoning so that decision is saved and parties notified. Scope covers the SA partner-management operations, approval queues, conflict resolution, rates, territories, and analytics, authenticated partner/SA role access as applicable, visible copy/state, primary CTA behavior, and PRD coverage §3 Scenario D, §5.2, §9.4. Out of scope: unrelated modules and deep backend calculation beyond the data needed to prove this case. | R90: 1. Log in as an SA partner-operations admin with a fixture containing two parties registered on the same domain. 2. Navigate to Deal Management → Conflict Queue and open the conflicted deal. 3. Select the winning party (Partner A or BlazeUp Direct) using the Decision radio buttons. 4. Enter a mandatory written reasoning in the Reasoning field and click Submit Decision. 5. Verify both parties receive a notification, the decision and reasoning are logged to the audit trail, and the conflict record becomes immutable (no further edit possible). | S90: 5.2
C91: PARTNER_UI_SA_PARTNER_MODULE_002 | D91: Resolve - Conflict queue decision - Prospect confirmation and written reasoning are visible | E91: Functional | F91: P1 | G91: Critical | H91: =IF(J91="No",I91,IF(OR(I91="FAILED",K91="FAILED"),"FAILED",IF(OR(I91="PASSED",K91="PASSED"),"PASSED",IF(OR(I91="IN_PROGRESS",K91="IN_PROGRESS"),"IN_PROGRESS",IF(OR(I91="BLOCKED",K91="BLOCKED"),"BLOCKED","NOT_STARTED"))))) -> NOT_STARTED | I91: NOT_STARTED | J91: NO | K91: NOT_STARTED | L91: §3 Scenario D, §5.2, §9.4 | M91: partner-platform-prd-v1.8.md | O91: Trang Le | P91: Includes 5 business day mediation expectation. | Q91: Validate the UI flow for conflict queue decision so that prospect confirmation and written reasoning are visible. Scope covers the SA partner-management operations, approval queues, conflict resolution, rates, territories, and analytics, authenticated partner/SA role access as applicable, visible copy/state, primary CTA behavior, and PRD coverage §3 Scenario D, §5.2, §9.4. Out of scope: unrelated modules and deep backend calculation beyond the data needed to prove this case. | R91: 1. Log in as an SA partner-operations admin with a conflict fixture where prospect confirmation status is available. 2. Navigate to Deal Management → Conflict Queue and open the conflicted deal. 3. Verify the Prospect Contacted field shows Yes / No / Cannot reach options and the first-registered timestamp is visible for both parties. 4. Select a prospect confirmation status and verify the UI highlights the recommended winner per PRD §3 Scenario D rule order. 5. Confirm written reasoning is required before Submit Decision is enabled and that the 5-business-day SLA indicator is shown on the conflict record. | S91: 5.2
B92: Partner Directory | C92: PARTNER_UI_SA_PARTNER_MODULE_003 | D92: Admin - Partner directory loads - Filters and partner rows are visible | E92: Functional | F92: P1 | G92: Critical | H92: =IF(J92="No",I92,IF(OR(I92="FAILED",K92="FAILED"),"FAILED",IF(OR(I92="PASSED",K92="PASSED"),"PASSED",IF(OR(I92="IN_PROGRESS",K92="IN_PROGRESS"),"IN_PROGRESS",IF(OR(I92="BLOCKED",K92="BLOCKED"),"BLOCKED","NOT_STARTED"))))) -> NOT_STARTED | I92: NOT_STARTED | J92: NO | K92: NOT_STARTED | L92: §5.1 | M92: partner-platform-prd-v1.8.md | O92: Trang Le | Q92: Validate the UI flow for partner directory loads so that filters and partner rows are visible. Scope covers the SA partner-management operations, approval queues, conflict resolution, rates, territories, and analytics, authenticated partner/SA role access as applicable, visible copy/state, primary CTA behavior, and PRD coverage §5.1. Out of scope: unrelated modules and deep backend calculation beyond the data needed to prove this case. | R92: 1. Log in as an SA partner-operations admin and navigate to /partners. 2. Verify the partner directory table loads with columns: Partner, Tier, ARR, Open Deals, Clients, Status. 3. Apply the Region, Tier, Type, and Status filters one at a time and confirm the list updates correctly after each. 4. Use the search bar to find a partner by name and verify the correct row appears. 5. Click through to Pending Approval tab and confirm pending applicants are listed separately from active partners. | S92: 5.1
B93: SA Operations | C93: PARTNER_UI_SA_PARTNER_MODULE_004 | D93: Review - Partner application FSM - SA Review Legal Countersign and Final Approval stages are visible | E93: Functional | F93: P1 | G93: Critical | H93: =IF(J93="No",I93,IF(OR(I93="FAILED",K93="FAILED"),"FAILED",IF(OR(I93="PASSED",K93="PASSED"),"PASSED",IF(OR(I93="IN_PROGRESS",K93="IN_PROGRESS"),"IN_PROGRESS",IF(OR(I93="BLOCKED",K93="BLOCKED"),"BLOCKED","NOT_STARTED"))))) -> NOT_STARTED | I93: NOT_STARTED | J93: NO | K93: NOT_STARTED | L93: §5.1, §12.1 B3 | M93: partner-platform-prd-v1.8.md | O93: Trang Le | Q93: Validate the UI flow for partner application fsm so that sa review legal countersign and final approval stages are visible. Scope covers the SA partner-management operations, approval queues, conflict resolution, rates, territories, and analytics, authenticated partner/SA role access as applicable, visible copy/state, primary CTA behavior, and PRD coverage §5.1, §12.1 B3. Out of scope: unrelated modules and deep backend calculation beyond the data needed to prove this case. | R93: 1. Log in as an SA partner-operations admin and navigate to a partner application in Pending Approval status. 2. Verify the application review UI displays three distinct FSM stages: SA Review, Legal Countersign, Final Approval — each with a clear status indicator (active/pending/complete). 3. Confirm the current active stage is highlighted and previous stages show completion state. 4. Verify the SA cannot skip stages — Final Approval button is disabled while Legal Countersign stage is incomplete. 5. Confirm the applicant's company details, contact, regions, type, and team certifications are visible on the same screen. | S93: 5.1a
C94: PARTNER_UI_SA_PARTNER_MODULE_005 | D94: Block - Missing signed agreement - SA cannot advance to legal countersign | E94: Negative | F94: P1 | G94: Critical | H94: =IF(J94="No",I94,IF(OR(I94="FAILED",K94="FAILED"),"FAILED",IF(OR(I94="PASSED",K94="PASSED"),"PASSED",IF(OR(I94="IN_PROGRESS",K94="IN_PROGRESS"),"IN_PROGRESS",IF(OR(I94="BLOCKED",K94="BLOCKED"),"BLOCKED","NOT_STARTED"))))) -> NOT_STARTED | I94: NOT_STARTED | J94: NO | K94: NOT_STARTED | L94: §5.1, §12.1 B3 | M94: partner-platform-prd-v1.8.md | O94: Trang Le | Q94: Validate the UI flow for missing signed agreement so that sa cannot advance to legal countersign. Scope covers the SA partner-management operations, approval queues, conflict resolution, rates, territories, and analytics, authenticated partner/SA role access as applicable, visible copy/state, primary CTA behavior, and PRD coverage §5.1, §12.1 B3. Out of scope: unrelated modules and deep backend calculation beyond the data needed to prove this case. | R94: 1. Log in as an SA partner-operations admin and open a partner application that has no signed partner agreement attached. 2. Navigate to the SA Review stage and attempt to advance to Legal Countersign without attaching an agreement. 3. Verify the Advance to Legal Countersign button is disabled or blocked with an inline error message indicating the signed agreement is required. 4. Click Request Agreement and confirm the system sends a notification to the applicant's primary contact. 5. Attach a mock signed agreement document and confirm the Advance button becomes enabled. | S94: 5.1
C95: PARTNER_UI_SA_PARTNER_MODULE_006 | D95: Countersign - Legal countersigns partner agreement - Final approval becomes available | E95: Functional | F95: P1 | G95: Critical | H95: =IF(J95="No",I95,IF(OR(I95="FAILED",K95="FAILED"),"FAILED",IF(OR(I95="PASSED",K95="PASSED"),"PASSED",IF(OR(I95="IN_PROGRESS",K95="IN_PROGRESS"),"IN_PROGRESS",IF(OR(I95="BLOCKED",K95="BLOCKED"),"BLOCKED","NOT_STARTED"))))) -> NOT_STARTED | I95: NOT_STARTED | J95: NO | K95: NOT_STARTED | L95: §5.1, §9.4, §12.1 B3 | M95: partner-platform-prd-v1.8.md | O95: Trang Le | P95: Covers staged approval FSM after signed agreement is attached. | Q95: Validate the UI flow for legal countersigns partner agreement so that final approval becomes available. Scope covers the SA partner-management operations, approval queues, conflict resolution, rates, territories, and analytics, authenticated partner/SA role access as applicable, visible copy/state, primary CTA behavior, and PRD coverage §5.1, §9.4, §12.1 B3. Out of scope: unrelated modules and deep backend calculation beyond the data needed to prove this case. | R95: 1. Log in as an SA partner-operations admin with required permissions. 2. Open the SA partner module area relevant to: Legal countersigns partner agreement. 3. Locate or create the partner/deal/rate/conflict fixture for this scenario. 4. Perform the action and verify final approval becomes available. 5. Confirm audit trail, written reasoning, approval stage, notification, or analytics update required by the PRD is present. | S95: 5.1
C96: PARTNER_UI_SA_PARTNER_MODULE_007 | D96: Review - SA deal approval queue - Pending and conflict queues are visible | E96: Functional | F96: P1 | G96: Critical | H96: =IF(J96="No",I96,IF(OR(I96="FAILED",K96="FAILED"),"FAILED",IF(OR(I96="PASSED",K96="PASSED"),"PASSED",IF(OR(I96="IN_PROGRESS",K96="IN_PROGRESS"),"IN_PROGRESS",IF(OR(I96="BLOCKED",K96="BLOCKED"),"BLOCKED","NOT_STARTED"))))) -> NOT_STARTED | I96: NOT_STARTED | J96: NO | K96: NOT_STARTED | L96: §5.2 | M96: partner-platform-prd-v1.8.md | O96: Trang Le | Q96: Validate the UI flow for sa deal approval queue so that pending and conflict queues are visible. Scope covers the SA partner-management operations, approval queues, conflict resolution, rates, territories, and analytics, authenticated partner/SA role access as applicable, visible copy/state, primary CTA behavior, and PRD coverage §5.2. Out of scope: unrelated modules and deep backend calculation beyond the data needed to prove this case. | R96: 1. Log in as an SA partner-operations admin. 2. Navigate to /partners → Deal Management → Pending Approval queue. 3. Verify the pending approval queue lists deals with partner name, ACV, deal type, domain, enrichment data, and conflict-check status. 4. Switch to the Conflict Queue tab and verify it shows conflicted-domain deals with both parties listed. 5. Confirm the Approve + Assign, Reject, and Request Info buttons are visible on at least one pending deal row. | S96: 5.2
C97: PARTNER_UI_SA_PARTNER_MODULE_008 | D97: Approve - SA assigns rep to co-sell deal - Approval starts protection clock | E97: Functional | F97: P1 | G97: Critical | H97: =IF(J97="No",I97,IF(OR(I97="FAILED",K97="FAILED"),"FAILED",IF(OR(I97="PASSED",K97="PASSED"),"PASSED",IF(OR(I97="IN_PROGRESS",K97="IN_PROGRESS"),"IN_PROGRESS",IF(OR(I97="BLOCKED",K97="BLOCKED"),"BLOCKED","NOT_STARTED"))))) -> NOT_STARTED | I97: NOT_STARTED | J97: NO | K97: NOT_STARTED | L97: §5.2, §6.2 | M97: partner-platform-prd-v1.8.md | O97: Trang Le | Q97: Validate the UI flow for sa assigns rep to co-sell deal so that approval starts protection clock. Scope covers the SA partner-management operations, approval queues, conflict resolution, rates, territories, and analytics, authenticated partner/SA role access as applicable, visible copy/state, primary CTA behavior, and PRD coverage §5.2, §6.2. Out of scope: unrelated modules and deep backend calculation beyond the data needed to prove this case. | R97: 1. Log in as an SA partner-operations admin and open a co-sell deal in the Pending Approval queue. 2. Select a BlazeUp rep from the Assign BlazeUp rep dropdown and click Approve + Assign. 3. Verify the deal status changes to Approved and the protection clock start date is stamped with today's date. 4. Confirm the assigned rep receives a task in the dogfood CRM: "Reach out to [partner] re: [prospect] co-sell." 5. Verify the partner portal shows the deal as Approved with the assigned rep's name, photo, and email visible in the deal detail. | S97: 5.2
C98: PARTNER_UI_SA_PARTNER_MODULE_009 | D98: Configure - Commission rate table - Versioned rates can be edited | E98: Functional | F98: P1 | G98: Critical | H98: =IF(J98="No",I98,IF(OR(I98="FAILED",K98="FAILED"),"FAILED",IF(OR(I98="PASSED",K98="PASSED"),"PASSED",IF(OR(I98="IN_PROGRESS",K98="IN_PROGRESS"),"IN_PROGRESS",IF(OR(I98="BLOCKED",K98="BLOCKED"),"BLOCKED","NOT_STARTED"))))) -> NOT_STARTED | I98: NOT_STARTED | J98: NO | K98: NOT_STARTED | L98: §5.3, §8.2 | M98: partner-platform-prd-v1.8.md | O98: Trang Le | Q98: Validate the UI flow for commission rate table so that versioned rates can be edited. Scope covers the SA partner-management operations, approval queues, conflict resolution, rates, territories, and analytics, authenticated partner/SA role access as applicable, visible copy/state, primary CTA behavior, and PRD coverage §5.3, §8.2. Out of scope: unrelated modules and deep backend calculation beyond the data needed to prove this case. | R98: 1. Log in as an SA partner-operations admin and navigate to Commission → Rate Table. 2. Verify the current rate table displays all tier × deal-type combinations (Registered/Select/Advanced/Premier × Referral/Reseller/Co-sell) with NN, EN, EE rate fields. 3. Click Edit rates, change one rate value (e.g. Select Referral NN rate), and save. 4. Verify a new version is created with a new version ID and effectiveFrom date; the previous version is preserved in Version history and not overwritten. 5. Confirm a deal approved after the rate change uses the new rate, while a deal approved before continues to show the previously locked rate. | S98: 5.3
C99: PARTNER_UI_SA_PARTNER_MODULE_010 | D99: Configure - SPIFF programme - Bonus programme is created | E99: Functional | F99: P2 | G99: Major | H99: =IF(J99="No",I99,IF(OR(I99="FAILED",K99="FAILED"),"FAILED",IF(OR(I99="PASSED",K99="PASSED"),"PASSED",IF(OR(I99="IN_PROGRESS",K99="IN_PROGRESS"),"IN_PROGRESS",IF(OR(I99="BLOCKED",K99="BLOCKED"),"BLOCKED","NOT_STARTED"))))) -> NOT_STARTED | I99: NOT_STARTED | J99: NO | K99: NOT_STARTED | L99: §5.3 | M99: partner-platform-prd-v1.8.md | O99: Trang Le | Q99: Validate the UI flow for spiff programme so that bonus programme is created. Scope covers the SA partner-management operations, approval queues, conflict resolution, rates, territories, and analytics, authenticated partner/SA role access as applicable, visible copy/state, primary CTA behavior, and PRD coverage §5.3. Out of scope: unrelated modules and deep backend calculation beyond the data needed to prove this case. | R99: 1. Log in as an SA partner-operations admin and navigate to Commission → SPIFF Programmes. 2. Click + Add SPIFF Programme and fill in: name, bonus percentage, applicable regions, applicable tiers (Select/Advanced/Premier), valid from/to dates. 3. Save the programme and verify it appears in the Active SPIFF Programmes list with correct details. 4. Confirm the programme is inactive before the valid from date and that the Edit and Deactivate actions are available. 5. Verify the new SPIFF is included in the commission projection shown to partners when registering a qualifying deal during the programme window. | S99: 5.3
C100: PARTNER_UI_SA_PARTNER_MODULE_011 | D100: View - SA analytics dashboard - Funnel and waiver metrics are displayed | E100: Functional | F100: P2 | G100: Major | H100: =IF(J100="No",I100,IF(OR(I100="FAILED",K100="FAILED"),"FAILED",IF(OR(I100="PASSED",K100="PASSED"),"PASSED",IF(OR(I100="IN_PROGRESS",K100="IN_PROGRESS"),"IN_PROGRESS",IF(OR(I100="BLOCKED",K100="BLOCKED"),"BLOCKED","NOT_STARTED"))))) -> NOT_STARTED | I100: NOT_STARTED | J100: NO | K100: NOT_STARTED | L100: §5.5 | M100: partner-platform-prd-v1.8.md | O100: Trang Le | Q100: Validate the UI flow for sa analytics dashboard so that funnel and waiver metrics are displayed. Scope covers the SA partner-management operations, approval queues, conflict resolution, rates, territories, and analytics, authenticated partner/SA role access as applicable, visible copy/state, primary CTA behavior, and PRD coverage §5.5. Out of scope: unrelated modules and deep backend calculation beyond the data needed to prove this case. | R100: 1. Log in as an SA partner-operations admin and navigate to the Partner Programme Analytics dashboard. 2. Verify the funnel metrics are visible: Registered → Approved → In Progress → Won → Lost with counts and conversion rates. 3. Confirm summary KPIs are shown: Partner-sourced ARR, Approval Rate, Win Rate, Avg Deal Size, Avg Deal Velocity vs direct. 4. Locate the commission metrics section and verify Commission Paid YTD, Pending, Clawbacks Issued, and Clawback Waivers Granted are all displayed as separate line items. 5. Verify the Top 5 Partners by ARR table shows tier badge, PSM allocation type (dedicated vs shared), and client count per partner. | S100: 5.5
C101: PARTNER_UI_SA_PARTNER_MODULE_012 | D101: Assign - Territory exclusivity - Assignment saves with effective dates | E101: Functional | F101: P2 | G101: Major | H101: =IF(J101="No",I101,IF(OR(I101="FAILED",K101="FAILED"),"FAILED",IF(OR(I101="PASSED",K101="PASSED"),"PASSED",IF(OR(I101="IN_PROGRESS",K101="IN_PROGRESS"),"IN_PROGRESS",IF(OR(I101="BLOCKED",K101="BLOCKED"),"BLOCKED","NOT_STARTED"))))) -> NOT_STARTED | I101: NOT_STARTED | J101: NO | K101: NOT_STARTED | L101: §5.4 | M101: partner-platform-prd-v1.8.md | O101: Trang Le | Q101: Validate the UI flow for territory exclusivity so that assignment saves with effective dates. Scope covers the SA partner-management operations, approval queues, conflict resolution, rates, territories, and analytics, authenticated partner/SA role access as applicable, visible copy/state, primary CTA behavior, and PRD coverage §5.4. Out of scope: unrelated modules and deep backend calculation beyond the data needed to prove this case. | R101: 1. Log in as an SA partner-operations admin, open a partner profile, and navigate to Territory Assignments. 2. Click + Assign Territory and fill in: regions (e.g. UAE, Saudi Arabia), verticals (e.g. HR + Payroll), exclusivity type (Exclusive), effective from date, and effective to date. 3. Save and verify the assignment row appears with all selected values and correct date range. 4. Confirm that setting exclusivity type to Exclusive shows a warning if another partner already has Preferred or Exclusive rights in the same region/vertical combination. 5. Verify the territory rule is reflected in conflict resolution: when a new deal is registered in an Exclusive territory, the SA conflict queue auto-routes it to the exclusive partner rather than entering normal first-registered-wins flow. | S101: 5.4
A102: Security / Compliance | B102: Security & Compliance | C102: PARTNER_UI_SECURITY_COMPLIANCE_001 | D102: Deny - Cross-partner data access in UI - Other partner data is not visible | E102: Security | F102: P1 | G102: Critical | H102: =IF(J102="No",I102,IF(OR(I102="FAILED",K102="FAILED"),"FAILED",IF(OR(I102="PASSED",K102="PASSED"),"PASSED",IF(OR(I102="IN_PROGRESS",K102="IN_PROGRESS"),"IN_PROGRESS",IF(OR(I102="BLOCKED",K102="BLOCKED"),"BLOCKED","NOT_STARTED"))))) -> NOT_STARTED | I102: NOT_STARTED | J102: NO | K102: NOT_STARTED | L102: §9.1 | M102: partner-platform-prd-v1.8.md | O102: Trang Le | Q102: Validate the UI flow for cross-partner data access in ui so that other partner data is not visible. Scope covers the partner security, access-control, audit, data minimization, and compliance controls, authenticated partner/SA role access as applicable, visible copy/state, primary CTA behavior, and PRD coverage §9.1. Out of scope: unrelated modules and deep backend calculation beyond the data needed to prove this case. | R102: 1. Prepare fixtures for at least two partners and one SA/admin action where applicable. 2. Log in with the role required for: Cross-partner data access in UI. 3. Attempt to view, submit, or audit the targeted data/action. 4. Verify other partner data is not visible and only allowed fields/data are exposed. 5. Confirm denial, placeholder, notification, or audit entry includes the required actor/action/context without leaking sensitive data. | S102: 9.1
...

Sheet Regression Suite
A1: REGRESSION SUITE — MODULE STATUS SUMMARY
A2: Item | B2: Description | C2: Summary
A3: TOTAL | B3: Total number of tests | C3: =SUM(C4:C8) -> 119
A4: PASSED | B4: Number of tests PASSED | C4: =COUNTIF('Regression Suite'!G13:G999,"PASSED") -> 0
A5: FAILED | B5: Number of tests FAILED | C5: =COUNTIF('Regression Suite'!G13:G999,"FAILED") -> 0
A6: NOT_STARTED | B6: Number of tests not started | C6: =COUNTIF('Regression Suite'!G13:G999,"NOT_STARTED") -> 118
A7: IN_PROGRESS | B7: Number currently being tested | C7: =COUNTIF('Regression Suite'!G13:G999,"IN_PROGRESS") -> 0
A8: BLOCKED | B8: Tests that could not be executed | C8: =COUNTIF('Regression Suite'!G13:G999,"BLOCKED") -> 1
A11: REGRESSION SUITE — P1 Test Cases (All Modules)
A12: Auto-compiled from all P1 TCs across active modules | Run before every release
A13: TC ID | B13: Module | C13: Test Case Name | D13: Type (UI/API) | E13: Priority | F13: Owner | G13: Automation Status | H13: Automation TC Mapping
A14: Partner Platform
A15: PARTNER_UI_PARTNER_PORTAL_SHELL_001 | B15: Partner Platform | C15: Navigate - Open main menu routes - Correct page content is shown | D15: UI | E15: P1 | F15: Trang Le | G15: NOT_STARTED | H15: tests/ui/partner_002
A16: PARTNER_UI_DASHBOARD_001 | B16: Partner Platform | C16: View - Partner shell loads for channel partner - Dashboard is displayed | D16: UI | E16: P1 | F16: Trang Le | G16: NOT_STARTED | H16: tests/ui/partner_001
A17: PARTNER_UI_DASHBOARD_002 | B17: Partner Platform | C17: Render - Dashboard KPI cards available - Actionable metrics are visible | D17: UI | E17: P1 | F17: Trang Le | G17: NOT_STARTED | H17: tests/ui/partner_003
A18: PARTNER_UI_DASHBOARD_003 | B18: Partner Platform | C18: Render - Tier progress exists on dashboard - Progress to next tier is visible | D18: UI | E18: P1 | F18: Trang Le | G18: NOT_STARTED | H18: tests/ui/partner_004
A19: PARTNER_UI_DASHBOARD_004 | B19: Partner Platform | C19: Render - Action Required list has pending tasks - Partner sees next actions | D19: UI | E19: P1 | F19: Trang Le | G19: NOT_STARTED | H19: tests/ui/partner_005
A20: PARTNER_UI_DASHBOARD_005 | B20: Partner Platform | C20: Calculate - Tier qualification dashboard - T12M ARR threshold and next-tier delta are visible | D20: UI | E20: P1 | F20: Trang Le | G20: NOT_STARTED
A21: PARTNER_UI_DASHBOARD_006 | B21: Partner Platform | C21: Warn - Tier downgrade pending - 30-day notice and grace quarter are displayed | D21: UI | E21: P1 | F21: Trang Le | G21: NOT_STARTED
A22: PARTNER_UI_MY_PIPELINE_001 | B22: Partner Platform | C22: Register - Enter valid company details - Wizard advances to contact step | D22: UI | E22: P1 | F22: Trang Le | G22: NOT_STARTED | H22: tests/ui/partner_010
A23: PARTNER_UI_MY_PIPELINE_002 | B23: Partner Platform | C23: Validate - Leave company name blank - Required field error is shown | D23: UI | E23: P1 | F23: Trang Le | G23: NOT_STARTED | H23: tests/ui/partner_011
A24: PARTNER_UI_MY_PIPELINE_003 | B24: Partner Platform | C24: Validate - Enter invalid domain - Domain format error is shown | D24: UI | E24: P1 | F24: Trang Le | G24: NOT_STARTED | H24: tests/ui/partner_012
A25: PARTNER_UI_MY_PIPELINE_004 | B25: Partner Platform | C25: Warn - Domain already exists - Inline active-account warning is shown | D25: UI | E25: P1 | F25: Trang Le | G25: NOT_STARTED | H25: tests/ui/partner_014
A26: PARTNER_UI_MY_PIPELINE_005 | B26: Partner Platform | C26: Submit - Existing domain with warning - Deal enters conflict queue | D26: UI | E26: P1 | F26: Trang Le | G26: NOT_STARTED | H26: tests/ui/partner_015
A27: PARTNER_UI_MY_PIPELINE_006 | B27: Partner Platform | C27: Validate - Enter contact without email - Required field error is shown | D27: UI | E27: P1 | F27: Trang Le | G27: NOT_STARTED | H27: tests/ui/partner_016
A28: PARTNER_UI_MY_PIPELINE_007 | B28: Partner Platform | C28: Validate - Enter malformed email - Email error is shown | D28: UI | E28: P1 | F28: Trang Le | G28: NOT_STARTED | H28: tests/ui/partner_017
A29: PARTNER_UI_MY_PIPELINE_008 | B29: Partner Platform | C29: Select - Choose referral deal type - Direct billing model is implied | D29: UI | E29: P1 | F29: Trang Le | G29: NOT_STARTED | H29: tests/ui/partner_020
A30: PARTNER_UI_MY_PIPELINE_009 | B30: Partner Platform | C30: Select - Choose reseller deal type - Reseller billing path is available | D30: UI | E30: P1 | F30: Trang Le | G30: NOT_STARTED | H30: tests/ui/partner_021
A31: PARTNER_UI_MY_PIPELINE_010 | B31: Partner Platform | C31: Select - Choose co-sell deal type - Co-sell option is captured | D31: UI | E31: P1 | F31: Trang Le | G31: NOT_STARTED | H31: tests/ui/partner_022
A32: PARTNER_UI_MY_PIPELINE_011 | B32: Partner Platform | C32: Confirm - Review registration summary - All entered data is displayed | D32: UI | E32: P1 | F32: Trang Le | G32: NOT_STARTED | H32: tests/ui/partner_023
A33: PARTNER_UI_MY_PIPELINE_012 | B33: Partner Platform | C33: Submit - Valid deal registration - Success response appears within 2 seconds | D33: UI | E33: P1 | F33: Trang Le | G33: NOT_STARTED | H33: tests/ui/partner_024
... A37: PARTNER_UI_MY_PIPELINE_016 | B37: Partner Platform | C37: Accept - Co-sell override proposal - Partner acceptance is recorded | D37: UI | E37: P1 | F37: Trang Le | G37: NOT_STARTED | H37: tests/ui/partner_034
A38: PARTNER_UI_MY_PIPELINE_017 | B38: Partner Platform | C38: Block - Co-sell override under or equal $100K ACV - Override option is unavailable | D38: UI | E38: P1 | F38: Trang Le | G38: NOT_STARTED
A39: PARTNER_UI_MY_PIPELINE_018 | B39: Partner Platform | C39: Require - Co-sell override above $100K ACV - Partner written agreement is required | D39: UI | E39: P1 | F39: Trang Le | G39: NOT_STARTED
A40: PARTNER_UI_MY_CLIENTS_001 | B40: Partner Platform | C40: Click - Action Required renewal CTA - Renewal registration flow opens | D40: UI | E40: P1 | F40: Trang Le | G40: NOT_STARTED | H40: tests/ui/partner_006
A41: PARTNER_UI_MY_CLIENTS_002 | B41: Partner Platform | C41: List - Open My Clients - Post-close clients are displayed | D41: UI | E41: P1 | F41: Trang Le | G41: NOT_STARTED | H41: tests/ui/partner_036
A42: PARTNER_UI_MY_CLIENTS_003 | B42: Partner Platform | C42: Open - Client health detail - ARR, renewal, usage, tickets, and CSM are visible | D42: UI | E42: P1 | F42: Trang Le | G42: NOT_STARTED | H42: tests/ui/partner_040
A43: PARTNER_UI_MY_CLIENTS_004 | B43: Partner Platform | C43: Register - Renewal deal from client detail - Renewal context is prefilled | D43: UI | E43: P1 | F43: Trang Le | G43: NOT_STARTED | H43: tests/ui/partner_041
A44: PARTNER_UI_MY_CLIENTS_005 | B44: Partner Platform | C44: Add - MSP managed client - Provisioning form is shown | D44: UI | E44: P1 | F44: Trang Le | G44: NOT_STARTED | H44: tests/ui/partner_043
A45: PARTNER_UI_MY_CLIENTS_006 | B45: Partner Platform | C45: Toggle - MSP ticket consent default - Consent is off by default | D45: UI | E45: P1 | F45: Trang Le | G45: NOT_STARTED | H45: tests/ui/partner_044
A46: PARTNER_UI_COMMISSIONS_001 | B46: Partner Platform | C46: Calculate - Type estimated annual value - Commission projection updates live | D46: UI | E46: P1 | F46: Trang Le | G46: NOT_STARTED | H46: tests/ui/partner_018
A47: PARTNER_UI_COMMISSIONS_002 | B47: Partner Platform | C47: View - Commissions page - Earned pending and paid totals are visible | D47: UI | E47: P1 | F47: Trang Le | G47: NOT_STARTED | H47: tests/ui/partner_045
A48: PARTNER_UI_COMMISSIONS_003 | B48: Partner Platform | C48: Trace - Commission row detail - Deal close to payment details are visible | D48: UI | E48: P1 | F48: Trang Le | G48: NOT_STARTED | H48: tests/ui/partner_046
A49: PARTNER_UI_COMMISSIONS_004 | B49: Partner Platform | C49: Submit - Commission dispute - Dispute is created from one text field | D49: UI | E49: P1 | F49: Trang Le | G49: NOT_STARTED | H49: tests/ui/partner_047
A50: PARTNER_UI_COMMISSIONS_005 | B50: Partner Platform | C50: Submit - Product failure waiver - Evidence can be linked and request submitted | D50: UI | E50: P1 | F50: Trang Le | G50: NOT_STARTED | H50: tests/ui/partner_048
A51: PARTNER_UI_COMMISSIONS_006 | B51: Partner Platform | C51: Approve - Commission payout over $10K - Two-eye approval is enforced | D51: UI | E51: P1 | F51: Trang Le | G51: NOT_STARTED | H51: tests/ui/partner_069
A52: PARTNER_UI_COMMISSIONS_007 | B52: Partner Platform | C52: Display - Clawback notification - Policy terms and product-failure waiver path are visible | D52: UI | E52: P1 | F52: Trang Le | G52: NOT_STARTED
A53: PARTNER_UI_SA_PARTNER_MODULE_001 | B53: Partner Platform | C53: Resolve - Conflict queue with reasoning - Decision is saved and parties notified | D53: UI | E53: P1 | F53: Trang Le | G53: NOT_STARTED | H53: tests/ui/partner_066
A54: PARTNER_UI_SA_PARTNER_MODULE_002 | B54: Partner Platform | C54: Resolve - Conflict queue decision - Prospect confirmation and written reasoning are visible | D54: UI | E54: P1 | F54: Trang Le | G54: NOT_STARTED
A55: PARTNER_UI_SA_PARTNER_MODULE_003 | B55: Partner Platform | C55: Admin - Partner directory loads - Filters and partner rows are visible | D55: UI | E55: P1 | F55: Trang Le | G55: NOT_STARTED | H55: tests/ui/partner_060
A56: PARTNER_UI_SA_PARTNER_MODULE_004 | B56: Partner Platform | C56: Review - Partner application FSM - SA Review Legal Countersign and Final Approval stages are visible | D56: UI | E56: P1 | F56: Trang Le | G56: NOT_STARTED | H56: tests/ui/partner_061
A57: PARTNER_UI_SA_PARTNER_MODULE_005 | B57: Partner Platform | C57: Block - Missing signed agreement - SA cannot advance to legal countersign | D57: UI | E57: P1 | F57: Trang Le | G57: NOT_STARTED | H57: tests/ui/partner_062
A58: PARTNER_UI_SA_PARTNER_MODULE_006 | B58: Partner Platform | C58: Approve - Partner final approval - Portal account creation is triggered | D58: UI | E58: P1 | F58: Trang Le | G58: NOT_STARTED | H58: tests/ui/partner_063
A59: PARTNER_UI_SA_PARTNER_MODULE_007 | B59: Partner Platform | C59: Review - SA deal approval queue - Pending and conflict queues are visible | D59: UI | E59: P1 | F59: Trang Le | G59: NOT_STARTED | H59: tests/ui/partner_064
A60: PARTNER_UI_SA_PARTNER_MODULE_008 | B60: Partner Platform | C60: Approve - SA assigns rep to co-sell deal - Approval starts protection clock | D60: UI | E60: P1 | F60: Trang Le | G60: NOT_STARTED | H60: tests/ui/partner_065
A61: PARTNER_UI_SA_PARTNER_MODULE_009 | B61: Partner Platform | C61: Configure - Commission rate table - Versioned rates can be edited | D61: UI | E61: P1 | F61: Trang Le | G61: NOT_STARTED | H61: tests/ui/partner_067
A62: PARTNER_UI_SECURITY_COMPLIANCE_001 | B62: Partner Platform | C62: Deny - Cross-partner data access in UI - Other partner data is not visible | D62: UI | E62: P1 | F62: Trang Le | G62: NOT_STARTED | H62: tests/ui/partner_073
A63: PARTNER_UI_SECURITY_COMPLIANCE_002 | B63: Partner Platform | C63: Audit - SA action completed - Activity log entry is visible | D63: UI | E63: P1 | F63: Trang Le | G63: NOT_STARTED | H63: tests/ui/partner_074
A64: PARTNER_UI_SECURITY_COMPLIANCE_003 | B64: Partner Platform | C64: Validate - Deal registration prospect data minimization - Only allowed prospect fields are requested | D64: UI | E64: P1 | F64: Trang Le | G64: NOT_STARTED
A65: PARTNER_API_AUTH_ACCESS_CONTROL_001 | B65: Partner Platform | C65: Authenticate - Valid partner JWT - Partner-scoped request succeeds | D65: API | E65: P1 | F65: Trang Le | G65: NOT_STARTED | H65: tests/api/partner_001
A66: PARTNER_API_AUTH_ACCESS_CONTROL_002 | B66: Partner Platform | C66: Reject - Tenant JWT on partner API - Request is unauthorized | D66: API | E66: P1 | F66: Trang Le | G66: NOT_STARTED | H66: tests/api/partner_002
A67: PARTNER_API_AUTH_ACCESS_CONTROL_003 | B67: Partner Platform | C67: Reject - Partner JWT accessing another partner - Request is forbidden | D67: API | E67: P1 | F67: Trang Le | G67: NOT_STARTED | H67: tests/api/partner_003
A68: PARTNER_API_AUTH_ACCESS_CONTROL_004 | B68: Partner Platform | C68: Enforce - Admin MFA policy - Protected action requires MFA | D68: API | E68: P1 | F68: Trang Le | G68: NOT_STARTED | H68: tests/api/partner_004
A69: PARTNER_API_AUTH_ACCESS_CONTROL_005 | B69: Partner Platform | C69: Guard - MSP accesses payroll data - Request is forbidden | D69: API | E69: P1 | F69: Trang Le | G69: NOT_STARTED | H69: tests/api/partner_027
A70: PARTNER_API_AUTH_ACCESS_CONTROL_006 | B70: Partner Platform | C70: Guard - MSP exports employee records - Request is forbidden | D70: API | E70: P1 | F70: Trang Le | G70: NOT_STARTED | H70: tests/api/partner_028
A71: PARTNER_API_DASHBOARD_DATA_001 | B71: Partner Platform | C71: GET - Partner dashboard stats - KPI schema is returned | D71: API | E71: P1 | F71: Trang Le | G71: NOT_STARTED | H71: tests/api/partner_005
A72: PARTNER_API_DEAL_REGISTRATION_001 | B72: Partner Platform | C72: Validate - Missing required registration fields - 400 response includes field errors | D72: API | E72: P1 | F72: Trang Le | G72: NOT_STARTED | H72: tests/api/partner_010
A73: PARTNER_API_DEAL_REGISTRATION_PIPELINE_001 | B73: Partner Platform | C73: POST - Register referral deal - Deal is created pending approval | D73: API | E73: P1 | F73: Trang Le | G73: NOT_STARTED | H73: tests/api/partner_006
A74: PARTNER_API_DEAL_REGISTRATION_PIPELINE_002 | B74: Partner Platform | C74: POST - Register reseller deal - Billing model reseller is stored | D74: API | E74: P1 | F74: Trang Le | G74: NOT_STARTED | H74: tests/api/partner_007
A75: PARTNER_API_DEAL_REGISTRATION_PIPELINE_003 | B75: Partner Platform | C75: POST - Register co-sell deal - Co-sell metadata is stored | D75: API | E75: P1 | F75: Trang Le | G75: NOT_STARTED | H75: tests/api/partner_008
A76: PARTNER_API_DEAL_REGISTRATION_PIPELINE_004 | B76: Partner Platform | C76: POST - Register deal with existing domain - Conflict status is raised | D76: API | E76: P1 | F76: Trang Le | G76: NOT_STARTED | H76: tests/api/partner_009
... A82: PARTNER_API_DEAL_REGISTRATION_PIPELINE_010 | B82: Partner Platform | C82: Sync - Deal approved event - CRM owner and stage are updated | D82: API | E82: P1 | F82: Trang Le | G82: NOT_STARTED | H82: tests/api/partner_056
A83: PARTNER_API_DEAL_REGISTRATION_PIPELINE_011 | B83: Partner Platform | C83: Calculate - Co-sell split default - 70/30 split is stored for standard co-sell deal | D83: API | E83: P1 | F83: Trang Le | G83: NOT_STARTED
A84: PARTNER_API_DEAL_REGISTRATION_PIPELINE_012 | B84: Partner Platform | C84: Reject - Co-sell split override at or below $100K ACV - Override is not accepted | D84: API | E84: P1 | F84: Trang Le | G84: NOT_STARTED
A85: PARTNER_API_DEAL_REGISTRATION_PIPELINE_013 | B85: Partner Platform | C85: Resolve - Conflict with prospect confirmation - Confirmed partner wins conflict | D85: API | E85: P1 | F85: Trang Le | G85: NOT_STARTED
A86: PARTNER_API_DEAL_REGISTRATION_PIPELINE_014 | B86: Partner Platform | C86: Resolve - Conflict with unreachable prospect - First registered deal wins tiebreaker | D86: API | E86: P1 | F86: Trang Le | G86: NOT_STARTED
A87: PARTNER_API_DEAL_REGISTRATION_PIPELINE_015 | B87: Partner Platform | C87: Enforce - Multi-partner influenced deal with no registration - No attribution or commission is created on tenant provisioning | D87: API | E87: P1 | F87: Trang Le | G87: NOT_STARTED
A88: PARTNER_API_PIPELINE_MANAGEMENT_001 | B88: Partner Platform | C88: GET - Partner deals list - Only own deals are returned | D88: API | E88: P1 | F88: Trang Le | G88: NOT_STARTED | H88: tests/api/partner_012
A89: PARTNER_API_TENANT_PROVISIONING_ATTRIBUTION_001 | B89: Partner Platform | C89: POST - Accept co-sell override - Override is locked at approval | D89: API | E89: P1 | F89: Trang Le | G89: NOT_STARTED | H89: tests/api/partner_016
A90: PARTNER_API_TENANT_PROVISIONING_ATTRIBUTION_002 | B90: Partner Platform | C90: POST - Referral close - Tenant provision and commission events are emitted | D90: API | E90: P1 | F90: Trang Le | G90: NOT_STARTED | H90: tests/api/partner_029
A91: PARTNER_API_TENANT_PROVISIONING_ATTRIBUTION_003 | B91: Partner Platform | C91: POST - Reseller close - Invoice targets reseller partner | D91: API | E91: P1 | F91: Trang Le | G91: NOT_STARTED | H91: tests/api/partner_030
A92: PARTNER_API_TENANT_PROVISIONING_ATTRIBUTION_004 | B92: Partner Platform | C92: POST - Expansion close - Existing tenant line items are updated | D92: API | E92: P1 | F92: Trang Le | G92: NOT_STARTED | H92: tests/api/partner_031
A93: PARTNER_API_TENANT_PROVISIONING_ATTRIBUTION_005 | B93: Partner Platform | C93: Calculate - Expansion commission NN stage - Full configured rate applies | D93: API | E93: P1 | F93: Trang Le | G93: NOT_STARTED | H93: tests/api/partner_032
A94: PARTNER_API_TENANT_PROVISIONING_ATTRIBUTION_006 | B94: Partner Platform | C94: Calculate - Expansion commission EN stage - Lower configured rate applies | D94: API | E94: P1 | F94: Trang Le | G94: NOT_STARTED | H94: tests/api/partner_033
A95: PARTNER_API_TENANT_PROVISIONING_ATTRIBUTION_007 | B95: Partner Platform | C95: Sync - Deal won event - CRM opportunity closes won with tenant ID | D95: API | E95: P1 | F95: Trang Le | G95: NOT_STARTED | H95: tests/api/partner_057
A96: PARTNER_API_TENANT_PROVISIONING_ATTRIBUTION_008 | B96: Partner Platform | C96: Store - Tenant attribution block - Permanent partner fields are written | D96: API | E96: P1 | F96: Trang Le | G96: NOT_STARTED | H96: tests/api/partner_058
A97: PARTNER_API_TENANT_PROVISIONING_ATTRIBUTION_009 | B97: Partner Platform | C97: Override - Tenant attribution by SA - Two-eye approval and history are required | D97: API | E97: P1 | F97: Trang Le | G97: NOT_STARTED | H97: tests/api/partner_059
A98: PARTNER_API_TENANT_PROVISIONING_ATTRIBUTION_010 | B98: Partner Platform | C98: Lock - Co-sell override after partner acceptance - Approved split cannot be renegotiated | D98: API | E98: P1 | F98: Trang Le | G98: NOT_STARTED
A99: PARTNER_API_CLIENT_HEALTH_MSP_001 | B99: Partner Platform | C99: GET - Partner clients - Post-close tenants are returned | D99: API | E99: P1 | F99: Trang Le | G99: NOT_STARTED | H99: tests/api/partner_021
A100: PARTNER_API_CLIENT_HEALTH_MSP_002 | B100: Partner Platform | C100: GET - Client health metrics - Usage renewal and ticket metrics are returned | D100: API | E100: P1 | F100: Trang Le | G100: NOT_STARTED | H100: tests/api/partner_022
A101: PARTNER_API_CLIENT_HEALTH_MSP_003 | B101: Partner Platform | C101: GET - Client tickets without MSP consent - Only count and severity are returned | D101: API | E101: P1 | F101: Trang Le | G101: NOT_STARTED | H101: tests/api/partner_023
A102: PARTNER_API_CLIENT_HEALTH_MSP_004 | B102: Partner Platform | C102: GET - Client tickets with MSP consent - Ticket content is returned | D102: API | E102: P1 | F102: Trang Le | G102: NOT_STARTED | H102: tests/api/partner_024
A103: PARTNER_API_CLIENT_HEALTH_MSP_005 | B103: Partner Platform | C103: PATCH - Revoke MSP consent - Content access stops immediately | D103: API | E103: P1 | F103: Trang Le | G103: NOT_STARTED | H103: tests/api/partner_025
A104: PARTNER_API_CLIENT_HEALTH_MSP_006 | B104: Partner Platform | C104: POST - MSP tenant provision - partner_managed tenant is created | D104: API | E104: P1 | F104: Trang Le | G104: NOT_STARTED | H104: tests/api/partner_026
A105: PARTNER_API_CLIENT_HEALTH_MSP_007 | B105: Partner Platform | C105: Transfer - MSP handoff - Old history preserved and event emitted | D105: API | E105: P1 | F105: Trang Le | G105: NOT_STARTED | H105: tests/api/partner_060
A106: PARTNER_API_CLIENT_HEALTH_MSP_008 | B106: Partner Platform | C106: Calculate - MSP tier qualification - Total managed ARR is used | D106: API | E106: P1 | F106: Trang Le | G106: NOT_STARTED | H106: tests/api/partner_062
A107: PARTNER_API_CLIENT_HEALTH_MSP_009 | B107: Partner Platform | C107: Audit - MSP consent grant and revoke - Event includes actor timestamps and access changes immediately | D107: API | E107: P1 | F107: Trang Le | G107: NOT_STARTED
A108: PARTNER_API_COMMISSIONS_PAYOUTS_001 | B108: Partner Platform | C108: Calculate - Renewal EE stage - Lowest configured rate applies | D108: API | E108: P1 | F108: Trang Le | G108: NOT_STARTED | H108: tests/api/partner_034
A109: PARTNER_API_COMMISSIONS_PAYOUTS_002 | B109: Partner Platform | C109: GET - Commission history - Partner commission ledger is returned | D109: API | E109: P1 | F109: Trang Le | G109: NOT_STARTED | H109: tests/api/partner_035
A110: PARTNER_API_COMMISSIONS_PAYOUTS_003 | B110: Partner Platform | C110: POST - Commission dispute - Dispute log entry is created | D110: API | E110: P1 | F110: Trang Le | G110: NOT_STARTED | H110: tests/api/partner_036
...

Sheet Execution Log
A1: Execution Log
A2: Sprint / Release | B2: Date | C2: Build Version | D2: Module | E2: TC ID | F2: Executor | G2: Result | H2: Note
A3: Sprint 1 | B3: 2026-05-20 | C3: v0.1.0-alpha | D3: Partner Platform | E3: PARTNER_UI_001 | F3: Trang Le | G3: Not Started | H3: Initial smoke run — placeholder

Sheet Test Scope
A1: TEST SCOPE
A2: Document: partner-platform-prd-v1.8 | Last updated: 2026-05-20 | Status: Living Document
A3: ✅ IN SCOPE
A4: Category | B4: Module | C4: Description | D4: Owner | E4: Status
A5: Partner Platform
A6: In Scope | B6: Partner Platform | C6: Partner portal shell: navigation, dashboard, KPI cards, tier progress, action-required list. | D6: QA Team | E6: Active
A7: In Scope | B7: Partner Platform | C7: Deal registration wizard: referral, reseller, co-sell deal types; validation, conflict detection, commission projection. | D7: QA Team | E7: Active
A8: In Scope | B8: Partner Platform | C8: Pipeline management: deal list, filters, deal detail, timeline, notes, documents, BlazeUp rep view. | D8: QA Team | E8: Active
A9: In Scope | B9: Partner Platform | C9: Client health: client list, health detail (ARR, renewal, usage, tickets), MSP managed client provisioning, consent toggle. | D9: QA Team | E9: Active
A10: In Scope | B10: Partner Platform | C10: Commissions: earned/pending/paid totals, commission trace, dispute submission, product failure waiver, payout details. | D10: QA Team | E10: Active
A11: In Scope | B11: Partner Platform | C11: Training & Resources: certifications, learning paths, marketing assets, co-branded deck, ROI calculator, sandbox reset. | D11: QA Team | E11: Active
A12: In Scope | B12: Partner Platform | C12: Team & Referral: team member invite, campaign referral link creation and analytics. | D12: QA Team | E12: Active
A13: In Scope | B13: Partner Platform | C13: SA Partner Module: partner directory, application FSM (staged approval), deal approval/conflict queues, commission config, territory, analytics, ledger approval. | D13: QA Team | E13: Active
A14: In Scope | B14: Partner Platform | C14: Backend APIs: ms-sa-partners endpoints, Kafka events, MongoDB/Redis persistence, commission engine, tenant provisioning, MSP scope guard, audit trail. | D14: QA Team | E14: Active
A15: In Scope | B15: Partner Platform | C15: Security: partner JWT separation, cross-partner isolation, MFA gates, MSP consent enforcement, SA two-eye approvals, data residency. | D15: QA Team | E15: Active
A17: 🚫 OUT OF SCOPE
A18: Category | B18: Module | C18: Description | D18: Owner | E18: Status
A19: Pack Partner
A20: Out of Scope | B20: Pack Partner | C20: Pack Partner marketplace features — only separation from Channel Partner accounts is validated. | D20: N/A | E20: Excluded
A21: Partner Platform
A22: Out of Scope | B22: Partner Platform | C22: Final Legal/Compliance decisions pending sign-off — related test cases are placeholders only. | D22: N/A | E22: Excluded
A23: Out of Scope | B23: Partner Platform | C23: Exact commission rates/window durations for NN/EN/EE stages — SA will configure values before launch; exact figures not testable yet. | D23: N/A | E23: Pending
A24: Out of Scope | B24: Partner Platform | C24: Third-party training platform vendor behavior — deferred until build-vs-buy decision is finalized. | D24: N/A | E24: Pending
A25: Other Modules
A26: Out of Scope | B26: Other Modules | C26: 9 remaining modules (CRM, etc.) — not yet assigned; will be added as requirements are provided. | D26: N/A | E26: Pending
A28: 📌 ASSUMPTIONS
A29: Category | B29: Module | C29: Description | D29: Owner | E29: Status
A30: All Modules
A31: Assumption | B31: All Modules | C31: This is a living document. New modules will be added as requirements are provided by the team. | D31: QA Team | E31: Active
A32: In Scope | B32: Partner Platform | C32: Requirement-phase automation mappings are placeholders; executable automation will be updated after requirements stabilize. | D32: QA Team | E32: Active
A33: Partner Platform
A34: Assumption | B34: Partner Platform | C34: All test statuses default to Not Started. Status logic: Fail if any = Fail; Pass if Manual = Pass and Automation = Pass/Not Started; else Not Started. | D34: QA Team | E34: Active
A35: Assumption | B35: Partner Platform | C35: Automation mapping IDs (e.g. tests/ui/partner_001) are placeholders — replace with real script paths when automation is implemented. | D35: QA Team | E35: Active
A36: Assumption | B36: Partner Platform | C36: partner.blazeup.ai (dogfood tenant) is the test target. Auth Phase 0 hooks/mocks are used for non-auth slices; live partner auth tested only after auth gate lands. | D36: Dev Team | E36: Active
A38: 🔑 ENTRY & EXIT CRITERIA
A39: Category | B39: Module | C39: Description | D39: Owner | E39: Status
A40: Partner Platform
A41: Entry Criteria | B41: Partner Platform | C41: PRD v1.8 is baselined and available to QA team. | D41: PM | E41: Active
A42: Entry Criteria | B42: Partner Platform | C42: Test environment is deployed: Partner Portal, SA Partner Module, ms-sa-partners, dogfood CRM bridge, tenant provisioning, billing, Kafka test topics. | D42: Dev Team | E42: Active
A43: Entry Criteria | B43: Partner Platform | C43: Seed data is ready: partners, deals, clients, commissions, sandbox profiles, conflict fixtures. | D43: Dev Team | E43: Active
A44: Entry Criteria | B44: Partner Platform | C44: Auth Phase 0 test hooks or mocks are available for non-auth test slices. | D44: Dev Team | E44: Active
A45: Exit Criteria | B45: Partner Platform | C45: All P1 test cases executed with zero unresolved Critical or Major release-blocking defects. | D45: QA Team | E45: Active
A46: Exit Criteria | B46: Partner Platform | C46: Requirement coverage = 100% for all active testable PRD sections. | D46: QA Team | E46: Active
A47: Exit Criteria | B47: Partner Platform | C47: Regression Suite P1 cases pass on the release candidate build. | D47: QA Team | E47: Active
A48: Exit Criteria | B48: Partner Platform | C48: Execution Log is updated with build version, executor, result, and defect references for all executed TCs. | D48: QA Team | E48: Active
